Workbook

Sheet Legend
A1: Contents and Legends
A3: 1 | B3: ='Supplementary Table 1'!A1 -> Supplementary Table 1. Genome-wide association study summary statistics included in this study and their use across genetic analyses.
A4: 2 | B4: ='Supplementary Table 2'!A1 -> Supplementary Table 2. Observed-scale SNP heritability estimated by LD-score regression for the GWAS datasets in the primary and replication analysis panels.
A5: 3 | B5: ='Supplementary Table 3'!A1 -> Supplementary Table 3. Cross-trait genetic correlations between two influenza GWAS definitions and the psychiatric disorder GWAS datasets in the primary and replication panels.
A6: 4 | B6: ='Supplementary Table 4'!A1 -> Supplementary Table 4. Bivariate MiXeR estimates of polygenic overlap between influenza and the psychiatric disorder GWAS datasets.
A7: 5 | B7: ='Supplementary Table 5'!A1 -> Supplementary Table 5. Model fit statistics for the genomic structural equation models relating influenza to the healthcare-contact and infection-specific factors.
A8: 6 | B8: ='Supplementary Table 6'!A1 -> Supplementary Table 6. Standardized indicator loadings and influenza structural coefficients in the orthogonal bifactor model (M2d).
A9: 7 | B9: ='Supplementary Table 7'!A1 -> Supplementary Table 7. Associations of psychiatric disorder outcomes with the general and infection-specific factors in the bifactor outcome model (M3b) and sensitivity excluding COVID-19 indicators.
A10: 8 | B10: ='Supplementary Table 8'!A1 -> Supplementary Table 8. Validity of the healthcare-contact and infection-specific factors assessed by genetic correlations with independent traits.
A11: 9 | B11: ='Supplementary Table 9'!A1 -> Supplementary Table 9. Attenuation of influenza-disorder genetic correlations after conditioning on healthcare-contact and psychological-distress covariates by multi-trait conditional and joint analysis.
A12: 10 | B12: ='Supplementary Table 10'!A1 -> Supplementary Table 10. Genome-wide significant loci of the influenza GWAS and their residual association signals after GWAS-by-subtraction conditioning.
A13: 11 | B13: ='Supplementary Table 11'!A1 -> Supplementary Table 11. Colocalization of the ST6GAL1 and B3GALT5 influenza GWAS loci with cis-eQTL and cis-pQTL across tissues and cell types.
A14: 12 | B14: ='Supplementary Table 12'!A1 -> Supplementary Table 12. SuSiE fine-mapped credible sets and brain chromatin annotations at the ST6GAL1 and B3GALT5 influenza loci.
A15: 13 | B15: ='Supplementary Table 13'!A1 -> Supplementary Table 13. Predicted enhancer-to-gene links at the ST6GAL1 and B3GALT5 influenza GWAS loci.
A16: 14 | B16: ='Supplementary Table 14'!A1 -> Supplementary Table 14. Single-nucleus ATAC-sequencing chromatin accessibility and accessibility-expression associations at the ST6GAL1 locus.
A17: 15 | B17: ='Supplementary Table 15'!A1 -> Supplementary Table 15. Summary-data-based Mendelian randomization of brain cell-type-specific ST6GAL1 and B3GALT5 expression on influenza and COVID-19.
A18: 16 | B18: ='Supplementary Table 16'!A1 -> Supplementary Table 16. Bidirectional two-sample Mendelian randomization between influenza and the psychiatric disorder GWAS datasets.
A19: 17 | B19: ='Supplementary Table 17'!A1 -> Supplementary Table 17. Bias-corrected Mendelian randomization of the effect of psychiatric disorders on influenza by MRlap.
A20: 18 | B20: ='Supplementary Table 18'!A1 -> Supplementary Table 18. Multivariable Mendelian randomization of substance-use traits on influenza and related outcomes.
A21: 19 | B21: ='Supplementary Table 19'!A1 -> Supplementary Table 19. Incident psychiatric diagnoses after influenza, upper respiratory tract infection and pneumonia in UK Biobank.
A22: 20 | B22: ='Supplementary Table 20'!A1 -> Supplementary Table 20. Smoking status, cigarette dose and self-reported recent flu, pneumonia or ear infection in NHANES 2005–2018.
A23: 21 | B23: ='Supplementary Table 21'!A1 -> Supplementary Table 21. Doctor-diagnosed depression, perceived stress, smoking and influenza vaccination in KNHANES 2016–2019.

Sheet Supplementary Table 1
A1: Supplementary Table 1. Genome-wide association study summary statistics included in this study and their use across genetic analyses.
A3: Trait | B3: GWAS accession | C3: URL | D3: Phenotype definition | E3: Panel | F3: Population | G3: Consortium or cohort | H3: Year | I3: N | J3: Cases | K3: Controls | L3: Publisher | M3: PMID | N3: DOI | O3: Analyses
A4: Influenza | B4: J10_INFLUENZA | C4: https://storage.googleapis.com/finngen-public-data-r12/summary_stats/release/finngen_R12_J10_INFLUENZA.gz | D4: Influenza | E4: Primary | F4: European | G4: FinnGen | H4: 2024 | I4: 427096 | J4: 11558 | K4: 415538 | L4: Nature | M4: 36653562 | N4: 10.1038/s41586-022-05473-8 | O4: LDSC, MiXeR, GenomicSEM, GWAS-by-subtraction, mtCOJO, 2SMR, MRlap, MVMR (primary), MVMR (GSCAN), MVMR (extended), coloc/SMR/SuSiE
A5: Influenza | B5: GCST90432107 | C5: https://www.ebi.ac.uk/gwas/studies/GCST90432107 | D5: Influenza | E5: Replication | F5: Multi-ancestry (86.0% European) | G5: AncestryDNA | H5: 2024 | I5: 294629 | J5: 18334 | K5: 276295 | L5: Nature Genetics | M5: 39103650 | N5: 10.1038/s41588-024-01844-1 | O5: LDSC, MiXeR, GWAS-by-subtraction, mtCOJO, 2SMR, MVMR (primary), MVMR (extended), coloc/SMR/SuSiE
A6: Alcohol dependence | B6: GCST90435890 | C6: https://www.ebi.ac.uk/gwas/studies/GCST90435890 | D6: Alcohol-related disorders (PheCode 317) | E6: Primary | F6: European | G6: UK Biobank | H6: 2018 | I6: 392277 | J6: 12922 | K6: 379355 | L6: Nature Genetics | M6: 30104761 | N6: 10.1038/s41588-018-0184-y | O6: LDSC, MiXeR, GenomicSEM, GWAS-by-subtraction, mtCOJO, 2SMR, MRlap, MVMR (primary), MVMR (extended)
A7: Alcohol dependence | B7: GCST90691955 | C7: https://www.ebi.ac.uk/gwas/studies/GCST90691955 | D7: Alcohol-related disorders (PheCode 317) | E7: Replication | F7: European | G7: UK Biobank | H7: 2025 | I7: 408116 | J7: 16070 | K7: 392046 | L7: Nature Genetics | M7: 40968291 | N7: 10.1038/s41588-025-02335-7 | O7: LDSC, MiXeR, mtCOJO, 2SMR, MRlap, MVMR (primary)
A8: Alzheimers disease | B8: GCST90449055 | C8: https://www.ebi.ac.uk/gwas/studies/GCST90449055 | D8: Alzheimer's disease (MTAG) | E8: Primary | F8: European | G8: PGC-ALZ, IGAP, ADSP, UK Biobank | H8: 2024 | I8: 455258 | J8: 71880 | K8: 383378 | L8: Nature Communications | M8: 39537608 | N8: 10.1038/s41467-024-53452-6 | O8: LDSC, MiXeR, GenomicSEM, GWAS-by-subtraction, mtCOJO, 2SMR, MRlap
A9: Alzheimers disease | B9: GCST90027158 | C9: https://www.ebi.ac.uk/gwas/studies/GCST90027158 | D9: Alzheimer's disease | E9: Replication | F9: European | G9: EADB | H9: 2022 | I9: 487511 | J9: 85934 | K9: 401577 | L9: Nature Genetics | M9: 35379992 | N9: 10.1038/s41588-022-01024-z | O9: LDSC, MiXeR, mtCOJO, 2SMR, MRlap
A10: Anorexia nervosa | B10: an_be2026 | C10: https://figshare.com/articles/dataset/an_be2026/32588628 | D10: Anorexia nervosa | E10: Primary | F10: European | G10: PGC-ED, Estonian Biobank (EstBB) | H10: 2025 | I10: 1268194 | J10: 24223 | K10: 1243971 | L10: Nature Mental Health | M10: 40385383 | N10: 10.1101/2025.01.31.25321397 | O10: LDSC, MiXeR, GenomicSEM, GWAS-by-subtraction, mtCOJO, 2SMR, MRlap
A11: Anorexia nervosa | B11: an2019 | C11: https://figshare.com/articles/dataset/an2019/14671980 | D11: Anorexia nervosa | E11: Replication | F11: European | G11: PGC-ED | H11: 2019 | I11: 72517 | J11: 16992 | K11: 55525 | L11: The American Journal of Psychiatry | M11: 31308545 | N11: 10.1038/s41588-019-0439-2 | O11: LDSC, MiXeR, mtCOJO, 2SMR, MRlap
A12: Anxiety disorder | B12: anx2026 | C12: https://figshare.com/articles/dataset/anx2026/31389910 | D12: Anxiety disorder | E12: Primary | F12: European | G12: PGC, 23andMe, Million Veteran Program (MVP), FinnGen, UK Biobank, iPSYCH | H12: 2026 | I12: 852222 | J12: 122341 | K12: 729881 | L12: Nature Genetics | M12: 41634414 | N12: 10.1038/s41588-025-02485-8 | O12: LDSC, MiXeR, GenomicSEM, GWAS-by-subtraction, mtCOJO, 2SMR, MRlap
A13: Anxiety disorder | B13: GCST90225527 | C13: https://www.ebi.ac.uk/gwas/studies/GCST90225527 | D13: ICD10 F41.9: Anxiety disorder, unspecified | E13: Replication | F13: European | G13: UK Biobank | H13: 2023 | I13: 502477 | J13: 16079 | K13: 486398 | L13: Genes, Brain, and Behavior | M13: 37259642 | N13: 10.1111/gbb.12851 | O13: LDSC, MiXeR, mtCOJO, 2SMR, MRlap
A14: Attention deficit hyperactivity disorder | B14: ADHD2022 | C14: https://doi.org/10.6084/m9.figshare.22564390 | D14: Attention deficit hyperactivity disorder | E14: Primary | F14: European | G14: PGC, iPSYCH, deCODE | H14: 2023 | I14: 225534 | J14: 38691 | K14: 186843 | L14: Nature Genetics | M14: 36702997 | N14: 10.1038/s41588-022-01285-8 | O14: LDSC, MiXeR, GenomicSEM, GWAS-by-subtraction, mtCOJO, 2SMR, MRlap
A15: Attention deficit hyperactivity disorder | B15: GCST90275147 | C15: https://www.ebi.ac.uk/gwas/studies/GCST90275147 | D15: Attention deficit hyperactivity disorder (adjusted for age, sex) | E15: Replication | F15: European | G15: iPSYCH | H15: 2023 | I15: 58286 | J15: 21738 | K15: 36548 | L15: Nature Communications | M15: 37689771 | N15: 10.1038/s41467-023-41210-z | O15: LDSC, MiXeR, mtCOJO, 2SMR, MRlap
... A39: Angina pectoris | B39: GCST90018793 | C39: https://www.ebi.ac.uk/gwas/studies/GCST90018793 | D39: Angina pectoris | E39: Other | F39: European | G39: UK Biobank | H39: 2021 | I39: 470931 | J39: 30025 | K39: 440906 | L39: Nature Genetics | M39: 34594039 | N39: 10.1038/s41588-021-00931-x | O39: GenomicSEM, GWAS-by-subtraction
A40: Annual healthcare cost | B40: GCST90292604 | C40: https://www.ebi.ac.uk/gwas/studies/GCST90292604 | D40: Annual healthcare cost | E40: Other | F40: European | G40: FinnGen | H40: 2023 | I40: 373160 | J40: NA | K40: NA | L40: Nature Communications | M40: 37704630 | N40: 10.1038/s41467-023-41394-4 | O40: GenomicSEM, GWAS-by-subtraction, mtCOJO, MVMR (primary)
A41: Asthma | B41: GCST008916 | C41: https://www.ebi.ac.uk/gwas/studies/GCST008916 | D41: Asthma | E41: Other | F41: European | G41: UK Biobank | H41: 2019 | I41: 394283 | J41: 46802 | K41: 347481 | L41: European Respiratory Journal | M41: 31619474 | N41: 10.1038/s41588-018-0121-6 | O41: MVMR (primary)
A42: Asthma | B42: GCST90652530 | C42: https://www.ebi.ac.uk/gwas/studies/GCST90652530 | D42: Asthma | E42: Other | F42: European | G42: FinnGen, UK Biobank | H42: 2025 | I42: 757083 | J42: 71481 | K42: 685602 | L42: Nature Communications | M42: 41213931 | N42: 10.1038/s41467-025-64847-4 | O42: GenomicSEM, GWAS-by-subtraction
A43: Body mass index | B43: GCST009004 | C43: https://www.ebi.ac.uk/gwas/studies/GCST009004 | D43: Body mass index | E43: Other | F43: European | G43: GIANT, UK Biobank | H43: 2018 | I43: 806834 | J43: NA | K43: NA | L43: Human Molecular Genetics | M43: 30239722 | N43: 10.1093/hmg/ddy271 | O43: GenomicSEM, GWAS-by-subtraction, MVMR (primary), MVMR (GSCAN), MVMR (extended)
A44: Chronic obstructive pulmonary disease | B44: GCST90399694 | C44: https://www.ebi.ac.uk/gwas/studies/GCST90399694 | D44: Chronic obstructive pulmonary disease | E44: Other | F44: European | G44: Global Biobank Meta-analysis Initiative (GBMI) | H44: 2022 | I44: 995917 | J44: 58559 | K44: 937358 | L44: Cell Genomics | M44: 36777996 | N44: 10.1016/j.xgen.2022.100192 | O44: GenomicSEM, GWAS-by-subtraction
A45: Cigarettes per day | B45: ieu-b-25 | C45: https://opengwas.io/datasets/ieu-b-25 | D45: Cigarettes per Day | E45: Other | F45: European | G45: GWAS and Sequencing Consortium of Alcohol and Nicotine Use (GSCAN) | H45: 2019 | I45: 337334 | J45: NA | K45: NA | L45: Nature Genetics | M45: 30643251 | N45: 10.1038/s41588-019-0527-0 | O45: MVMR (GSCAN)
A46: Coronary artery disease | B46: GCST90132314 | C46: https://www.ebi.ac.uk/gwas/studies/GCST90132314 | D46: Coronary artery disease | E46: Other | F46: European | G46: CARDIoGRAMplusC4D | H46: 2022 | I46: 1165690 | J46: 181522 | K46: 984168 | L46: Nature Genetics | M46: 36474045 | N46: 10.1038/s41588-022-01233-6 | O46: GenomicSEM, GWAS-by-subtraction
A47: COVID-19 | B47: GCST011073 | C47: https://www.ebi.ac.uk/gwas/studies/GCST011073 | D47: COVID-19 (RELEASE 5) | E47: Other | F47: European | G47: COVID-19 Host Genetics Initiative (HGI) | H47: 2020 | I47: 1683768 | J47: 38984 | K47: 1644784 | L47: European Journal of Human Genetics | M47: 32404885 | N47: 10.1038/s41431-020-0636-6 | O47: GenomicSEM, GWAS-by-subtraction
A48: COVID-19 | B48: GCST011081 | C48: https://www.ebi.ac.uk/gwas/studies/GCST011081 | D48: COVID-19 (hospitalized vs population) RELEASE 5 | E48: Other | F48: European | G48: COVID-19 Host Genetics Initiative (HGI) | H48: 2020 | I48: 1887658 | J48: 9986 | K48: 1877672 | L48: European Journal of Human Genetics | M48: 32404885 | N48: 10.1038/s41431-020-0636-6 | O48: GenomicSEM, GWAS-by-subtraction, MVMR (extended)
A49: COVID-19 | B49: GCST90013414 | C49: https://www.ebi.ac.uk/gwas/studies/GCST90013414 | D49: COVID-19 (critical illness vs population) | E49: Other | F49: European | G49: GenOMICC | H49: 2020 | I49: 10056 | J49: 1676 | K49: 8380 | L49: Nature | M49: 33307546 | N49: 10.1038/s41586-020-2725-y | O49: MVMR (extended)
A50: COVID-19 | B50: COVID19_HGI_B2 | C50: https://www.covid19hg.org/results/r5/ | D50: COVID-19 | E50: Other | F50: European | G50: COVID-19 Host Genetics Initiative (HGI) | H50: 2020 | I50: 2062805 | J50: 32519 | K50: 2030286 | L50: European Journal of Human Genetics | M50: 32404885 | N50: 10.1038/s41431-020-0636-6 | O50: MVMR (GSCAN), coloc/SMR/SuSiE
A51: C-reactive protein levels | B51: GCST90029070 | C51: https://www.ebi.ac.uk/gwas/studies/GCST90029070 | D51: C-reactive protein levels | E51: Other | F51: European | G51: UK Biobank, CHARGE | H51: 2022 | I51: 575531 | J51: NA | K51: NA | L51: Nature Communications | M51: 35459240 | N51: 10.1038/s41467-022-29688-5 | O51: GenomicSEM, GWAS-by-subtraction
A52: Educational attainment | B52: GCST90566697 | C52: https://www.ebi.ac.uk/gwas/studies/GCST90566697 | D52: Educational attainment (MTAG) | E52: Other | F52: European | G52: UK Biobank, Social Science Genetic Association Consortium (SSGAC) | H52: 2025 | I52: 848919 | J52: NA | K52: NA | L52: Molecular Psychiatry | M52: 40360725 | N52: 10.1038/s41380-025-03047-4 | O52: GenomicSEM, GWAS-by-subtraction, MVMR (primary), MVMR (GSCAN), MVMR (extended)
A53: Psychiatric-specialist help-seeking | B53: GCST90042862 | C53: https://www.ebi.ac.uk/gwas/studies/GCST90042862 | D53: Seen psychiatrist for nerves anxiety tension or depression (UKB data field 2100) | E53: Other | F53: European | G53: UK Biobank | H53: 2021 | I53: 454181 | J53: 52417 | K53: 401764 | L53: Nature Genetics | M53: 34737426 | N53: 10.1038/s41588-021-00954-4 | O53: GenomicSEM, GWAS-by-subtraction, mtCOJO
A54: Hospital contact for infections | B54: GCST90270866 | C54: https://www.ebi.ac.uk/gwas/studies/GCST90270866 | D54: Any infection (hospital admission) | E54: Other | F54: European | G54: UK Biobank | H54: 2023 | I54: 700649 | J54: 123508 | K54: 577141 | L54: International Journal of Epidemiology | M54: 36773317 | N54: 10.1093/ije/dyad010 | O54: MVMR (extended)
A55: Hypertension | B55: GCST90038604 | C55: https://www.ebi.ac.uk/gwas/studies/GCST90038604 | D55: Hypertension | E55: Other | F55: European | G55: UK Biobank | H55: 2021 | I55: 484598 | J55: 129909 | K55: 354689 | L55: Nature Aging | M55: 33959723 | N55: 10.1038/s43587-021-00051-5 | O55: GenomicSEM, GWAS-by-subtraction
A56: Influenza and pneumonia | B56: J10_INFLUPNEU | C56: https://storage.googleapis.com/finngen-public-data-r12/summary_stats/release/finngen_R12_J10_INFLUPNEU.gz | D56: Influenza and pneumonia | E56: Other | F56: European | G56: FinnGen | H56: 2024 | I56: 500348 | J56: 84810 | K56: 415538 | L56: Nature | M56: 36653562 | N56: 10.1038/s41586-022-05473-8 | O56: MVMR (primary), MVMR (GSCAN)
A57: Influenza and pneumonia | B57: GCST90473653 | C57: https://www.ebi.ac.uk/gwas/studies/GCST90473653 | D57: ICD10 J09-J18: Influenza and pneumonia | E57: Other | F57: European | G57: UK Biobank Whole-Genome Sequencing Consortium | H57: 2025 | I57: 458440 | J57: 49930 | K57: 408510 | L57: Nature | M57: 40770095 | N57: 10.1038/s41586-025-09272-9 | O57: MVMR (extended)
A58: Ischemic stroke | B58: GCST90104540 | C58: https://www.ebi.ac.uk/gwas/studies/GCST90104540 | D58: Ischemic stroke | E58: Other | F58: European | G58: MEGASTROKE | H58: 2022 | I58: 1296908 | J58: 62100 | K58: 1234808 | L58: Nature | M58: 36180795 | N58: 10.1038/s41586-022-05165-3 | O58: GenomicSEM, GWAS-by-subtraction
A59: Myocardial infarction | B59: GCST90038610 | C59: https://www.ebi.ac.uk/gwas/studies/GCST90038610 | D59: Myocardial infarction | E59: Other | F59: European | G59: UK Biobank | H59: 2021 | I59: 484598 | J59: 11081 | K59: 473517 | L59: Nature Aging | M59: 33959723 | N59: 10.1038/s43587-021-00051-5 | O59: GenomicSEM, GWAS-by-subtraction
A60: Neutrophil count | B60: ieu-b-34 | C60: https://opengwas.io/datasets/ieu-b-34 | D60: neutrophil cell count | E60: Other | F60: European | G60: Blood Cell Consortium | H60: 2020 | I60: 563946 | J60: NA | K60: NA | L60: Cell | M60: 32888493 | N60: 10.1016/j.cell.2020.06.045 | O60: MVMR (primary)
A61: Number of illnesses | B61: GCST90691745 | C61: https://www.ebi.ac.uk/gwas/studies/GCST90691745 | D61: Number of self-reported non-cancer illnesses (UKB data field 135) | E61: Other | F61: European | G61: UK Biobank | H61: 2025 | I61: 420473 | J61: NA | K61: NA | L61: Nature Genetics | M61: 40968291 | N61: 10.1038/s41588-025-02335-7 | O61: GenomicSEM, GWAS-by-subtraction, mtCOJO
A62: Pneumonia | B62: ieu-b-4976 | C62: https://opengwas.io/datasets/ieu-b-4976 | D62: Pneumonia | E62: Other | F62: European | G62: UK Biobank | H62: 2021 | I62: 486484 | J62: 22567 | K62: 463917 | L62: Nature | M62: 30305743 | N62: 10.1038/s41586-018-0579-z | O62: MVMR (primary)
A63: Pneumonia | B63: GCST90624053 | C63: https://www.ebi.ac.uk/gwas/studies/GCST90624053 | D63: Pneumonia | E63: Other | F63: European | G63: UK Biobank | H63: 2025 | I63: 832234 | J63: 77431 | K63: 754803 | L63: Nature Genetics | M63: 40759756 | N63: 10.1038/s41588-025-02269-0 | O63: GenomicSEM, GWAS-by-subtraction, MVMR (extended)
A64: Pneumonia | B64: GCST90270869 | C64: https://www.ebi.ac.uk/gwas/studies/GCST90270869 | D64: Pneumonia (hospital admission) | E64: Other | F64: European | G64: UK Biobank | H64: 2023 | I64: 700649 | J64: 55241 | K64: 645408 | L64: International Journal of Epidemiology | M64: 36773317 | N64: 10.1093/ije/dyad010 | O64: MVMR (extended)
A65: Pneumonia | B65: J10_PNEUMONIA | C65: https://storage.googleapis.com/finngen-public-data-r12/summary_stats/release/finngen_R12_J10_PNEUMONIA.gz | D65: Pneumonia | E65: Other | F65: European | G65: FinnGen | H65: 2024 | I65: 500348 | J65: 78791 | K65: 421557 | L65: Nature | M65: 36653562 | N65: 10.1038/s41586-022-05473-8 | O65: MVMR (GSCAN)
A66: Smoking initiation | B66: ieu-b-4877 | C66: https://opengwas.io/datasets/ieu-b-4877 | D66: smoking initiation | E66: Other | F66: European | G66: GWAS and Sequencing Consortium of Alcohol and Nicotine Use (GSCAN) | H66: 2019 | I66: 311629 | J66: NA | K66: NA | L66: Nature Genetics | M66: 30643251 | N66: 10.1038/s41588-019-0527-0 | O66: MVMR (GSCAN)
A67: Smoking status | B67: GCST007327 | C67: https://www.ebi.ac.uk/gwas/studies/GCST007327 | D67: Smoking status (ever vs never smokers) | E67: Other | F67: European | G67: Social Science Genetic Association Consortium (SSGAC) | H67: 2019 | I67: 518633 | J67: NA | K67: NA | L67: Nature Genetics | M67: 30643258 | N67: 10.1038/s41588-019-0409-3 | O67: GenomicSEM, GWAS-by-subtraction, MVMR (primary)
A68: Tobacco use disorder | B68: GCST90691956 | C68: https://www.ebi.ac.uk/gwas/studies/GCST90691956 | D68: Tobacco use disorder (PheCode 318) | E68: Other | F68: European | G68: UK Biobank | H68: 2025 | I68: 407034 | J68: 14988 | K68: 392046 | L68: Nature Genetics | M68: 40968291 | N68: 10.1038/s41588-025-02335-7 | O68: MVMR (primary)
A69: Type 2 diabetes | B69: GCST90029024 | C69: https://www.ebi.ac.uk/gwas/studies/GCST90029024 | D69: Type 2 diabetes | E69: Other | F69: European | G69: UK Biobank | H69: 2018 | I69: 468298 | J69: NA | K69: NA | L69: Nature Genetics | M69: 29892013 | N69: 10.1038/s41588-018-0054-x | O69: GenomicSEM, GWAS-by-subtraction
A70: Upper respiratory tract infection | B70: GCST90281181 | C70: https://www.ebi.ac.uk/gwas/studies/GCST90281181 | D70: Upper respiratory tract infection | E70: Other | F70: European | G70: UK Biobank | H70: 2023 | I70: 486484 | J70: 2795 | K70: 483689 | L70: PloS Medicine | M70: 36716318 | N70: 10.1371/journal.pmed.1004174 | O70: GenomicSEM, GWAS-by-subtraction
A71: Upper respiratory tract infection | B71: GCST90473682 | C71: https://www.ebi.ac.uk/gwas/studies/GCST90473682 | D71: Other diseases of upper respiratory tract | E71: Other | F71: European | G71: UK Biobank Whole-Genome Sequencing Consortium | H71: 2025 | I71: 458440 | J71: 80634 | K71: 377806 | L71: Nature | M71: 40770095 | N71: 10.1038/s41586-025-09272-9 | O71: GenomicSEM, GWAS-by-subtraction
A73: Note: This table catalogues every GWAS summary statistics dataset used in this study. Panel indicates the role of each dataset: Primary, main analysis panel (European-ancestry psychiatric and neurodevelopmental disorder GWAS); Replication, alternative GWAS panel (not necessarily independent); Other, datasets outside the two panels that entered specific analyses as covariates, comparator or negative-control outcomes. Two influenza phenotype definitions were used as the exposure: J10_INFLUENZA (FinnGen, ICD-10 code J10; primary) and GCST90432107 (Kosmicki et al.; replication). The Analyses column lists the frameworks each dataset entered: LDSC, LD-score regression; MiXeR, polygenic mixture-model overlap; GenomicSEM, genomic structural equation modelling; GWAS-by-subtraction, residual influenza GWAS after removing genetic components of psychiatric and control traits; mtCOJO, multi-trait conditional and joint analysis conditioning the influenza GWAS on healthcare-contact and distress covariates; 2SMR, two-sample Mendelian randomization; MRlap, Mendelian randomization corrected for latent heritable confounding and sample overlap; MVMR, multivariable Mendelian randomization (primary models, GSCAN smoking phenotypes, and extended infectious-disease outcomes); coloc/SMR/SuSiE, colocalization, summary-data-based Mendelian randomization and sum-of-single-effects fine-mapping at the ST6GAL1 and B3GALT5 loci. Sample size (N), cases and controls are as reported by the source study. NA, not reported or not applicable. Abbreviations: GWAS, genome-wide association study; ICD, International Classification of Diseases; SMR, summary-data-based Mendelian randomization; SuSiE, sum of single effects.

Sheet Supplementary Table 2
A1: Supplementary Table 2. Observed-scale SNP heritability estimated by LD-score regression for the GWAS datasets in the primary and replication analysis panels.
A3: Trait | B3: GWAS accession | C3: Panel | D3: SNP h2 | E3: SE | F3: h2 z | G3: LDSC intercept | H3: Intercept SE | I3: Lambda-GC | J3: QC passed (z > 4)
A4: Influenza | B4: J10_INFLUENZA | C4: Primary | D4: 0.0624 | E4: 0.013 | F4: 4.8 | G4: 1.0091 | H4: 0.0079 | I4: 1.0618 | J4: Yes
A5: Alcohol dependence | B5: GCST90435890 | C5: Primary | D5: 0.0819 | E5: 0.0103 | F5: 7.9514563 | G5: 1.0147 | H5: 0.0065 | I5: 1.0802 | J5: Yes
A6: Alzheimer's disease | B6: GCST90449055 | C6: Primary | D6: 0.0525 | E6: 0.0036 | F6: 14.583333 | G6: 0.7885 | H6: 0.0122 | I6: 0.9489 | J6: Yes
A7: Anorexia nervosa | B7: an_be2026 | C7: Primary | D7: 0.1591 | E7: 0.0092 | F7: 17.293478 | G7: 1.0216 | H7: 0.0083 | I7: 1.2597 | J7: Yes
A8: Anxiety disorder | B8: anx2026 | C8: Primary | D8: 0.07 | E8: 0.0026 | F8: 26.923077 | G8: 1.0408 | H8: 0.009 | I8: 1.4853 | J8: Yes
A9: Attention-deficit/hyperactivity disorder | B9: ADHD2022 | C9: Primary | D9: 0.164 | E9: 0.0076 | F9: 21.578947 | G9: 1.0314 | H9: 0.0092 | I9: 1.3546 | J9: Yes
A10: Autism spectrum disorder | B10: asd2019 | C10: Primary | D10: 0.2118 | E10: 0.0158 | F10: 13.405063 | G10: 0.9992 | H10: 0.0079 | I10: 1.1619 | J10: Yes
A11: Bipolar disorder | B11: ieu-b-5110 | C11: Primary | D11: 0.1948 | E11: 0.0071 | F11: 27.43662 | G11: 1.0191 | H11: 0.0088 | I11: 1.4459 | J11: Yes
A12: Major depressive disorder | B12: GCST005839 | C12: Primary | D12: 0.0338 | E12: 0.0022 | F12: 15.363636 | G12: 0.9901 | H12: 0.0096 | I12: 1.2267 | J12: Yes
A13: Obsessive-compulsive disorder | B13: ieu-a-1189 | C13: Primary | D13: 0.146 | E13: 0.02 | F13: 7.3 | G13: 0.9906 | H13: 0.0065 | I13: 1.0496 | J13: Yes
A14: Opiate dependence | B14: GCST90018994 | C14: Primary | D14: 0.1666 | E14: 0.0093 | F14: 17.913978 | G14: 1.0081 | H14: 0.0075 | I14: 1.2005 | J14: Yes
A15: Parkinson's disease | B15: GCST009324 | C15: Primary | D15: 0.2186 | E15: 0.0208 | F15: 10.509615 | G15: 0.9733 | H15: 0.0065 | I15: 1.0649 | J15: Yes
... A38: Tobacco use disorder | B38: GCST90693050 | C38: Replication | D38: 0.1496 | E38: 0.0116 | F38: 12.896552 | G38: 1.0088 | H38: 0.007 | I38: 1.1555 | J38: Yes
A40: Note: SNP heritability (h2) on the observed scale was estimated for each GWAS dataset by LD-score regression using HapMap3 SNPs and a European linkage disequilibrium reference panel. The heritability z statistic is h2 divided by its standard error; QC passed indicates z > 4, the conventional threshold for sufficient polygenic signal precision. Lambda-GC is the genomic control inflation factor of the summary statistics, and the LDSC intercept estimates inflation from population stratification and cryptic relatedness, with values near 1 indicating minimal confounding. The two influenza phenotype definitions are J10_INFLUENZA (FinnGen, ICD-10 code J10; primary exposure) and GCST90432107 (Kosmicki et al.; replication exposure). GCST90432107 was a multi-ancestry meta-analysis (86.0% European ancestry); all other datasets in this table were European-ancestry GWAS. NA, not applicable. Abbreviations: GWAS, genome-wide association study; LD, linkage disequilibrium; LDSC, LD-score regression; SE, standard error.

Sheet Supplementary Table 3
A1: Supplementary Table 3. Cross-trait genetic correlations between two influenza GWAS definitions and the psychiatric disorder GWAS datasets in the primary and replication panels.
A3: Influenza GWAS | B3: Trait | C3: GWAS accession | D3: Panel | E3: rg | F3: SE | G3: z | H3: P | I3: FDR | J3: gcov intercept
A4: J10_INFLUENZA | B4: Alcohol dependence | C4: GCST90435890 | D4: Primary | E4: 0.3026 | F4: 0.1022 | G4: 2.9608611 | H4: 0.003067803 | I4: 0.005061875 | J4: 0.0006
A5: J10_INFLUENZA | B5: Alzheimer's disease | C5: GCST90449055 | D5: Primary | E5: 0.0799 | F5: 0.0809 | G5: 0.98763906 | H5: 0.32332945 | I5: 0.39518044 | J5: 0.0015
A6: J10_INFLUENZA | B6: Anorexia nervosa | C6: an_be2026 | D6: Primary | E6: 0.1046 | F6: 0.0636 | G6: 1.6446541 | H6: 0.10004117 | I6: 0.14353732 | J6: -0.0003
A7: J10_INFLUENZA | B7: Anxiety disorder | C7: anx2026 | D7: Primary | E7: 0.3671 | F7: 0.0605 | G7: 6.0677686 | H7: 1.296996e-09 | I7: 2.1400433e-08 | J7: 0.0031
A8: J10_INFLUENZA | B8: Attention-deficit/hyperactivity disorder | C8: ADHD2022 | D8: Primary | E8: 0.3142 | F8: 0.062 | G8: 5.0677419 | H8: 4.0256267e-07 | I8: 4.4281894e-06 | J8: -0.0026
A9: J10_INFLUENZA | B9: Autism spectrum disorder | C9: asd2019 | D9: Primary | E9: -0.0329 | F9: 0.1068 | G9: -0.30805243 | H9: 0.75804243 | I9: 0.8069484 | J9: 0.0015
A10: J10_INFLUENZA | B10: Bipolar disorder | C10: ieu-b-5110 | D10: Primary | E10: 0.1817 | F10: 0.0499 | G10: 3.6412826 | H10: 0.00027128319 | I10: 0.00052660854 | J10: 0.0015
A11: J10_INFLUENZA | B11: Major depressive disorder | C11: GCST005839 | D11: Primary | E11: 0.3348 | F11: 0.0772 | G11: 4.3367876 | H11: 1.4458024e-05 | I11: 6.8159254e-05 | J11: -0.0007
A12: J10_INFLUENZA | B12: Obsessive-compulsive disorder | C12: ieu-a-1189 | D12: Primary | E12: 0.0778 | F12: 0.1074 | G12: 0.72439479 | H12: 0.4688234 | I12: 0.5334887 | J12: -0.0044
A13: J10_INFLUENZA | B13: Opiate dependence | C13: GCST90018994 | D13: Primary | E13: 0.4199 | F13: 0.0846 | G13: 4.963357 | H13: 6.9285068e-07 | I13: 5.7160181e-06 | J13: -0.0061
A14: J10_INFLUENZA | B14: Parkinson's disease | C14: GCST009324 | D14: Primary | E14: -0.0408 | F14: 0.0917 | G14: -0.44492912 | H14: 0.65637098 | I14: 0.72200808 | J14: -0.0005
A15: J10_INFLUENZA | B15: Post-traumatic stress disorder | C15: ptsd2024 | D15: Primary | E15: 0.4321 | F15: 0.0579 | G15: 7.462867 | H15: 8.4659786e-14 | I15: 2.7937729e-12 | J15: 0.0056
... A69: GCST90432107 | B69: Tobacco use disorder | C69: GCST90693050 | D69: Replication | E69: 0.4729 | F69: 0.0785 | G69: 6.0242038 | H69: 1.699441e-09 | I69: 7.7708388e-09 | J69: 0.002
A71: Note: Genetic correlations (rg) between each influenza GWAS and each disorder GWAS were estimated by cross-trait LD-score regression using HapMap3 SNPs and a European linkage disequilibrium reference panel; rg is on the observed scale. The influenza exposures are J10_INFLUENZA (FinnGen, ICD-10 code J10; primary) and GCST90432107 (Kosmicki et al.; replication). P values are two-sided, derived from z = rg / SE under a standard normal distribution; FDR was computed by the Benjamini-Hochberg procedure within each exposure panel. The gcov intercept is the cross-trait LD-score regression intercept, which estimates genetic covariance attributable to sample overlap and shared stratification; values near 0 indicate negligible overlap. GCST90432107 was a multi-ancestry meta-analysis (86.0% European ancestry); all other datasets in this table were European-ancestry GWAS. NA, not applicable. Abbreviations: FDR, false discovery rate; GWAS, genome-wide association study; LD, linkage disequilibrium; SE, standard error.

Sheet Supplementary Table 4
A1: Supplementary Table 4. Bivariate MiXeR estimates of polygenic overlap between influenza and the psychiatric disorder GWAS datasets.
A3: Influenza GWAS accession | B3: Disorder GWAS accession | C3: Trait | D3: Panel | E3: Influenza h2 (mean) | F3: Influenza h2 (SD) | G3: Trait h2 (mean) | H3: Trait h2 (SD) | I3: rg (mean) | J3: rg (SD) | K3: Influenza-specific SNPs (mean) | L3: Influenza-specific SNPs (SD) | M3: Trait-specific SNPs (mean) | N3: Trait-specific SNPs (SD) | O3: Shared SNPs (mean) | P3: Shared SNPs (SD) | Q3: Dice (mean) | R3: Dice (SD) | S3: Delta AIC | T3: Delta BIC
A4: J10_INFLUENZA | B4: GCST90435890 | C4: Alcohol dependence | D4: Primary | E4: 0.052874518 | F4: 0.0046433326 | G4: 0.059897225 | H4: 0.0041597496 | I4: 0.20100413 | J4: 0.056767823 | K4: 2424.6992 | L4: 2034.2698 | M4: 2434.4049 | N4: 1148.7499 | O4: 948.63954 | P4: 679.43815 | Q4: 0.27393831 | R4: 0.10488079 | S4: -1.6838247 | T4: -11.235
A5: J10_INFLUENZA | B5: GCST90449055 | C5: Alzheimers disease | D5: Primary | E5: 0.052874518 | F5: 0.0046433326 | G5: 0.041348499 | H5: 0.00090125982 | I5: 0.12886964 | J5: 0.025305075 | K5: 3027.1529 | L5: 2514.0884 | M5: 239.17884 | N5: 166.3654 | O5: 346.18586 | P5: 208.10178 | Q5: 0.19970575 | R5: 0.14222046 | S5: 4.4931452 | T5: -4.9073034
A6: J10_INFLUENZA | B6: an_be2026 | C6: Anorexia nervosa | D6: Primary | E6: 0.052874518 | F6: 0.0046433326 | G6: 0.14805551 | H6: 0.0027897355 | I6: 0.068853164 | J6: 0.018139628 | K6: 2232.6878 | L6: 2216.371 | M6: 7373.3379 | N6: 1050.782 | O6: 1140.651 | P6: 926.93699 | Q6: 0.18480044 | R6: 0.13918914 | S6: -1.3557784 | T6: -10.86713
A7: J10_INFLUENZA | B7: anx2026 | C7: Anxiety disorder | D7: Primary | E7: 0.052874518 | F7: 0.0046433326 | G7: 0.067096211 | H7: 0.00066762428 | I7: 0.38990655 | J7: 0.033198884 | K7: 592.05667 | L7: 1581.2093 | M7: 9505.9287 | N7: 1027.0459 | O7: 2781.2821 | P7: 1130.1627 | Q7: 0.34497923 | R7: 0.085227248 | S7: -1.1484202 | T7: -10.685791
A8: J10_INFLUENZA | B8: ADHD2022 | C8: Attention deficit hyperactivity disorder | D8: Primary | E8: 0.052874518 | F8: 0.0046433326 | G8: 0.1514269 | H8: 0.0033840202 | I8: 0.37440314 | J8: 0.025937938 | K8: 1264.7696 | L8: 1722.957 | M8: 5611.0848 | N8: 838.21956 | O8: 2108.5692 | P8: 923.3987 | Q8: 0.37061241 | R8: 0.075065189 | S8: -1.1768095 | T8: -10.549154
A9: J10_INFLUENZA | B9: asd2019 | C9: Autism spectrum disorder | D9: Primary | E9: 0.052874518 | F9: 0.0046433326 | G9: 0.19463373 | H9: 0.0052299281 | I9: -0.056819652 | J9: 0.023476076 | K9: 1010.6942 | L9: 811.17732 | M9: 9593.5591 | N9: 2956.5453 | O9: 2362.6445 | P9: 2390.1386 | Q9: 0.27965236 | R9: 0.21337818 | S9: -1.4623897 | T9: -10.949829
A10: J10_INFLUENZA | B10: ieu-b-5110 | C10: Bipolar disorder | D10: Primary | E10: 0.052874518 | F10: 0.0046433326 | G10: 0.187285 | H10: 0.0021979474 | I10: 0.26115667 | J10: 0.027749223 | K10: 1815.1699 | L10: 2108.2409 | M10: 7056.8534 | N10: 645.67875 | O10: 1558.1689 | P10: 505.40892 | Q10: 0.25685915 | R10: 0.04296314 | S10: -0.8378458 | T10: -10.359941
A11: J10_INFLUENZA | B11: GCST005839 | C11: Major depressive disorder | D11: Primary | E11: 0.052874518 | F11: 0.0046433326 | G11: 0.031408538 | H11: 0.00084550407 | I11: 0.30992875 | J11: 0.042841065 | K11: 177.72063 | L11: 575.2936 | M11: 21892.046 | N11: 4384.4994 | O11: 3195.6181 | P11: 2062.4054 | Q11: 0.21690822 | R11: 0.10330248 | S11: -1.7918888 | T11: -10.983029
A12: J10_INFLUENZA | B12: ieu-a-1189 | C12: Obsessive-compulsive disorder | D12: Primary | E12: 0.052874518 | F12: 0.0046433326 | G12: 0.11942901 | H12: 0.0071467991 | I12: -0.072590701 | J12: 0.047635805 | K12: 3067.385 | L12: 2418.8001 | M12: 2035.201 | N12: 651.48299 | O12: 305.95372 | P12: 224.62313 | Q12: 0.10595297 | R12: 0.058445325 | S12: -1.7083912 | T12: -11.234456
A13: J10_INFLUENZA | B13: GCST90018994 | C13: Opiate dependence | D13: Primary | E13: 0.052874518 | F13: 0.0046433326 | G13: 0.12785227 | H13: 0.0028109719 | I13: 0.4142813 | J13: 0.032501251 | K13: 1012.8719 | L13: 1819.2663 | M13: 6927.7543 | N13: 1428.5173 | O13: 2360.4669 | P13: 810.10285 | Q13: 0.36777642 | R13: 0.068249337 | S13: -1.6577815 | T13: -11.172821
A14: J10_INFLUENZA | B14: GCST009324 | C14: Parkinson disease | D14: Primary | E14: 0.052874518 | F14: 0.0046433326 | G14: 0.1499347 | H14: 0.0090327801 | I14: -0.10160679 | J14: 0.040876153 | K14: 3006.2955 | L14: 2429.6749 | M14: 265.96649 | N14: 232.14509 | O14: 367.04329 | P14: 214.14279 | Q14: 0.19243272 | R14: 0.092654817 | S14: -0.67522947 | T14: -10.225815
A15: J10_INFLUENZA | B15: ptsd2024 | C15: Post traumatic stress disorder | D15: Primary | E15: 0.052874518 | F15: 0.0046433326 | G15: 0.067697857 | H15: 0.00097928468 | I15: 0.45246657 | J15: 0.042546694 | K15: 348.6093 | L15: 1198.9191 | M15: 7826.908 | N15: 1507.5575 | O15: 3024.7294 | P15: 1522.4217 | Q15: 0.40725785 | R15: 0.12594226 | S15: -1.4247309 | T15: -10.937544
... A36: GCST90432107 | B36: GCST90693050 | C36: Tobacco use disorder | D36: Replication | E36: 0.03686985 | F36: 0.0049231522 | G36: 0.12499492 | H36: 0.0035223535 | I36: 0.37695163 | J36: 0.062219934 | K36: 0.6255768 | L36: 2.7242916 | M36: 3386.9321 | N36: 401.69445 | O36: 570.55771 | P36: 169.15613 | Q36: 0.25199743 | R36: 0.071428089 | S36: -1.9861639 | T36: -11.51317
A38: Note: Bivariate causal mixture model (MiXeR) estimates of polygenic overlap between each influenza GWAS and each disorder GWAS, from 20 replicate runs. Influenza h2 and Trait h2 are SNP-based heritabilities on the liability scale for influenza (trait 1) and the disorder (trait 2), reported as mean ± SD across replicates. rg is the estimated genetic correlation. SNP counts are the estimated numbers of trait-influenza-specific (nc1), disorder-specific (nc2) and shared (nc12) causal variants at a per-SNP probability threshold of 1e-9; these are raw variant counts (the corresponding Venn diagrams in the main figures display them scaled per 1,000 variants). Dice is the Dice coefficient quantifying the proportion of shared causal variants. Delta AIC and Delta BIC are the differences in Akaike and Bayesian information criteria between the full bivariate model and the best-fitting nested model (positive values support the full model with non-zero genetic overlap, as encoded by the native best_vs_min_AIC/BIC fields). GCST90432107 was a multi-ancestry meta-analysis (86.0% European ancestry); all other datasets in this table were European-ancestry GWAS. Abbreviations: AIC, Akaike information criterion; BIC, Bayesian information criterion; GWAS, genome-wide association study; h2, SNP-based heritability; SD, standard deviation; SNP, single-nucleotide polymorphism.

Sheet Supplementary Table 5
A1: Supplementary Table 5. Model fit statistics for the genomic structural equation models relating influenza to the healthcare-contact and infection-specific factors.
A3: Model | B3: Chi-square | C3: df | D3: AIC | E3: Delta AIC vs best | F3: CFI | G3: SRMR
A4: Single factor (M0) | B4: 592.07 | C4: 44 | D4: 636.1 | E4: NA | F4: 0.9102 | G4: 0.1695
A5: Correlated two-factor (M1) | B5: 590.7 | C5: 43 | D5: 636.7 | E5: NA | F5: 0.9103 | G5: 0.1669
A6: Influenza as infection indicator (M2a) | B6: 607.74 | C6: 53 | D6: 657.7 | E6: 59 | F6: 0.9108 | G6: 0.155
A7: Influenza as healthcare-contact indicator (M2b) | B7: 625.32 | C7: 53 | D7: 675.3 | E7: 76.6 | F7: 0.9079 | G7: 0.1689
A8: Influenza regressed on both factors (M2c) | B8: 601.99 | C8: 52 | D8: 654 | E8: 55.3 | F8: 0.9115 | G8: 0.1539
A9: Orthogonal bifactor (M2d) | B9: 540.71 | C9: 49 | D9: 598.7 | E9: 0 | F9: 0.9209 | G9: 0.1141
A11: Note: Model fit statistics for the confirmatory factor models of the genetic covariance structure among the indicator traits, estimated by genomic structural equation modelling with diagonally weighted least squares. M0, single general factor; M1, correlated two-factor model (healthcare-contact factor F_H and infection-specific factor F_I); M2a-M2d, influenza placement variants on the M1 structure, with influenza specified as an indicator of F_I (M2a), of F_H (M2b), regressed on both factors (M2c), or modelled as an outcome of an orthogonal bifactor structure (M2d). Delta AIC vs best is the difference in Akaike information criterion relative to the best-fitting placement model; smaller values indicate better fit. CFI, comparative fit index; SRMR, standardized root mean square residual. In M1, the genetic correlation between F_H and F_I was 0.8898 (SE = 0.0898, P = 3.850 × 10-23). NA, not applicable. Abbreviations: AIC, Akaike information criterion; CFI, comparative fit index; SRMR, standardized root mean square residual.

Sheet Supplementary Table 6
A1: Supplementary Table 6. Standardized indicator loadings and influenza structural coefficients in the orthogonal bifactor model (M2d).
A3: Block | B3: Factor | C3: Indicator or outcome | D3: Estimate | E3: SE | F3: P | G3: Significance | H3: R2 contribution
A4: Indicator loadings | B4: G (general) | C4: Help-seeking from a GP | D4: 0.8132 | E4: 0.0237 | F4: 4.78e-259 | G4: *** | H4: NA
A5: Indicator loadings | B5: G (general) | C5: Annual healthcare cost | D5: 0.7394 | E5: 0.0174 | F5: 1.436 × 10^-394 | G5: *** | H5: NA
A6: Indicator loadings | B6: G (general) | C6: Number of illnesses | D6: 0.6907 | E6: 0.0161 | F6: 4.147 × 10^-402 | G6: *** | H6: NA
A7: Indicator loadings | B7: G (general) | C7: Post-traumatic stress disorder | D7: 0.8989 | E7: 0.0244 | F7: 1.07e-297 | G7: *** | H7: NA
A8: Indicator loadings | B8: G (general) | C8: Anxiety disorder | D8: 0.8435 | E8: 0.0185 | F8: 6.646 × 10^-454 | G8: *** | H8: NA
A9: Indicator loadings | B9: G (general) | C9: Major depressive disorder | D9: 0.8871 | E9: 0.0335 | F9: 1.2e-154 | G9: *** | H9: NA
A10: Indicator loadings | B10: G (general) | C10: Sleep disorder | D10: 0.5802 | E10: 0.0311 | F10: 1.31e-77 | G10: *** | H10: NA
A11: Indicator loadings | B11: G (general) | C11: Pneumonia | D11: 0.6379 | E11: 0.0323 | F11: 1.36e-86 | G11: *** | H11: NA
A12: Indicator loadings | B12: G (general) | C12: Upper respiratory tract infection | D12: 0.3152 | E12: 0.0222 | F12: 1.08e-45 | G12: *** | H12: NA
A13: Indicator loadings | B13: G (general) | C13: COVID-19 (hospitalized) | D13: 0.2794 | E13: 0.0391 | F13: 8.46e-13 | G13: *** | H13: NA
A14: Indicator loadings | B14: G (general) | C14: COVID-19 (susceptibility) | D14: 0.1429 | E14: 0.0406 | F14: 0.000431 | G14: *** | H14: NA
A15: Indicator loadings | B15: F_Is (infection-specific) | C15: Pneumonia | D15: 0.3739 | E15: 0.1094 | F15: 0.000636 | G15: *** | H15: NA
A16: Indicator loadings | B16: F_Is (infection-specific) | C16: Upper respiratory tract infection | D16: -0.0509 | E16: 0.0626 | F16: 0.416 | G16: NA | H16: NA
A17: Indicator loadings | B17: F_Is (infection-specific) | C17: COVID-19 (hospitalized) | D17: 1.0057 | E17: 0.1811 | F17: 2.81e-08 | G17: *** | H17: NA
A18: Indicator loadings | B18: F_Is (infection-specific) | C18: COVID-19 (susceptibility) | D18: 0.7861 | E18: 0.1502 | F18: 1.65e-07 | G18: *** | H18: NA
A19: Influenza structural paths | B19: G (general) | C19: Influenza (clinically ascertained) | D19: 0.531 | E19: 0.0375 | F19: 1.51e-45 | G19: *** | H19: 0.282
A20: Influenza structural paths | B20: F_Is (infection-specific) | C20: Influenza (clinically ascertained) | D20: 0.431 | E20: 0.1203 | F20: 0.00034 | G20: *** | H20: 0.1858
A22: Note: Standardized parameter estimates from the orthogonal bifactor model (M2d) in which a general genetic factor G and an infection-specific factor F_Is load on the indicator traits, and clinically ascertained influenza is regressed on both factors. Indicator loadings are standardized factor loadings of the 11 indicator traits on G and F_Is. Influenza structural paths are standardized regression coefficients of influenza on each factor, with the R2 contribution column giving the proportion of influenza variance explained by each factor. P values are two-sided. Significance stars follow conventional thresholds (* P < 0.05, ** P < 0.01, *** P < 0.001). NA, not estimated or not applicable. The COVID-19 hospitalization indicator had a negative standardized residual variance (-0.0894) in M2d, indicating a Heywood-type solution; the bifactor decomposition is therefore exploratory. Abbreviations: F_Is, infection-specific factor; G, general genetic factor; SE, standard error.

Sheet Supplementary Table 7
A1: Supplementary Table 7. Associations of psychiatric disorder outcomes with the general and infection-specific factors in the bifactor outcome model (M3b) and sensitivity excluding COVID-19 indicators.
A3: Outcome | B3: G beta | C3: G P | D3: F_Is beta | E3: F_Is SE | F3: F_Is P | G3: F_Is FDR | H3: Pathway | I3: Main F_Is beta (SE) | J3: Main FDR | K3: No-COVID F_Is beta (SE) | L3: No-COVID FDR
A4: Schizophrenia | B4: 0.3802 | C4: 1.95e-133 | D4: -0.0733 | E4: 0.0420 | F4: 0.0812 | G4: 0.151 | H4: Single-pathway | I4: -0.0733 (0.0420) | J4: 0.151 | K4: -0.4087 (0.3951) | L4: 0.473
A5: Attention-deficit/hyperactivity disorder | B5: 0.6875 | C5: 3.25e-235 | D5: 0.1282 | E5: 0.0594 | F5: 0.0308 | G5: 0.0667 | H5: Single-pathway | I5: +0.1282 (0.0594)* | J5: 0.0667 | K5: +0.4630 (0.1976)* | L5: 0.042
A6: Tobacco use disorder | B6: 0.5968 | C6: 3.43e-118 | D6: 0.5443 | E6: 0.0990 | F6: 3.86e-08 | G6: 5.02e-07 | H6: Dual-pathway | I6: +0.5443 (0.0990)*** | J6: 5.02e-07 | K6: +0.7429 (0.2205)*** | L6: 0.00828
A7: Alcohol dependence | B7: 0.5972 | C7: 2.56e-82 | D7: 0.3879 | E7: 0.0993 | F7: 9.42e-05 | G7: 0.000585 | H7: Dual-pathway | I7: +0.3879 (0.0993)*** | J7: 0.000585 | K7: +0.6734 (0.2433)** | L7: 0.0207
A8: Opiate dependence | B8: 0.7033 | C8: 7.42e-230 | D8: 0.2517 | E8: 0.0659 | F8: 0.000135 | G8: 0.000585 | H8: Dual-pathway | I8: +0.2517 (0.0659)*** | J8: 0.000585 | K8: +0.4978 (0.1666)** | L8: 0.0155
A9: Anorexia nervosa | B9: 0.2893 | C9: 2.81e-46 | D9: -0.1537 | E9: 0.0604 | F9: 0.011 | G9: 0.0286 | H9: Opposite pathway | I9: -0.1537 (0.0604)* | J9: 0.0286 | K9: -0.2867 (0.1553) | L9: 0.119
A10: Tourette syndrome | B10: 0.2511 | C10: 1.85e-19 | D10: -0.0136 | E10: 0.0846 | F10: 0.872 | G10: 0.872 | H10: Single-pathway | I10: -0.0136 (0.0846) | J10: 0.872 | K10: +0.0692 (0.1528) | L10: 0.65
A11: Autism spectrum disorder | B11: 0.3492 | C11: 2.55e-51 | D11: -0.2522 | E11: 0.0816 | F11: 0.00201 | G11: 0.00653 | H11: Opposite pathway | I11: -0.2522 (0.0816)** | J11: 0.00653 | K11: -0.4916 (0.1850)** | L11: 0.0216
A12: Parkinson's disease | B12: 0.0410 | C12: 0.104 | D12: -0.0793 | E12: 0.0797 | F12: 0.319 | G12: 0.415 | H12: Single-pathway | I12: -0.0793 (0.0797) | J12: 0.415 | K12: -0.1080 (0.1421) | L12: 0.546
A13: Obsessive-compulsive disorder | B13: 0.2010 | C13: 1.76e-09 | D13: -0.0436 | E13: 0.0994 | F13: 0.661 | G13: 0.781 | H13: Single-pathway | I13: -0.0436 (0.0994) | J13: 0.781 | K13: n.c. | L13: NA
A14: Alzheimer's disease | B14: 0.1632 | C14: 1.18e-13 | D14: 0.1043 | E14: 0.0639 | F14: 0.103 | G14: 0.167 | H14: Single-pathway | I14: +0.1043 (0.0639) | J14: 0.167 | K14: +0.1156 (0.1909) | L14: 0.6
A15: Bipolar disorder | B15: 0.4554 | C15: 5.17e-176 | D15: -0.0692 | E15: 0.0477 | F15: 0.147 | G15: 0.212 | H15: Single-pathway | I15: -0.0692 (0.0477) | J15: 0.212 | K15: -0.5293 (0.6702) | L15: 0.546
A16: Suicide attempt | B16: 0.7793 | C16: 1.18e-218 | D16: -0.0200 | E16: 0.0672 | F16: 0.766 | G16: 0.83 | H16: Single-pathway | I16: -0.0200 (0.0672) | J16: 0.83 | K16: n.c. | L16: NA
A18: Note: Standardized associations of the 13 psychiatric and neurodevelopmental disorder outcomes with the general genetic factor G and the infection-specific factor F_Is in the bifactor outcome model (M3b), estimated by genomic structural equation modelling. P values are two-sided; FDR was computed by the Benjamini-Hochberg procedure across the F_Is cross-loadings. Pathway classifies each outcome by the sign and significance of its F_Is cross-loading (dual pathway, significant positive cross-loading; opposite pathway, significant negative cross-loading; single pathway, non-significant cross-loading). Sensitivity columns report the F_Is cross-loading and its FDR after removing COVID-19 hospitalization indicator from the model (leave-one-out analysis), given as estimate (SE) with significance stars (* P < 0.05, ** P < 0.01, *** P < 0.001). NA, not estimated. Abbreviations: FDR, false discovery rate; F_Is, infection-specific factor; G, general genetic factor; SE, standard error.

Sheet Supplementary Table 8
A1: Supplementary Table 8. Validity of the healthcare-contact and infection-specific factors assessed by genetic correlations with independent traits.
A3: Trait | B3: F_H rg (95% CI) | C3: F_H FDR | D3: F_I rg (95% CI) | E3: F_I FDR
A4: Angina pectoris | B4: 0.5022 (0.4634, 0.5410)*** | C4: 6.82e-141 | D4: 0.4214 (0.2942, 0.5486)*** | E4: 9.89e-11
A5: Asthma | B5: 0.5795 (0.5438, 0.6152)*** | C5: 1.62e-221 | D5: 0.6160 (0.4553, 0.7767)*** | E5: 7.92e-14
A6: Body mass index | B6: 0.3205 (0.2954, 0.3456)*** | C6: 3e-137 | D6: 0.4462 (0.3439, 0.5485)*** | E6: 2e-17
A7: C-reactive protein | B7: 0.3285 (0.3024, 0.3546)*** | C7: 7.61e-135 | D7: 0.5272 (0.4080, 0.6464)*** | E7: 6.46e-18
A8: Chronic obstructive pulmonary disease | B8: 0.6535 (0.6143, 0.6927)*** | C8: 1.56e-232 | D8: 0.8616 (0.6856, 1.0376)*** | E8: 1.48e-21
A9: Coronary artery disease | B9: 0.3825 (0.3537, 0.4113)*** | C9: 7.26e-149 | D9: 0.3497 (0.2501, 0.4493)*** | E9: 6.83e-12
A10: Educational attainment | B10: -0.3926 (-0.4214, -0.3638)*** | C10: 5.14e-157 | D10: -0.4705 (-0.5732, -0.3678)*** | E10: 4.34e-19
A11: Hypertension | B11: 0.2843 (0.2557, 0.3129)*** | C11: 5.54e-84 | D11: 0.1840 (0.0903, 0.2777)*** | E11: 0.000118
A12: Ischaemic stroke | B12: 0.3408 (0.2951, 0.3865)*** | C12: 5.26e-48 | D12: 0.4457 (0.3038, 0.5876)*** | E12: 8.31e-10
A13: Myocardial infarction | B13: 0.3437 (0.2959, 0.3915)*** | C13: 6.72e-45 | D13: 0.3399 (0.2056, 0.4742)*** | E13: 7.4e-07
A14: Smoking status | B14: 0.3962 (0.3648, 0.4276)*** | C14: 2.19e-134 | D14: 0.4574 (0.3520, 0.5628)*** | E14: 2.54e-17
A15: Type 2 diabetes | B15: 0.3853 (0.3526, 0.4180)*** | C15: 5.81e-117 | D15: 0.4034 (0.2923, 0.5145)*** | E15: 1.43e-12
A17: Note: Genetic correlations (rg) of the healthcare-contact factor F_H and the infection-specific factor F_Is with 12 independent validity traits not used in model estimation, with 95% confidence intervals in parentheses. Estimates were obtained from the M1 correlated two-factor model; FDR was computed by the Benjamini-Hochberg procedure within each factor. Significance stars follow conventional thresholds (* P < 0.05, ** P < 0.01, *** P < 0.001). NA, not applicable. Abbreviations: CI, confidence interval; FDR, false discovery rate; F_H, healthcare-contact factor; F_I, infection-specific factor; rg, genetic correlation.

Sheet Supplementary Table 9
A1: Supplementary Table 9. Attenuation of influenza-disorder genetic correlations after conditioning on healthcare-contact and psychological-distress covariates by multi-trait conditional and joint analysis.
A3: Disorder | B3: Pathway | C3: Unconditioned rg | D3: Unconditioned P | E3: Conditioned on GP-help-seeking rg | F3: Conditioned on GP-help-seeking P | G3: Conditioned on healthcare cost rg | H3: Conditioned on healthcare cost P | I3: Conditioned on number of illnesses rg | J3: Conditioned on number of illnesses P | K3: Conditioned on all healthcare-contact traits rg | L3: Conditioned on all healthcare-contact traits P | M3: Conditioned on psychological distress rg | N3: Conditioned on psychological distress P
A4: Post-traumatic stress disorder | C4: 0.4448 | D4: 3.05e-15 | E4: 0.3082 | F4: 2.73e-08 | G4: 0.2475 | H4: 2.04e-05 | I4: 0.4015 | J4: 2.18e-11 | K4: 0.2406 | L4: 2e-05 | M4: 0.162 | N4: 0.023
A5: Opiate dependence | B5: Dual-pathway | C5: 0.3968 | D5: 7.8e-10 | E5: 0.3336 | F5: 1.69e-06 | G5: 0.2169 | H5: 0.00315 | I5: 0.3506 | J5: 5.63e-07 | K5: 0.2328 | L5: 0.00129 | M5: 0.2759 | N5: 0.00297
A6: Suicide attempt | B6: Single-pathway | C6: 0.385 | D6: 1.01e-11 | E6: 0.2459 | F6: 2.69e-05 | G6: 0.2326 | H6: 0.000237 | I6: 0.3624 | J6: 2.47e-09 | K6: 0.1907 | L6: 0.00162 | M6: 0.2464 | N6: 0.00102
A7: Anxiety disorder | C7: 0.3734 | D7: 2.43e-13 | E7: 0.21 | F7: 4.35e-05 | G7: 0.1924 | H7: 0.00054 | I7: 0.3302 | J7: 1.53e-09 | K7: 0.1757 | L7: 0.00132 | M7: 0.1488 | N7: 0.0285
A8: Tobacco use disorder | B8: Dual-pathway | C8: 0.3554 | D8: 1.42e-09 | E8: 0.3269 | F8: 4.42e-07 | G8: 0.1779 | H8: 0.00795 | I8: 0.3059 | J8: 1.01e-06 | K8: 0.223 | L8: 0.000925 | M8: 0.1689 | N8: 0.0422
A9: Major depressive disorder | C9: 0.3522 | D9: 6.84e-10 | E9: 0.1901 | F9: 0.0019 | G9: 0.1843 | H9: 0.00406 | I9: 0.3044 | J9: 8.82e-07 | K9: 0.1787 | L9: 0.00607 | M9: 0.148 | N9: 0.0498
A10: Sleep disorder | C10: 0.3368 | D10: 1.85e-06 | E10: 0.2713 | F10: 0.000329 | G10: 0.1192 | H10: 0.135 | I10: 0.2727 | J10: 0.000267 | K10: 0.1565 | L10: 0.0491 | M10: 0.484 | N10: 2.39e-06
A11: Attention deficit hyperactivity disorder | B11: Single-pathway | C11: 0.2946 | D11: 2.77e-09 | E11: 0.2353 | F11: 5.06e-06 | G11: 0.1057 | H11: 0.0543 | I11: 0.2499 | J11: 2.73e-06 | K11: 0.133 | L11: 0.0125 | M11: 0.2816 | N11: 7.78e-05
A12: Alcohol dependence | B12: Dual-pathway | C12: 0.2483 | D12: 0.000472 | E12: 0.1821 | F12: 0.0171 | G12: 0.0446 | H12: 0.575 | I12: 0.1999 | J12: 0.00852 | K12: 0.0459 | L12: 0.578 | M12: 0.2155 | N12: 0.0245
A13: Schizophrenia | B13: Single-pathway | C13: 0.2033 | D13: 4.56e-06 | E13: 0.102 | F13: 0.0325 | G13: 0.1298 | H13: 0.0128 | I13: 0.1999 | J13: 4.41e-05 | K13: 0.0903 | L13: 0.0728 | M13: 0.0624 | N13: 0.314
A14: Bipolar disorder | B14: Single-pathway | C14: 0.1922 | D14: 2.16e-07 | E14: 0.0724 | F14: 0.0613 | G14: 0.1189 | H14: 0.00555 | I14: 0.1799 | J14: 6.84e-06 | K14: 0.0707 | L14: 0.0854 | M14: 0.1772 | N14: 0.000526
A15: Tourette syndrome | B15: Single-pathway | C15: 0.1615 | D15: 0.108 | E15: 0.1245 | F15: 0.275 | G15: 0.1415 | H15: 0.216 | I15: 0.1431 | J15: 0.183 | K15: 0.1381 | L15: 0.242 | M15: 0.0766 | N15: 0.578
A16: Anorexia nervosa | B16: Opposite pathway | C16: 0.1038 | D16: 0.0288 | E16: 0.0289 | F16: 0.562 | G16: 0.0801 | H16: 0.142 | I16: 0.1139 | J16: 0.0244 | K16: 0.0213 | L16: 0.694 | M16: -0.0018 | N16: 0.978
A17: Obsessive-compulsive disorder | B17: Single-pathway | C17: 0.0782 | D17: 0.316 | E17: 0.0276 | F17: 0.75 | G17: 0.0775 | H17: 0.407 | I17: 0.0987 | J17: 0.245 | K17: 0.0565 | L17: 0.546 | M17: -0.0815 | N17: 0.466
A18: Alzheimer's disease | C18: -0.0021 | D18: 0.972 | E18: -0.0192 | F18: 0.763 | G18: -0.0276 | H18: 0.683 | I18: -0.0117 | J18: 0.853 | K18: -0.0231 | L18: 0.728 | M18: -0.035 | N18: 0.653
A19: Autism spectrum disorder | B19: Opposite pathway | C19: -0.0131 | D19: 0.847 | E19: -0.0743 | F19: 0.286 | G19: -0.0364 | H19: 0.614 | I19: -0.0417 | J19: 0.559 | K19: 0.0085 | L19: 0.9 | M19: 0.0492 | N19: 0.567
A20: Parkinson disease | B20: Single-pathway | C20: -0.0226 | D20: 0.709 | E20: -0.0363 | F20: 0.587 | G20: -0.0249 | H20: 0.733 | I20: -0.0301 | J20: 0.653 | K20: -0.0417 | L20: 0.56 | M20: 0.0341 | N20: 0.695
A22: Note: Combined-panel genetic correlations (rg) between influenza and each psychiatric or neurodevelopmental disorder before (unconditioned) and after multi-trait conditioning on healthcare-contact and psychological-distress covariates, estimated by multi-trait conditional and joint analysis (mtCOJO) with genome-wide significant SNPs of the covariates fitted as co-heritable traits. Psychiatric-specialist help-seeking, healthcare cost and number of illnesses were conditioned jointly as the all healthcare-contact traits model; psychological distress was conditioned separately. P values are two-sided. Pathway classifies each disorder by the sign and significance of its cross-loading on the infection-specific factor F_Is in the bifactor outcome model (Supplementary Table 7); NA indicates disorders not included in that model (post-traumatic stress disorder, anxiety disorder, major depressive disorder and sleep disorder). Disorder order follows the descending unconditioned rg. Abbreviations: GP, general practitioner; mtCOJO, multi-trait conditional and joint analysis; rg, genetic correlation.

Sheet Supplementary Table 10
A1: Supplementary Table 10. Genome-wide significant loci of the influenza GWAS and their residual association signals after GWAS-by-subtraction conditioning.
A3: Block | B3: Locus | C3: Lead SNP | D3: CHR | E3: POS | F3: P FinnGen raw | G3: P FinnGen SUB1 | H3: P FinnGen SUB2 | I3: P Kosmicki raw | J3: P Kosmicki SUB1 | K3: P Kosmicki SUB2 | L3: Panel | M3: Stage | N3: SNPs analysed | O3: Lambda residual | P3: Top P residual
A4: GWS loci | B4: ST6GAL1 | C4: rs13322149 | D4: 3 | E4: 186977425 | F4: 5.18633e-10 | G4: 6.11209e-10 | H4: 7.8375e-10 | I4: 3.648e-19 | J4: 3.68373e-18 | K4: 2.30076e-18
A5: GWS loci | B5: B3GALT5 | C5: rs2837113 | D5: 21 | E5: 39676197 | F5: 5.55086e-08 | G5: 1.10738e-08 | H5: 2.85206e-08 | I5: 4.086e-32 | J5: 3.70532e-33 | K5: 7.82251e-33
A6: Residual GWAS QC | L6: FinnGen | M6: SUB1 | N6: 1141400 | O6: 1.0362 | P6: 6.11e-10
A7: Residual GWAS QC | L7: FinnGen | M7: SUB2 | N7: 741010 | O7: 1.0406 | P7: 7.84e-10
A8: Residual GWAS QC | L8: Kosmicki | M8: SUB1 | N8: 1136148 | O8: 1.0458 | P8: 3.71e-33
A9: Residual GWAS QC | L9: Kosmicki | M9: SUB2 | N9: 738015 | O9: 1.0525 | P9: 7.82e-33
A11: Note: Genome-wide significant loci of the influenza GWAS and their association signals in the GWAS-by-subtraction residual models for the two influenza GWAS panels (FinnGen J10_INFLUENZA and Kosmicki et al.). SUB1 is the residual GWAS after regressing out genetic effects of the healthcare-contact covariates (Psychiatric-specialist help-seeking, healthcare cost and number of illnesses); SUB2 is the residual GWAS after additionally regressing out the illness-distress dimension indicators (post-traumatic stress disorder, anxiety, major depressive disorder, sleep disorder, pneumonia, upper respiratory tract infection, COVID-19 hospitalization and susceptibility). The genome-wide lead SNP was rs13322149 at ST6GAL1; by contrast, rs55958900 was the most significant marginal SNP within the GWAS-eQTL overlapping-variant set used for regulatory comparisons; P values are two-sided from the GWAS or residual summary statistics at the lead SNP (exact values in full decimal notation). The residual GWAS QC block reports the number of SNPs analysed, the genomic control lambda of the residual trait (Lambda_Fres) and the smallest residual P value (Top P_Fres) for each panel and residualization stage. NA, not applicable. Abbreviations: GWAS, genome-wide association study; GWS, genome-wide significant; SNP, single-nucleotide polymorphism.

Sheet Supplementary Table 11
A1: Supplementary Table 11. Colocalization of the ST6GAL1 and B3GALT5 influenza GWAS loci with cis-eQTL and cis-pQTL across tissues and cell types.
A3: Block | B3: GWAS | C3: Locus | D3: Gene | E3: Tissue or pQTL dataset | F3: n SNPs | G3: PP.H0 | H3: PP.H1 | I3: PP.H2 | J3: PP.H3 | K3: PP.H4 | L3: Note
A4: eQTL colocalization | B4: COVID19_HGI_B2_B3GALT5 | C4: B3GALT5 | D4: B3GALT5 | E4: Brain_Amygdala | F4: 7306 | G4: 0.46950283 | H4: 0.059133457 | I4: 0.41325724 | J4: 0.052043312 | K4: 0.0060631576 | L4: OK
A5: eQTL colocalization | B5: COVID19_HGI_B2_B3GALT5 | C5: B3GALT5 | D5: B3GALT5 | E5: Brain_Cerebellum | F5: 7317 | G5: 0.51313858 | H5: 0.064781837 | I5: 0.36812384 | J5: 0.046466777 | K5: 0.0074889639 | L5: OK
A6: eQTL colocalization | B6: COVID19_HGI_B2_B3GALT5 | C6: B3GALT5 | D6: B3GALT5 | E6: Brain_Cortex | F6: 7317 | G6: 0.14789468 | H6: 0.018670627 | I6: 0.73659109 | J6: 0.092985407 | K6: 0.0038582042 | L6: OK
A7: eQTL colocalization | B7: COVID19_HGI_B2_B3GALT5 | C7: B3GALT5 | D7: B3GALT5 | E7: Brain_Frontal_Cortex_BA9 | F7: 7317 | G7: 0.43364095 | H7: 0.054627832 | I7: 0.44947034 | J7: 0.056616292 | K7: 0.0056445904 | L7: OK
A8: eQTL colocalization | B8: COVID19_HGI_B2_B3GALT5 | C8: B3GALT5 | D8: B3GALT5 | E8: Brain_Hippocampus | F8: 7308 | G8: 0.46316022 | H8: 0.058223911 | I8: 0.41999263 | J8: 0.052791477 | K8: 0.0058317593 | L8: OK
A9: eQTL colocalization | B9: COVID19_HGI_B2_B3GALT5 | C9: B3GALT5 | D9: B3GALT5 | E9: Brain_Hypothalamus | F9: 7317 | G9: 0.46403892 | H9: 0.058582353 | I9: 0.41887039 | J9: 0.052874442 | K9: 0.0056338933 | L9: OK
A10: eQTL colocalization | B10: COVID19_HGI_B2_B3GALT5 | C10: B3GALT5 | D10: B3GALT5 | E10: Brain_Putamen_basal_ganglia | F10: 7318 | G10: 0.49872544 | H10: 0.062969423 | I10: 0.38343761 | J10: 0.04840664 | K10: 0.006460888 | L10: OK
A11: eQTL colocalization | B11: COVID19_HGI_B2_B3GALT5 | C11: B3GALT5 | D11: B3GALT5 | E11: Liver | F11: 7318 | G11: 0.53101669 | H11: 0.067046538 | I11: 0.35152833 | J11: 0.044378182 | K11: 0.0060302655 | L11: OK
A12: eQTL colocalization | B12: COVID19_HGI_B2_B3GALT5 | C12: B3GALT5 | D12: B3GALT5 | E12: Lung | F12: 7318 | G12: 0.53354131 | H12: 0.067365299 | I12: 0.34870728 | J12: 0.044021661 | K12: 0.0063644505 | L12: OK
A13: eQTL colocalization | B13: COVID19_HGI_B2_B3GALT5 | C13: B3GALT5 | D13: B3GALT5 | E13: Spleen | F13: 7318 | G13: 3.8245e-13 | H13: 4.828e-14 | I13: 0.88478678 | J13: 0.1117103 | K13: 0.0035029198 | L13: OK
A14: eQTL colocalization | B14: COVID19_HGI_B2_B3GALT5 | C14: B3GALT5 | D14: B3GALT5 | E14: Braineac2_putamen | F14: 6323 | G14: 0.53773383 | H14: 0.055137123 | I14: 0.36453286 | J14: 0.037372549 | K14: 0.0052236388 | L14: OK
A15: eQTL colocalization | B15: COVID19_HGI_B2_B3GALT5 | C15: B3GALT5 | D15: B3GALT5 | E15: Braineac2_substantia_nigra | F15: 5943 | G15: 0.55219597 | H15: 0.052438096 | I15: 0.35539813 | J15: 0.033743391 | K15: 0.0062244132 | L15: OK
... A71: eQTL colocalization | B71: COVID19_HGI_B2_ST6GAL1 | C71: ST6GAL1 | D71: ST6GAL1 | E71: brainSCOPE_Lamp5 | F71: 26 | G71: 0.021515575 | H71: 3.1606835e-06 | I71: 0.97255439 | J71: 0.00013708051 | K71: 0.0057897893 | L71: OK
A72: eQTL colocalization | B72: COVID19_HGI_B2_ST6GAL1 | C72: ST6GAL1 | D72: ST6GAL1 | E72: brainSCOPE_OPC | L72: <10 common SNPs
A73: eQTL colocalization | B73: COVID19_HGI_B2_ST6GAL1 | C73: ST6GAL1 | D73: ST6GAL1 | E73: brainSCOPE_Sst__Sst.Chodl | F73: 60 | G73: 1.5968759e-09 | H73: 4.7424e-13 | I73: 0.99667881 | J73: 0.00029296558 | K73: 0.0030282179 | L73: OK
A74: eQTL colocalization | B74: COVID19_HGI_B2_ST6GAL1 | C74: ST6GAL1 | D74: ST6GAL1 | E74: brainSCOPE_Vip | F74: 42 | G74: 4.9194794e-08 | H74: 7.03566e-12 | I74: 0.99611014 | J74: 0.00013870905 | K74: 0.0037510981 | L74: OK
A75: eQTL colocalization | B75: COVID19_HGI_B2_ST6GAL1 | C75: ST6GAL1 | D75: ST6GAL1 | E75: PsychENCODE_DLPFC_bulk | F75: 77 | G75: 6.9664209e-10 | H75: 2.8367e-13 | I75: 0.99493853 | J75: 0.00040048029 | K75: 0.0046609886 | L75: OK
A76: eQTL colocalization | B76: FinnGen_SUB2_B3GALT5 | C76: B3GALT5 | D76: B3GALT5 | E76: Brain_Amygdala | F76: 897 | G76: 0.7117171 | H76: 0.17695231 | I76: 0.078057107 | J76: 0.019393249 | K76: 0.013880233 | L76: OK
A77: eQTL colocalization | B77: FinnGen_SUB2_B3GALT5 | C77: B3GALT5 | D77: B3GALT5 | E77: Brain_Cerebellum | F77: 897 | G77: 0.72079198 | H77: 0.17920858 | I77: 0.067976209 | J77: 0.016885605 | K77: 0.015137623 | L77: OK
A78: eQTL colocalization | B78: FinnGen_SUB2_B3GALT5 | C78: B3GALT5 | D78: B3GALT5 | E78: Brain_Cortex | F78: 897 | G78: 0.58644663 | H78: 0.14580665 | I78: 0.20051054 | J78: 0.049834996 | K78: 0.017401178 | L78: OK
A79: eQTL colocalization | B79: FinnGen_SUB2_B3GALT5 | C79: B3GALT5 | D79: B3GALT5 | E79: Brain_Frontal_Cortex_BA9 | F79: 897 | G79: 0.70599919 | H79: 0.17553069 | I79: 0.070509632 | J79: 0.01750016 | K79: 0.030460327 | L79: OK
A80: eQTL colocalization | B80: FinnGen_SUB2_B3GALT5 | C80: B3GALT5 | D80: B3GALT5 | E80: Brain_Hippocampus | F80: 897 | G80: 0.6913641 | H80: 0.171892 | I80: 0.096958676 | J80: 0.024090881 | K80: 0.015694346 | L80: OK
A81: eQTL colocalization | B81: FinnGen_SUB2_B3GALT5 | C81: B3GALT5 | D81: B3GALT5 | E81: Brain_Hypothalamus | F81: 897 | G81: 0.72158227 | H81: 0.17940506 | I81: 0.067277617 | J81: 0.016712031 | K81: 0.01502302 | L81: OK
A82: eQTL colocalization | B82: FinnGen_SUB2_B3GALT5 | C82: B3GALT5 | D82: B3GALT5 | E82: Brain_Putamen_basal_ganglia | F82: 897 | G82: 0.72021027 | H82: 0.17906395 | I82: 0.071459987 | J82: 0.017755395 | K82: 0.011510395 | L82: OK
A83: eQTL colocalization | B83: FinnGen_SUB2_B3GALT5 | C83: B3GALT5 | D83: B3GALT5 | E83: Liver | F83: 897 | G83: 0.73447716 | H83: 0.18261109 | I83: 0.05733918 | J83: 0.014244759 | K83: 0.01132782 | L83: OK
A84: eQTL colocalization | B84: FinnGen_SUB2_B3GALT5 | C84: B3GALT5 | D84: B3GALT5 | E84: Lung | F84: 897 | G84: 0.69533472 | H84: 0.17287921 | I84: 0.057446441 | J84: 0.014222638 | K84: 0.060117 | L84: OK
... A90: eQTL colocalization | B90: FinnGen_SUB2_B3GALT5 | C90: B3GALT5 | D90: B3GALT5 | E90: ROSMAP_DLPFC | F90: 888 | G90: 0.70168116 | H90: 0.17436121 | I90: 0.089616627 | J90: 0.02225681 | K90: 0.012084195 | L90: OK
A91: eQTL colocalization | B91: FinnGen_SUB2_B3GALT5 | C91: B3GALT5 | D91: B3GALT5 | E91: brainSCOPE_Astro | L91: <10 common SNPs
A92: eQTL colocalization | B92: FinnGen_SUB2_B3GALT5 | C92: B3GALT5 | D92: B3GALT5 | E92: brainSCOPE_Chandelier__Pvalb | L92: <10 common SNPs
A93: eQTL colocalization | B93: FinnGen_SUB2_B3GALT5 | C93: B3GALT5 | D93: B3GALT5 | E93: brainSCOPE_L2.3.IT | F93: 19 | G93: 0.40884559 | H93: 4.3830413e-05 | I93: 0.58788825 | J93: 5.986226e-05 | K93: 0.0031624757 | L93: OK
A94: eQTL colocalization | B94: FinnGen_SUB2_B3GALT5 | C94: B3GALT5 | D94: B3GALT5 | E94: brainSCOPE_L4.IT | L94: <10 common SNPs
A95: eQTL colocalization | B95: FinnGen_SUB2_B3GALT5 | C95: B3GALT5 | D95: B3GALT5 | E95: brainSCOPE_L6.IT | L95: <10 common SNPs
A96: eQTL colocalization | B96: FinnGen_SUB2_B3GALT5 | C96: B3GALT5 | D96: B3GALT5 | E96: brainSCOPE_Vip | L96: <10 common SNPs
A97: eQTL colocalization | B97: FinnGen_SUB2_B3GALT5 | C97: B3GALT5 | D97: B3GALT5 | E97: PsychENCODE_DLPFC_bulk | L97: <10 common SNPs
A98: eQTL colocalization | B98: FinnGen_SUB2_ST6GAL1 | C98: ST6GAL1 | D98: ST6GAL1 | E98: Brain_Amygdala | F98: 717 | G98: 0.00068642511 | H98: 0.85964811 | I98: 5.2289837e-05 | J98: 0.065411252 | K98: 0.074201921 | L98: OK
A99: eQTL colocalization | B99: FinnGen_SUB2_ST6GAL1 | C99: ST6GAL1 | D99: ST6GAL1 | E99: Brain_Cerebellum | F99: 717 | G99: 0.00067762918 | H99: 0.84863249 | I99: 4.7476911e-05 | J99: 0.059366685 | K99: 0.091275721 | L99: OK
A100: eQTL colocalization | B100: FinnGen_SUB2_ST6GAL1 | C100: ST6GAL1 | D100: ST6GAL1 | E100: Brain_Cortex | F100: 717 | G100: 0.00066616909 | H100: 0.83428038 | I100: 7.8325051e-05 | J100: 0.09802384 | K100: 0.066951284 | L100: OK
A101: eQTL colocalization | B101: FinnGen_SUB2_ST6GAL1 | C101: ST6GAL1 | D101: ST6GAL1 | E101: Brain_Frontal_Cortex_BA9 | F101: 717 | G101: 0.00066863798 | H101: 0.83737231 | I101: 6.9693084e-05 | J101: 0.087205819 | K101: 0.074683544 | L101: OK
A102: eQTL colocalization | B102: FinnGen_SUB2_ST6GAL1 | C102: ST6GAL1 | D102: ST6GAL1 | E102: Brain_Hippocampus | F102: 717 | G102: 0.00069245905 | H102: 0.86720475 | I102: 4.7687666e-05 | J102: 0.059649494 | K102: 0.072405611 | L102: OK
A103: eQTL colocalization | B103: FinnGen_SUB2_ST6GAL1 | C103: ST6GAL1 | D103: ST6GAL1 | E103: Brain_Hypothalamus | F103: 717 | G103: 0.00066866675 | H103: 0.83740834 | I103: 5.5916569e-05 | J103: 0.069935479 | K103: 0.091931595 | L103: OK
A104: eQTL colocalization | B104: FinnGen_SUB2_ST6GAL1 | C104: ST6GAL1 | D104: ST6GAL1 | E104: Brain_Putamen_basal_ganglia | F104: 717 | G104: 0.00067311201 | H104: 0.84297538 | I104: 6.8880949e-05 | J104: 0.086193332 | K104: 0.070089294 | L104: OK
A105: eQTL colocalization | B105: FinnGen_SUB2_ST6GAL1 | C105: ST6GAL1 | D105: ST6GAL1 | E105: Cells_EBV-transformed_lymphocytes | F105: 717 | G105: 0.00066934537 | H105: 0.83825821 | I105: 4.774889e-05 | J105: 0.059697247 | K105: 0.10132745 | L105: OK
A106: eQTL colocalization | B106: FinnGen_SUB2_ST6GAL1 | C106: ST6GAL1 | D106: ST6GAL1 | E106: Liver | F106: 717 | G106: 0.00068514134 | H106: 0.85804038 | I106: 5.1623492e-05 | J106: 0.064574305 | K106: 0.076648554 | L106: OK
A107: eQTL colocalization | B107: FinnGen_SUB2_ST6GAL1 | C107: ST6GAL1 | D107: ST6GAL1 | E107: Lung | F107: 717 | G107: 0.00060487749 | H107: 0.75752152 | I107: 5.2016821e-05 | J107: 0.064966686 | K107: 0.1768549 | L107: OK
A108: eQTL colocalization | B108: FinnGen_SUB2_ST6GAL1 | C108: ST6GAL1 | D108: ST6GAL1 | E108: Spleen | F108: 717 | G108: 0.00044840678 | H108: 0.5615646 | I108: 0.00031402779 | J108: 0.39322992 | K108: 0.044443043 | L108: OK
A109: eQTL colocalization | B109: FinnGen_SUB2_ST6GAL1 | C109: ST6GAL1 | D109: ST6GAL1 | E109: Whole_Blood | F109: 717 | G109: 0.00050997697 | H109: 0.63867235 | I109: 0.00025545759 | J109: 0.31988299 | K109: 0.040679228 | L109: OK
... A116: eQTL colocalization | B116: FinnGen_SUB2_ST6GAL1 | C116: ST6GAL1 | D116: ST6GAL1 | E116: CommonMind_DLPFC | F116: 718 | G116: 0.0006629953 | H116: 0.83030222 | I116: 7.5513168e-05 | J116: 0.094494457 | K116: 0.074464819 | L116: OK
A117: eQTL colocalization | B117: FinnGen_SUB2_ST6GAL1 | C117: ST6GAL1 | D117: ST6GAL1 | E117: Natri2024_AT1 | L117: <10 common SNPs
A118: eQTL colocalization | B118: FinnGen_SUB2_ST6GAL1 | C118: ST6GAL1 | D118: ST6GAL1 | E118: Natri2024_AT2 | L118: <10 common SNPs
A119: eQTL colocalization | B119: FinnGen_SUB2_ST6GAL1 | C119: ST6GAL1 | D119: ST6GAL1 | E119: Natri2024_Basal | L119: <10 common SNPs
A120: eQTL colocalization | B120: FinnGen_SUB2_ST6GAL1 | C120: ST6GAL1 | D120: ST6GAL1 | E120: Natri2024_Ciliated | L120: <10 common SNPs
A121: eQTL colocalization | B121: FinnGen_SUB2_ST6GAL1 | C121: ST6GAL1 | D121: ST6GAL1 | E121: Natri2024_DifferentiatingCiliated | L121: <10 common SNPs
A122: eQTL colocalization | B122: FinnGen_SUB2_ST6GAL1 | C122: ST6GAL1 | D122: ST6GAL1 | E122: Natri2024_KRT5-KRT17+ | L122: <10 common SNPs
A123: eQTL colocalization | B123: FinnGen_SUB2_ST6GAL1 | C123: ST6GAL1 | D123: ST6GAL1 | E123: Natri2024_Proliferating | L123: <10 common SNPs
A124: eQTL colocalization | B124: FinnGen_SUB2_ST6GAL1 | C124: ST6GAL1 | D124: ST6GAL1 | E124: Natri2024_Secretory-SCGB1A1+MUC5B+ | L124: <10 common SNPs
A125: eQTL colocalization | B125: FinnGen_SUB2_ST6GAL1 | C125: ST6GAL1 | D125: ST6GAL1 | E125: Natri2024_Secretory-SCGB1A1+SCGB3A2+ | L125: <10 common SNPs
A126: eQTL colocalization | B126: FinnGen_SUB2_ST6GAL1 | C126: ST6GAL1 | D126: ST6GAL1 | E126: Natri2024_Secretory-SCGB3A2+ | L126: <10 common SNPs
A127: eQTL colocalization | B127: FinnGen_SUB2_ST6GAL1 | C127: ST6GAL1 | D127: ST6GAL1 | E127: Natri2024_TransitionalAT2 | L127: <10 common SNPs
A128: eQTL colocalization | B128: FinnGen_SUB2_ST6GAL1 | C128: ST6GAL1 | D128: ST6GAL1 | E128: Nedelec_macrophage_naive | F128: 716 | G128: 0.00068583835 | H128: 0.85890948 | I128: 4.8282544e-05 | J128: 0.060386663 | K128: 0.079969732 | L128: OK
A129: eQTL colocalization | B129: FinnGen_SUB2_ST6GAL1 | C129: ST6GAL1 | D129: ST6GAL1 | E129: Nedelec_macrophage_Salmonella | F129: 717 | G129: 0.0006761631 | H129: 0.8467929 | I129: 5.4552917e-05 | J129: 0.068235107 | K129: 0.084241278 | L129: OK
A130: eQTL colocalization | B130: FinnGen_SUB2_ST6GAL1 | C130: ST6GAL1 | D130: ST6GAL1 | E130: OneK1K_CD14_Mono | F130: 718 | G130: 0.00071789883 | H130: 0.89906066 | I130: 3.794927e-05 | J130: 0.047473062 | K130: 0.05271043 | L130: OK
A131: eQTL colocalization | B131: FinnGen_SUB2_ST6GAL1 | C131: ST6GAL1 | D131: ST6GAL1 | E131: OneK1K_CD4_Naive | F131: 718 | G131: 4.3931208e-36 | H131: 5.5017252e-33 | I131: 0.00079785849 | J131: 0.99919814 | K131: 3.997261e-06 | L131: OK
A132: eQTL colocalization | B132: FinnGen_SUB2_ST6GAL1 | C132: ST6GAL1 | D132: ST6GAL1 | E132: OneK1K_NK | F132: 718 | G132: 5.5504015e-18 | H132: 6.9510458e-15 | I132: 0.00079784794 | J132: 0.99918492 | K132: 1.7235833e-05 | L132: OK
A133: eQTL colocalization | B133: FinnGen_SUB2_ST6GAL1 | C133: ST6GAL1 | D133: ST6GAL1 | E133: Quach_monocyte_LPS | F133: 718 | G133: 0.00064968778 | H133: 0.81363655 | I133: 5.5615865e-05 | J133: 0.069534409 | K133: 0.11612373 | L133: OK
A134: eQTL colocalization | B134: FinnGen_SUB2_ST6GAL1 | C134: ST6GAL1 | D134: ST6GAL1 | E134: Quach_monocyte_naive | F134: 718 | G134: 0.00068807218 | H134: 0.86170725 | I134: 4.5781141e-05 | J134: 0.057253711 | K134: 0.080305184 | L134: OK
A135: eQTL colocalization | B135: FinnGen_SUB2_ST6GAL1 | C135: ST6GAL1 | D135: ST6GAL1 | E135: Quach_monocyte_Pam3CSK4 | F135: 717 | G135: 0.00066786722 | H135: 0.83640337 | I135: 6.1193308e-05 | J135: 0.076549108 | K135: 0.086318457 | L135: OK
A136: eQTL colocalization | B136: FinnGen_SUB2_ST6GAL1 | C136: ST6GAL1 | D136: ST6GAL1 | E136: Quach_monocyte_R848 | F136: 717 | G136: 0.00068248153 | H136: 0.85470559 | I136: 5.627593e-05 | J136: 0.070402996 | K136: 0.074152655 | L136: OK
A137: eQTL colocalization | B137: FinnGen_SUB2_ST6GAL1 | C137: ST6GAL1 | D137: ST6GAL1 | E137: ROSMAP_DLPFC | F137: 715 | G137: 0.00023810685 | H137: 0.29819321 | I137: 0.00047648369 | J137: 0.59662009 | K137: 0.10447211 | L137: OK
A138: eQTL colocalization | B138: FinnGen_SUB2_ST6GAL1 | C138: ST6GAL1 | D138: ST6GAL1 | E138: brainSCOPE_Chandelier__Pvalb | F138: 11 | G138: 1.015574e-11 | H138: 5.7521362e-10 | I138: 0.016651141 | J138: 0.94306724 | K138: 0.040281617 | L138: OK
A139: eQTL colocalization | B139: FinnGen_SUB2_ST6GAL1 | C139: ST6GAL1 | D139: ST6GAL1 | E139: brainSCOPE_L2.3.IT | F139: 12 | G139: 6.3849357e-09 | H139: 1.5818351e-07 | I139: 0.035473459 | J139: 0.87875099 | K139: 0.085775384 | L139: OK
... A142: eQTL colocalization | B142: FinnGen_SUB2_ST6GAL1 | C142: ST6GAL1 | D142: ST6GAL1 | E142: brainSCOPE_L6.IT | F142: 10 | G142: 0.00012604763 | H142: 0.0031270852 | I142: 0.0016519841 | J142: 0.040028608 | K142: 0.95506627 | L142: OK
A143: eQTL colocalization | B143: FinnGen_SUB2_ST6GAL1 | C143: ST6GAL1 | D143: ST6GAL1 | E143: brainSCOPE_Lamp5 | L143: <10 common SNPs
A144: eQTL colocalization | B144: FinnGen_SUB2_ST6GAL1 | C144: ST6GAL1 | D144: ST6GAL1 | E144: brainSCOPE_OPC | L144: <10 common SNPs
A145: eQTL colocalization | B145: FinnGen_SUB2_ST6GAL1 | C145: ST6GAL1 | D145: ST6GAL1 | E145: brainSCOPE_Sst__Sst.Chodl | L145: <10 common SNPs
A146: eQTL colocalization | B146: FinnGen_SUB2_ST6GAL1 | C146: ST6GAL1 | D146: ST6GAL1 | E146: brainSCOPE_Vip | L146: <10 common SNPs
A147: eQTL colocalization | B147: FinnGen_SUB2_ST6GAL1 | C147: ST6GAL1 | D147: ST6GAL1 | E147: PsychENCODE_DLPFC_bulk | L147: <10 common SNPs
A148: eQTL colocalization | B148: GCST90432107_B3GALT5 | C148: B3GALT5 | D148: B3GALT5 | E148: Brain_Amygdala | F148: 6907 | G148: 1.0064976e-25 | H148: 0.52638554 | I148: 8.4046284e-26 | J148: 0.43951736 | K148: 0.0340971 | L148: OK
A149: eQTL colocalization | B149: GCST90432107_B3GALT5 | C149: B3GALT5 | D149: B3GALT5 | E149: Brain_Cerebellum | F149: 6917 | G149: 1.09884e-25 | H149: 0.57467923 | I149: 7.4628597e-26 | J149: 0.39026293 | K149: 0.035057834 | L149: OK
A150: eQTL colocalization | B150: GCST90432107_B3GALT5 | C150: B3GALT5 | D150: B3GALT5 | E150: Brain_Cortex | F150: 6917 | G150: 3.3563013e-26 | H150: 0.17553025 | I150: 1.527219e-25 | J150: 0.79869012 | K150: 0.02577963 | L150: OK
A151: eQTL colocalization | B151: GCST90432107_B3GALT5 | C151: B3GALT5 | D151: B3GALT5 | E151: Brain_Frontal_Cortex_BA9 | F151: 6917 | G151: 9.337594e-26 | H151: 0.48834416 | I151: 8.4156341e-26 | J151: 0.44005524 | K151: 0.071600601 | L151: OK
A152: eQTL colocalization | B152: GCST90432107_B3GALT5 | C152: B3GALT5 | D152: B3GALT5 | E152: Brain_Hippocampus | F152: 6908 | G152: 9.9472729e-26 | H152: 0.52022971 | I152: 8.5326907e-26 | J152: 0.44621531 | K152: 0.033554982 | L152: OK
A153: eQTL colocalization | B153: GCST90432107_B3GALT5 | C153: B3GALT5 | D153: B3GALT5 | E153: Brain_Hypothalamus | F153: 6917 | G153: 1.0014758e-25 | H153: 0.52375897 | I153: 8.5298314e-26 | J153: 0.44606905 | K153: 0.030171984 | L153: OK
A154: eQTL colocalization | B154: GCST90432107_B3GALT5 | C154: B3GALT5 | D154: B3GALT5 | E154: Brain_Putamen_basal_ganglia | F154: 6917 | G154: 1.0608367e-25 | H154: 0.55480399 | I154: 7.7458359e-26 | J154: 0.40505714 | K154: 0.040138869 | L154: OK
A155: eQTL colocalization | B155: GCST90432107_B3GALT5 | C155: B3GALT5 | D155: B3GALT5 | E155: Liver | F155: 6918 | G155: 1.1363392e-25 | H155: 0.59429081 | I155: 7.114068e-26 | J155: 0.37202292 | K155: 0.033686272 | L155: OK
A156: eQTL colocalization | B156: GCST90432107_B3GALT5 | C156: B3GALT5 | D156: B3GALT5 | E156: Lung | F156: 6918 | G156: 8.9823099e-26 | H156: 0.46976325 | I156: 5.5733425e-26 | J156: 0.29123965 | K156: 0.2389971 | L156: OK
A157: eQTL colocalization | B157: GCST90432107_B3GALT5 | C157: B3GALT5 | D157: B3GALT5 | E157: Spleen | F157: 6918 | G157: 8.3166377e-38 | H157: 4.3494e-13 | I157: 1.9120929e-25 | J157: 1 | K157: 2.392e-14 | L157: OK
A158: eQTL colocalization | B158: GCST90432107_B3GALT5 | C158: B3GALT5 | D158: B3GALT5 | E158: Braineac2_putamen | F158: 5814 | G158: 1.130764e-25 | H158: 0.59138692 | I158: 7.0064959e-26 | J158: 0.36639588 | K158: 0.042217197 | L158: OK
A159: eQTL colocalization | B159: GCST90432107_B3GALT5 | C159: B3GALT5 | D159: B3GALT5 | E159: Braineac2_substantia_nigra | F159: 5455 | G159: 1.1450246e-25 | H159: 0.5988513 | I159: 6.7520254e-26 | J159: 0.35308488 | K159: 0.04806382 | L159: OK
... A215: eQTL colocalization | B215: GCST90432107_ST6GAL1 | C215: ST6GAL1 | D215: ST6GAL1 | E215: brainSCOPE_Lamp5 | F215: 23 | G215: 0.0064419219 | H215: 0.00020102947 | I215: 0.27246322 | J215: 0.0077895038 | K215: 0.71310433 | L215: OK
A216: eQTL colocalization | B216: GCST90432107_ST6GAL1 | C216: ST6GAL1 | D216: ST6GAL1 | E216: brainSCOPE_OPC | L216: <10 common SNPs
A217: eQTL colocalization | B217: GCST90432107_ST6GAL1 | C217: ST6GAL1 | D217: ST6GAL1 | E217: brainSCOPE_Sst__Sst.Chodl | F217: 54 | G217: 8.299967e-10 | H217: 3.572128e-11 | I217: 0.51128858 | J217: 0.021537597 | K217: 0.46717382 | L217: OK
A218: eQTL colocalization | B218: GCST90432107_ST6GAL1 | C218: ST6GAL1 | D218: ST6GAL1 | E218: brainSCOPE_Vip | F218: 40 | G218: 4.8391186e-08 | H218: 9.903792e-10 | I218: 0.95739042 | J218: 0.019571017 | K218: 0.023038514 | L218: OK
A219: eQTL colocalization | B219: GCST90432107_ST6GAL1 | C219: ST6GAL1 | D219: ST6GAL1 | E219: PsychENCODE_DLPFC_bulk | F219: 72 | G219: 6.0354312e-10 | H219: 6.362163e-11 | I219: 0.76447008 | J219: 0.080430416 | K219: 0.1550995 | L219: OK
A220: eQTL colocalization | B220: J10_INFLUENZA_B3GALT5 | C220: B3GALT5 | D220: B3GALT5 | E220: Brain_Amygdala | F220: 7265 | G220: 0.022517119 | H220: 0.49392638 | I220: 0.019654815 | J220: 0.43110724 | K220: 0.032794439 | L220: OK
A221: eQTL colocalization | B221: J10_INFLUENZA_B3GALT5 | C221: B3GALT5 | D221: B3GALT5 | E221: Brain_Cerebellum | F221: 7276 | G221: 0.024573154 | H221: 0.53906268 | I221: 0.017536105 | J221: 0.38465637 | K221: 0.034171689 | L221: OK
A222: eQTL colocalization | B222: J10_INFLUENZA_B3GALT5 | C222: B3GALT5 | D222: B3GALT5 | E222: Brain_Cortex | F222: 7276 | G222: 0.0068705806 | H222: 0.15072016 | I222: 0.035916166 | J222: 0.78787555 | K222: 0.018617541 | L222: OK
A223: eQTL colocalization | B223: J10_INFLUENZA_B3GALT5 | C223: B3GALT5 | D223: B3GALT5 | E223: Brain_Frontal_Cortex_BA9 | F223: 7276 | G223: 0.020046262 | H223: 0.43975572 | I223: 0.021025083 | J223: 0.46117016 | K223: 0.058002775 | L223: OK
A224: eQTL colocalization | B224: J10_INFLUENZA_B3GALT5 | C224: B3GALT5 | D224: B3GALT5 | E224: Brain_Hippocampus | F224: 7267 | G224: 0.02217748 | H224: 0.48649742 | I224: 0.020029032 | J224: 0.43933591 | K224: 0.03196015 | L224: OK
...

Sheet Supplementary Table 12
A1: Supplementary Table 12. SuSiE fine-mapped credible sets and brain chromatin annotations at the ST6GAL1 and B3GALT5 influenza loci.
A3: Dataset | B3: Credible set | C3: SNP | D3: Position | E3: z | F3: PIP | G3: cCRE ID | H3: cCRE class | I3: Chromatin states
A4: ST6GAL1_GWAS | B4: ST6GAL1_GWAS_CS3 | C4: 3:186931889:A:G | D4: 186931889 | E4: -4.8786811 | F4: 0.7506943
A5: ST6GAL1_GWAS | B5: ST6GAL1_GWAS_CS3 | C5: 3:186931894:A:G | D5: 186931894 | E5: -4.8786614 | F5: 0.74930475
A6: ST6GAL1_GWAS | B6: ST6GAL1_GWAS_CS1 | C6: 3:186933001:A:G | D6: 186933001 | E6: 4.8829387 | F6: 1 | G6: EH38D5523319 | H6: dELS | I6: Brain Angular Gyrus: Active TSS; Brain Angular Gyrus (v1): Weak transcription; Brain Anterior Caudate: Active TSS; Brain Cingulate Gyrus: Active TSS; Brain Cortex: Flanking TSS; Brain Hippocampus Middle: Active TSS; Brain Substantia Nigra: Active TSS
A7: ST6GAL1_GWAS | B7: ST6GAL1_GWAS_CS2 | C7: 3:186941996:A:G | D7: 186941996 | E7: -5.3118914 | F7: 1
A8: ST6GAL1_L6.IT_neuron | B8: ST6GAL1_L6.IT_neuron_CS2 | C8: 3:186922899:T:A | D8: 186922899 | E8: 4.3909086 | F8: 1
A9: ST6GAL1_L6.IT_neuron | B9: ST6GAL1_L6.IT_neuron_CS4 | C9: 3:186926674:A:G | D9: 186926674 | E9: -4.5557592 | F9: 1
A10: ST6GAL1_L6.IT_neuron | B10: ST6GAL1_L6.IT_neuron_CS1 | C10: 3:186931889:A:G | D10: 186931889 | E10: -5.7878494 | F10: 0.5
A11: ST6GAL1_L6.IT_neuron | B11: ST6GAL1_L6.IT_neuron_CS1 | C11: 3:186931894:A:G | D11: 186931894 | E11: -5.7878494 | F11: 0.5
A12: ST6GAL1_L6.IT_neuron | B12: ST6GAL1_L6.IT_neuron_CS5 | C12: 3:186933001:A:G | D12: 186933001 | E12: 5.5476698 | F12: 1 | G12: EH38D5523319 | H12: dELS | I12: Brain Angular Gyrus: Active TSS; Brain Angular Gyrus (v1): Weak transcription; Brain Anterior Caudate: Active TSS; Brain Cingulate Gyrus: Active TSS; Brain Cortex: Flanking TSS; Brain Hippocampus Middle: Active TSS; Brain Substantia Nigra: Active TSS
A13: ST6GAL1_L6.IT_neuron | B13: ST6GAL1_L6.IT_neuron_CS3 | C13: 3:186941077:G:C | D13: 186941077 | E13: 5.2531508 | F13: 1
A14: ST6GAL1_Lung | B14: ST6GAL1_Lung_CS2 | C14: 3:186907279:C:G | D14: 186907279 | E14: 5.1263529 | F14: 0.99999859
A15: ST6GAL1_Lung | B15: ST6GAL1_Lung_CS1 | C15: 3:186922899:T:A | D15: 186922899 | E15: 5.244719 | F15: 1
A16: ST6GAL1_Lung | B16: ST6GAL1_Lung_CS3 | C16: 3:186924322:T:G | D16: 186924322 | E16: -5.244719 | F16: 1
A17: B3GALT5_GWAS | B17: B3GALT5_GWAS_CS1 | C17: 21:39670772:G:A | D17: 39670772 | E17: -11.18003 | F17: 0.98740867
A18: B3GALT5_GWAS | B18: B3GALT5_GWAS_CS2 | C18: 21:39683309:A:G | D18: 39683309 | E18: -10.412592 | F18: 0.12706088
A19: B3GALT5_GWAS | B19: B3GALT5_GWAS_CS2 | C19: 21:39683882:G:T | D19: 39683882 | E19: -10.445707 | F19: 0.14404066
A20: B3GALT5_GWAS | B20: B3GALT5_GWAS_CS2 | C20: 21:39684411:G:A | D20: 39684411 | E20: -10.431398 | F20: 0.13640861
A21: B3GALT5_GWAS | B21: B3GALT5_GWAS_CS2 | C21: 21:39694299:A:G | D21: 39694299 | E21: -9.2336398 | F21: 0.33538017
A22: B3GALT5_GWAS | B22: B3GALT5_GWAS_CS2 | C22: 21:39697333:T:G | D22: 39697333 | E22: -9.034797 | F22: 0.20535415
A23: B3GALT5_GWAS | B23: B3GALT5_GWAS_CS2 | C23: 21:39698266:C:T | D23: 39698266 | E23: -8.9118414 | F23: 0.10899746
A24: B3GALT5_Lung | B24: B3GALT5_Lung_CS1 | C24: 21:39598257:G:T | D24: 39598257 | E24: 3.6611661 | F24: 0.96328348
A25: B3GALT5_Lung | B25: B3GALT5_Lung_CS2 | C25: 21:39640448:C:T | D25: 39640448 | E25: 3.1302882 | F25: 0.97593184
A27: Note: Fine-mapped credible sets from SuSiE summary-statistic fine-mapping of the ST6GAL1 and B3GALT5 loci in the influenza GWAS and in the lung and L6.IT neuron eQTL datasets that colocalized with the GWAS signal. Each row is a SNP assigned to a credible set (CS); PIP is the marginal posterior inclusion probability, not the within-single-effect alpha weight and z its signed fine-mapping z score. SNPs are listed by credible set; sets with a single SNP at PIP = 1 contain one candidate causal variant. The cCRE columns report the candidate cis-regulatory element (cCRE) of the encyclopedia of DNA elements (ENCODE) overlapping the SNP, and the Chromatin states column the chromatin state annotations of seven adult brain regions from the Roadmap Epigenomics Consortium in the format tissue: state, separated by semicolons; these annotations are available only for SNPs examined in the targeted annotation panel (the GWAS lead SNPs and shared fine-mapped SNPs). NA, not available. Abbreviations: cCRE, candidate cis-regulatory element; CS, credible set; eQTL, expression quantitative trait locus; GWAS, genome-wide association study; PIP, posterior inclusion probability; SNP, single-nucleotide polymorphism.

Sheet Supplementary Table 13
A1: Supplementary Table 13. Predicted enhancer-to-gene links at the ST6GAL1 and B3GALT5 influenza GWAS loci.
A3: Source | B3: Gene | C3: Gene ENSG | D3: Enhancer | E3: CHR | F3: Start | G3: End | H3: Score | I3: Gene rank | J3: Genome percentile | K3: Distance to SNP | L3: In cis window | M3: Nearest in cis | N3: Only cis link | O3: In SNP atac peak | P3: Liftover
A4: EpiMap_FOCS_brain | B4: B3GALT5 | C4: ENSG00000183778 | D4: chunk1983_3759_1 | E4: chr21 | F4: 38912949 | G4: 38913080 | H4: 0.01432949 | I4: 29 | J4: 0.19485711 | L4: No | M4: No | N4: No | O4: No | P4: ok
A5: EpiMap_FOCS_brain | B5: B3GALT5 | C5: ENSG00000183778 | D5: chunk1983_4636_1 | E5: chr21 | F5: 39209015 | G5: 39209162 | H5: 0.01406842 | I5: 34 | J5: 0.13427693 | L5: No | M5: No | N5: No | O5: No | P5: ok
A6: EpiMap_FOCS_brain | B6: B3GALT5 | C6: ENSG00000183778 | D6: chunk1983_4837_1 | E6: chr21 | F6: 39345780 | G6: 39345980 | H6: 0.028053827 | I6: 21 | J6: 0.36474304 | L6: No | M6: No | N6: No | O6: No | P6: ok
A7: EpiMap_FOCS_brain | B7: B3GALT5 | C7: ENSG00000183778 | D7: chunk1983_5175_1 | E7: chr21 | F7: 39523520 | G7: 39523706 | H7: 0.04222333 | I7: 14 | J7: 0.48870926 | L7: No | M7: No | N7: No | O7: No | P7: ok
A8: EpiMap_FOCS_brain | B8: B3GALT5 | C8: ENSG00000183778 | D8: chunk1983_5183_1 | E8: chr21 | F8: 39527230 | G8: 39528000 | H8: 0.098397218 | I8: 8 | J8: 0.69033881 | L8: No | M8: No | N8: No | O8: No | P8: ok
A9: EpiMap_FOCS_brain | B9: B3GALT5 | C9: ENSG00000183778 | D9: chunk1983_5184_1 | E9: chr21 | F9: 39527818 | G9: 39528000 | H9: 0.084931643 | I9: 10 | J9: 0.65931761 | L9: No | M9: No | N9: No | O9: No | P9: ok
A10: EpiMap_FOCS_brain | B10: B3GALT5 | C10: ENSG00000183778 | D10: chunk1983_5186_1 | E10: chr21 | F10: 39528080 | G10: 39528360 | H10: 0.11600483 | I10: 2 | J10: 0.72746434 | L10: No | M10: No | N10: No | O10: No | P10: ok
A11: EpiMap_FOCS_brain | B11: B3GALT5 | C11: ENSG00000183778 | D11: chunk1983_5189_1 | E11: chr21 | F11: 39528340 | G11: 39528524 | H11: 0.050332161 | I11: 12 | J11: 0.54663954 | L11: No | M11: No | N11: No | O11: No | P11: ok
A12: EpiMap_FOCS_brain | B12: B3GALT5 | C12: ENSG00000183778 | D12: chunk1983_5206_1 | E12: chr21 | F12: 39537640 | G12: 39537920 | H12: 0.03002741 | I12: 16 | J12: 0.43714916 | L12: No | M12: No | N12: No | O12: No | P12: ok
A13: EpiMap_FOCS_brain | B13: B3GALT5 | C13: ENSG00000183778 | D13: chunk1983_5208_1 | E13: chr21 | F13: 39538732 | G13: 39538940 | H13: 0.015764319 | I13: 24 | J13: 0.30103641 | L13: No | M13: No | N13: No | O13: No | P13: ok
A14: EpiMap_FOCS_brain | B14: B3GALT5 | C14: ENSG00000183778 | D14: chunk1983_5222_1 | E14: chr21 | F14: 39556277 | G14: 39556460 | H14: 0.014430793 | I14: 28 | J14: 0.21153758 | L14: No | M14: No | N14: No | O14: No | P14: ok
A15: EpiMap_FOCS_brain | B15: B3GALT5 | C15: ENSG00000183778 | D15: chunk1983_5281_1 | E15: chr21 | F15: 39601040 | G15: 39601460 | H15: 0.013912587 | I15: 36 | J15: 0.081415342 | L15: No | M15: No | N15: No | O15: No | P15: ok
... A42: EpiMap_FOCS_brain | B42: B3GALT5 | C42: ENSG00000183778 | D42: chunk1983_5517_1 | E42: chr21 | F42: 39676180 | G42: 39676403 | H42: 0.013770379 | I42: 38 | J42: 0.018073619 | L42: No | M42: No | N42: No | O42: No | P42: ok
A43: EpiMap_FOCS_brain | B43: ST6GAL1 | C43: ENSG00000073849 | D43: chunk2262_4168_1 | E43: chr3 | F43: 186933260 | G43: 186933660 | H43: 0.74156147 | I43: 1 | J43: 0.98839518 | K43: 259 | L43: Yes | M43: Yes | N43: No | O43: No | P43: ok
A44: EpiMap_FOCS_brain | B44: ST6GAL1 | C44: ENSG00000073849 | D44: chunk2262_4170_1 | E44: chr3 | F44: 186933520 | G44: 186933880 | H44: 0.68915344 | I44: 2 | J44: 0.98258364 | K44: 519 | L44: Yes | M44: No | N44: No | O44: No | P44: ok
A45: EpiMap_FOCS_brain | B45: ST6GAL1 | C45: ENSG00000073849 | D45: chunk2262_4171_1 | E45: chr3 | F45: 186933920 | G45: 186934120 | H45: 0.27920518 | I45: 35 | J45: 0.87988917 | K45: 919 | L45: Yes | M45: No | N45: No | O45: No | P45: ok
A46: EpiMap_FOCS_brain | B46: ST6GAL1 | C46: ENSG00000073849 | D46: chunk2262_4173_1 | E46: chr3 | F46: 186934400 | G46: 186934780 | H46: 0.05138048 | I46: 165 | J46: 0.54831201 | K46: 1399 | L46: Yes | M46: No | N46: No | O46: No | P46: ok
A47: EpiMap_FOCS_brain | B47: ST6GAL1 | C47: ENSG00000073849 | D47: chunk2262_4179_1 | E47: chr3 | F47: 186935591 | G47: 186935980 | H47: 0.27194408 | I47: 38 | J47: 0.87573969 | K47: 2590 | L47: Yes | M47: No | N47: No | O47: No | P47: ok
A48: EpiMap_FOCS_brain | B48: ST6GAL1 | C48: ENSG00000073849 | D48: chunk2262_4182_1 | E48: chr3 | F48: 186935973 | G48: 186936260 | H48: 0.27656067 | I48: 36 | J48: 0.87851036 | K48: 2972 | L48: Yes | M48: No | N48: No | O48: No | P48: ok
A49: EpiMap_FOCS_brain | B49: ST6GAL1 | C49: ENSG00000073849 | D49: chunk2262_4151_1 | E49: chr3 | F49: 186929781 | G49: 186929960 | H49: 0.33755025 | I49: 22 | J49: 0.90707975 | K49: 3041 | L49: Yes | M49: No | N49: No | O49: No | P49: ok
A50: EpiMap_FOCS_brain | B50: ST6GAL1 | C50: ENSG00000073849 | D50: chunk2262_4150_1 | E50: chr3 | F50: 186929560 | G50: 186929759 | H50: 0.23837914 | I50: 50 | J50: 0.85410261 | K50: 3242 | L50: Yes | M50: No | N50: No | O50: No | P50: ok
A51: EpiMap_FOCS_brain | B51: ST6GAL1 | C51: ENSG00000073849 | D51: chunk2262_4148_1 | E51: chr3 | F51: 186929460 | G51: 186929540 | H51: 0.04258017 | I51: 180 | J51: 0.49720544 | K51: 3461 | L51: Yes | M51: No | N51: No | O51: No | P51: ok
A52: EpiMap_FOCS_brain | B52: ST6GAL1 | C52: ENSG00000073849 | D52: chunk2262_4147_1 | E52: chr3 | F52: 186929274 | G52: 186929475 | H52: 0.073462208 | I52: 142 | J52: 0.63590988 | K52: 3526 | L52: Yes | M52: No | N52: No | O52: No | P52: ok
A53: EpiMap_FOCS_brain | B53: ST6GAL1 | C53: ENSG00000073849 | D53: chunk2262_4191_1 | E53: chr3 | F53: 186938420 | G53: 186938680 | H53: 0.052972434 | I53: 160 | J53: 0.55055009 | K53: 5419 | L53: Yes | M53: No | N53: No | O53: No | P53: ok
A54: EpiMap_FOCS_brain | B54: ST6GAL1 | C54: ENSG00000073849 | D54: chunk2262_4192_1 | E54: chr3 | F54: 186938573 | G54: 186938765 | H54: 0.053558698 | I54: 159 | J54: 0.55131726 | K54: 5572 | L54: Yes | M54: No | N54: No | O54: No | P54: ok
... A262: EpiMap_FOCS_brain | B262: ST6GAL1 | C262: ENSG00000073849 | D262: chunk2263_186_1 | E262: chr3 | F262: 187929501 | G262: 187929755 | H262: 0.015257564 | I262: 206 | J262: 0.2832999 | K262: 996500 | L262: Yes | M262: No | N262: No | O262: No | P262: ok
A263: PEC_INT16_HiC | B263: ST6GAL1 | C263: ENSG00000073849 | D263: EH37E1230348 | E263: chr3 | F263: 186929090 | G263: 186929593 | K263: 3408 | L263: Yes | M263: Yes | N263: Yes | O263: No | P263: native_hg38
A265: Note: Predicted enhancer-to-gene links supporting the ST6GAL1 and B3GALT5 loci, from the EpiMap FOCS brain enhancer-gene linking model (FOCS_predicted_links) and, for ST6GAL1, an independent promoter-capture Hi-C interaction from the PEC INT16 resource. Score is the linking score from the source model; Gene_rank and Genome_percentile rank the link among all links to the gene and across the genome respectively. Distance_to_SNP is the distance from the enhancer to the marginal SNP within the GWAS-eQTL overlap (rs55958900), not the genome-wide lead rs13322149 (NA for links not anchored to a SNP window). In_cis_window indicates the enhancer lies within the cis-linkage window of the locus; Nearest_in_cis marks the link to the nearest gene within the cis window; Only_cis_link indicates the enhancer is linked to only one gene in the cis window; In_SNP_atac_peak indicates overlap with an accessible chromatin peak at the lead SNP. Coordinates are on GRCh38. Abbreviations: GWAS, genome-wide association study; Hi-C, high-throughput chromosome conformation capture; PEC, PsychENCODE; SNP, single-nucleotide polymorphism.

Sheet Supplementary Table 14
A1: Supplementary Table 14. Single-nucleus ATAC-sequencing chromatin accessibility and accessibility-expression associations at the ST6GAL1 locus.
A3: Block | B3: Cell type | C3: Region | D3: Start | E3: End | F3: Signal | G3: Background | H3: Fold enrichment | I3: Analysis family | J3: Test | K3: n | L3: beta (SE) | M3: P | N3: Spearman rho | O3: Spearman P | P3: FDR
A4: Locus chromatin accessibility | B4: L6IT | C4: snp_rs10937275 | D4: 186932502 | E4: 186933502 | F4: 0.43232887 | G4: 0.0348 | H4: 12.423243
A5: Locus chromatin accessibility | B5: L6IT | C5: pec_enhancer | D5: 186929091 | E5: 186929594 | F5: 0.96075159 | G5: 0.0348 | H5: 27.607804
A6: Locus chromatin accessibility | B6: L6IT | C6: lead_snp | D6: 186977021 | E6: 186978021 | F6: 0.078615784 | G6: 0.0348 | H6: 2.2590742
A7: Locus chromatin accessibility | B7: L4IT | C7: snp_rs10937275 | D7: 186932502 | E7: 186933502 | F7: 0.2807043 | G7: 0.025 | H7: 11.228172
A8: Locus chromatin accessibility | B8: L4IT | C8: pec_enhancer | D8: 186929091 | E8: 186929594 | F8: 0.64387897 | G8: 0.025 | H8: 25.755158
A9: Locus chromatin accessibility | B9: L4IT | C9: lead_snp | D9: 186977021 | E9: 186978021 | F9: 0.057192807 | G9: 0.025 | H9: 2.2877122
A10: Locus chromatin accessibility | B10: L5IT | C10: snp_rs10937275 | D10: 186932502 | E10: 186933502 | F10: 0.43085874 | G10: 0.0294 | H10: 14.655059
A11: Locus chromatin accessibility | B11: L5IT | C11: pec_enhancer | D11: 186929091 | E11: 186929594 | F11: 0.731375 | G11: 0.0294 | H11: 24.8767
A12: Locus chromatin accessibility | B12: L5IT | C12: lead_snp | D12: 186977021 | E12: 186978021 | F12: 0.23474266 | G12: 0.0294 | H12: 7.9844441
A13: Locus chromatin accessibility | B13: L6CT | C13: snp_rs10937275 | D13: 186932502 | E13: 186933502 | F13: 0.48208282 | G13: 0.033100002 | H13: 14.564435
A14: Locus chromatin accessibility | B14: L6CT | C14: pec_enhancer | D14: 186929091 | E14: 186929594 | F14: 0.98262342 | G14: 0.033100002 | H14: 29.686507
A15: Locus chromatin accessibility | B15: L6CT | C15: lead_snp | D15: 186977021 | E15: 186978021 | F15: 0.21781189 | G15: 0.033100002 | H15: 6.5804193
... A30: Locus chromatin accessibility | B30: Astro | C30: lead_snp | D30: 186977021 | E30: 186978021 | F30: 1.6929818 | G30: 0.023399999 | H30: 72.349652
A31: Locus chromatin accessibility | B31: Micro-PVM | C31: snp_rs10937275 | D31: 186932502 | E31: 186933502 | F31: 0.73244955 | G31: 0
A32: Locus chromatin accessibility | B32: Micro-PVM | C32: pec_enhancer | D32: 186929091 | E32: 186929594 | F32: 0.51959048 | G32: 0
A33: Locus chromatin accessibility | B33: Micro-PVM | C33: lead_snp | D33: 186977021 | E33: 186978021 | F33: 1.4685267 | G33: 0
A34: Cell-type comparison | B34: Astro | C34: lead_snp | H34: 72.349652
A35: Cell-type comparison | B35: L4IT | C35: lead_snp | H35: 2.2877122
A36: Cell-type comparison | B36: L5IT | C36: lead_snp | H36: 7.9844441
A37: Cell-type comparison | B37: L6CT | C37: lead_snp | H37: 6.5804193
A38: Cell-type comparison | B38: L6IT | C38: lead_snp | H38: 2.2590742
A39: Cell-type comparison | B39: Micro-PVM | C39: lead_snp
A40: Cell-type comparison | B40: OPC | C40: lead_snp | H40: 29.937064
A41: Cell-type comparison | B41: Oligo | C41: lead_snp | H41: 4.1398602
A42: Cell-type comparison | B42: Pvalb | C42: lead_snp | H42: 14.458941
A43: Cell-type comparison | B43: Sst | C43: lead_snp | H43: 2.8075259
A44: Cell-type comparison | B44: Astro | C44: pec_enhancer | H44: 2.5416667
A45: Cell-type comparison | B45: L4IT | C45: pec_enhancer | H45: 25.755158
A46: Cell-type comparison | B46: L5IT | C46: pec_enhancer | H46: 24.8767
A47: Cell-type comparison | B47: L6CT | C47: pec_enhancer | H47: 29.686507
A48: Cell-type comparison | B48: L6IT | C48: pec_enhancer | H48: 27.607804
A49: Cell-type comparison | B49: Micro-PVM | C49: pec_enhancer
A50: Cell-type comparison | B50: OPC | C50: pec_enhancer | H50: 18.916667
A51: Cell-type comparison | B51: Oligo | C51: pec_enhancer | H51: 3.1329365
A52: Cell-type comparison | B52: Pvalb | C52: pec_enhancer | H52: 12.603572
A53: Cell-type comparison | B53: Sst | C53: pec_enhancer | H53: 12.047619
A54: Cell-type comparison | B54: Astro | C54: snp_rs10937275 | H54: 28.425575
A55: Cell-type comparison | B55: L4IT | C55: snp_rs10937275 | H55: 11.228172
A56: Cell-type comparison | B56: L5IT | C56: snp_rs10937275 | H56: 14.655059
A57: Cell-type comparison | B57: L6CT | C57: snp_rs10937275 | H57: 14.564435
A58: Cell-type comparison | B58: L6IT | C58: snp_rs10937275 | H58: 12.423243
A59: Cell-type comparison | B59: Micro-PVM | C59: snp_rs10937275
A60: Cell-type comparison | B60: OPC | C60: snp_rs10937275 | H60: 20.587413
A61: Cell-type comparison | B61: Oligo | C61: snp_rs10937275 | H61: 3.0889111
A62: Cell-type comparison | B62: Pvalb | C62: snp_rs10937275 | H62: 9.5448554
A63: Cell-type comparison | B63: Sst | C63: snp_rs10937275 | H63: 8.0023311
A64: Peak-expression association tests | B64: L6 IT | I64: celltype_specificity | J64: target:ST6GAL1 | K64: 79 | L64: 0.0893 (0.2120) | M64: 0.67497305 | N64: -0.029284323 | O64: 0.79780339 | P64: 0.88957522
A65: Peak-expression association tests | B65: L6 IT | I65: celltype_specificity | J65: lead_negctrl:ST6GAL1 | K65: 79 | L65: -0.0343 (0.0835) | M65: 0.68267655 | N65: -0.08936222 | O65: 0.43352291 | P65: 0.88957522
A66: Peak-expression association tests | B66: Oligodendrocyte | I66: celltype_specificity | J66: target:ST6GAL1 | K66: 80 | L66: 0.8292 (0.5571) | M66: 0.14094249 | N66: 0.039217065 | O66: 0.72980838 | P66: 0.88957522
A67: Peak-expression association tests | B67: Oligodendrocyte | I67: celltype_specificity | J67: lead_negctrl:ST6GAL1 | K67: 80 | L67: -0.0203 (0.1457) | M67: 0.88957522 | N67: -0.082900158 | O67: 0.46473549 | P67: 0.88957522
A68: Peak-expression association tests | B68: Astrocyte | I68: celltype_specificity | J68: target:ST6GAL1 | K68: 84 | L68: -0.1368 (0.6200) | M68: 0.82589846 | N68: 0.011501468 | O68: 0.917299 | P68: 0.88957522
A69: Peak-expression association tests | B69: Astrocyte | I69: celltype_specificity | J69: lead_negctrl:ST6GAL1 | K69: 84 | L69: -0.0597 (0.2190) | M69: 0.78571958 | N69: 0.0230844 | O69: 0.83489354 | P69: 0.88957522
A70: Peak-expression association tests | B70: Microglia-PVM | I70: celltype_specificity | J70: target:ST6GAL1 | K70: 80 | L70: 0.2168 (0.2383) | M70: 0.36614043 | N70: -0.09052977 | O70: 0.42451031 | P70: 0.88957522
A71: Peak-expression association tests | B71: Microglia-PVM | I71: celltype_specificity | J71: lead_negctrl:ST6GAL1 | K71: 80 | L71: -0.0390 (0.0690) | M71: 0.57383757 | N71: -0.10794908 | O71: 0.34052981 | P71: 0.88957522
A72: Peak-expression association tests | B72: L6 IT | I72: gene_specificity | J72: target:ADIPOQ | K72: 79 | L72: 0.0948 (0.0771) | M72: 0.22303351 | N72: 0.17034796 | O72: 0.13336943 | P72: 0.50182539
A73: Peak-expression association tests | B73: L6 IT | I73: gene_specificity | J73: target:ADIPOQ-AS1 | K73: 79 | L73: 0.0348 (0.0338) | M73: 0.30724631 | N73: 0.018695894 | O73: 0.87009459 | P73: 0.55304335
A74: Peak-expression association tests | B74: L6 IT | I74: gene_specificity | J74: target:AHSG | K74: 79 | L74: 0.0235 (0.1442) | M74: 0.87128967 | N74: -0.013612235 | O74: 0.90522368 | P74: 0.9944795
A75: Peak-expression association tests | B75: L6 IT | I75: gene_specificity | J75: target:BCL6 | K75: 79 | L75: -0.0878 (0.3259) | M75: 0.78834645 | N75: -0.03164557 | O75: 0.7818891 | P75: 0.9675161
... A85: Peak-expression association tests | B85: L6 IT | I85: gene_specificity | J85: target:LINC02020 | K85: 79 | L85: -0.0561 (0.0950) | M85: 0.55681835 | N85: 0.011709146 | O85: 0.91842505 | P85: 0.83522753
A86: Peak-expression association tests | B86: L6 IT | I86: gene_specificity | J86: target:LINC02041 | K86: 79 | L86: 0.0000 (0.0000)
A87: Peak-expression association tests | B87: L6 IT | I87: gene_specificity | J87: target:LINC02043 | K87: 79 | L87: -0.1267 (0.1675) | M87: 0.45185109 | N87: -0.07899221 | O87: 0.48894382 | P87: 0.71764585
A88: Peak-expression association tests | B88: L6 IT | I88: gene_specificity | J88: target:LINC02051 | K88: 79 | L88: -0.0140 (0.0119) | M88: 0.24277235 | N88: -0.21916503 | O88: 0.05230733 | P88: 0.50421949
A89: Peak-expression association tests | B89: L6 IT | I89: gene_specificity | J89: target:LINC02052 | K89: 79 | L89: 0.0844 (0.0617) | M89: 0.17574241 | N89: 0.16356679 | O89: 0.14976525 | P89: 0.49050651
A90: Peak-expression association tests | B90: L6 IT | I90: gene_specificity | J90: target:MASP1 | K90: 79 | L90: 0.0028 (0.0966) | M90: 0.97728947 | N90: 0.015185876 | O90: 0.89432684 | P90: 0.99946606
A91: Peak-expression association tests | B91: L6 IT | I91: gene_specificity | J91: target:RFC4 | K91: 79 | L91: -0.2584 (0.1916) | M91: 0.18166908 | N91: -0.062560857 | O91: 0.58387937 | P91: 0.49050651
A92: Peak-expression association tests | B92: L6 IT | I92: gene_specificity | J92: target:RPL39L | K92: 79 | L92: 0.3023 (0.1712) | M92: 0.081603671 | N92: 0.055306719 | O92: 0.62830615 | P92: 0.39894815
A93: Peak-expression association tests | B93: L6 IT | I93: gene_specificity | J93: target:RTP1 | K93: 79 | L93: -0.1427 (0.1153) | M93: 0.219894 | N93: -0.042475468 | O93: 0.71013075 | P93: 0.50182539
A94: Peak-expression association tests | B94: L6 IT | I94: gene_specificity | J94: target:RTP2 | K94: 79 | L94: 0.0117 (0.0113) | M94: 0.30417276 | N94: 0.075679027 | O94: 0.50740743 | P94: 0.55304335
A95: Peak-expression association tests | B95: L6 IT | I95: gene_specificity | J95: target:RTP4 | K95: 79 | L95: -0.0258 (0.0167) | M95: 0.12736711 | N95: -0.17450869 | O95: 0.12400628 | P95: 0.49050651
A96: Peak-expression association tests | B96: L6 IT | I96: gene_specificity | J96: target:SST | K96: 79 | L96: 0.0512 (0.1387) | M96: 0.71327207 | N96: 0.077987038 | O96: 0.49450764 | P96: 0.91706409
A97: Peak-expression association tests | B97: L6 IT | I97: gene_specificity | J97: target:ST6GAL1 | K97: 79 | L97: 0.0893 (0.2120) | M97: 0.67497305 | N97: -0.029284323 | O97: 0.79780339 | P97: 0.91121361
A98: Peak-expression association tests | B98: L6 IT | I98: gene_specificity | J98: target:TBCCD1 | K98: 79 | L98: -0.0218 (0.1764) | M98: 0.90182236 | N98: 0.01436222 | O98: 0.90002802 | P98: 0.9944795
A99: Peak-expression association tests | B99: L6 IT | I99: gene_specificity | J99: target:LIFR | K99: 79 | L99: 0.3813 (0.1769) | M99: 0.034470003 | N99: 0.20900682 | O99: 0.06452192 | P99: 0.28279207
A100: Peak-expression association tests | B100: L6 IT | I100: gene_specificity | J100: target:LINC02110 | K100: 79 | L100: 0.0000 (0.0000)
A101: Peak-expression association tests | B101: L6 IT | I101: background_peaks | J101: rand:chr5:87265668-87269667 | K101: 79 | L101: 0.6357 (0.2627) | M101: 0.018067975 | N101: 0.17125122 | O101: 0.13129253 | P101: 0.95466802
A102: Peak-expression association tests | B102: L6 IT | I102: background_peaks | J102: rand:chr9:27570584-27575036 | K102: 79 | L102: -0.1421 (0.2521) | M102: 0.5747259 | N102: -0.0022882181 | O102: 0.98403222 | P102: 0.95466802
A103: Peak-expression association tests | B103: L6 IT | I103: background_peaks | J103: rand:chr19:55254144-55260324 | K103: 79 | L103: -0.0224 (0.2528) | M103: 0.92975146 | N103: 0.0048442064 | O103: 0.96620358 | P103: 0.97609565
A104: Peak-expression association tests | B104: L6 IT | I104: background_peaks | J104: rand:chr19:795370-799818 | K104: 79 | L104: 0.2534 (0.2783) | M104: 0.3655439 | N104: 0.053675755 | O104: 0.63848707 | P104: 0.95466802
A105: Peak-expression association tests | B105: L6 IT | I105: background_peaks | J105: rand:chr11:131909133-131915643 | K105: 79 | L105: -0.1743 (0.2092) | M105: 0.4074585 | N105: -0.10326193 | O105: 0.36514392 | P105: 0.95466802
A106: Peak-expression association tests | B106: L6 IT | I106: background_peaks | J106: rand:chr19:33298036-33304710 | K106: 79 | L106: -0.1190 (0.2311) | M106: 0.60816876 | N106: -0.11467868 | O106: 0.31424022 | P106: 0.95466802
A107: Peak-expression association tests | B107: L6 IT | I107: background_peaks | J107: rand:chr3:195540169-195547236 | K107: 79 | L107: -0.3204 (0.2353) | M107: 0.17763977 | N107: -0.18950828 | O107: 0.094379778 | P107: 0.95466802
A108: Peak-expression association tests | B108: L6 IT | I108: background_peaks | J108: rand:chr1:33429530-33437570 | K108: 79 | L108: 0.0453 (0.2119) | M108: 0.83137488 | N108: 0.022176241 | O108: 0.84618461 | P108: 0.95700794
A109: Peak-expression association tests | B109: L6 IT | I109: background_peaks | J109: rand:chr2:73279543-73287268 | K109: 79 | L109: -0.2271 (0.1998) | M109: 0.25938188 | N109: -0.11097858 | O109: 0.33021115 | P109: 0.95466802
A110: Peak-expression association tests | B110: L6 IT | I110: background_peaks | J110: rand:chr10:73768817-73775769 | K110: 79 | L110: -0.4038 (0.2588) | M110: 0.12309635 | N110: -0.16655307 | O110: 0.14236831 | P110: 0.95466802
A111: Peak-expression association tests | B111: L6 IT | I111: background_peaks | J111: rand:chr18:34975520-34980435 | K111: 79 | L111: 0.6284 (0.2677) | M111: 0.021674556 | N111: 0.23600292 | O111: 0.036270582 | P111: 0.95466802
A112: Peak-expression association tests | B112: L6 IT | I112: background_peaks | J112: rand:chr16:75647032-75650869 | K112: 79 | L112: -0.4454 (0.2489) | M112: 0.077718292 | N112: -0.1662853 | O112: 0.14302013 | P112: 0.95466802
... A500: Peak-expression association tests | B500: Microglia-PVM | I500: background_peaks | J500: rand:chr6:13409622-13415812 | K500: 80 | L500: -0.1606 (0.1753) | M500: 0.36271234 | N500: 0.071425223 | O500: 0.52895829 | P500: 0.95466802
A502: Note: Single-nucleus ATAC-sequencing (snATAC-seq) support for the ST6GAL1 locus in human cortex. The locus chromatin accessibility block reports chromatin accessibility signal at the lead SNP, the linked PsychENCODE enhancer and the fine-mapped SNP rs10937275 in each cell type, with the background accessibility and the fold enrichment of signal over background. The cell-type comparison block reports the same fold enrichments side by side across cell types (NA indicates cell types without data). The peak-expression association tests block reports linear and Spearman correlations between peak accessibility and ST6GAL1 expression across donor nuclei within each cell type: the analysis-family labels are celltype_specificity, gene_specificity and background_peaks; beta (SE) is the slope of the accessibility-expression regression, P values are two-sided, and FDR was computed by the Benjamini-Hochberg procedure within each analysis family. Abbreviations: ATAC-seq, assay for transposase-accessible chromatin using sequencing; FDR, false discovery rate; SE, standard error; SNP, single-nucleotide polymorphism.

Sheet Supplementary Table 15
A1: Supplementary Table 15. Summary-data-based Mendelian randomization of brain cell-type-specific ST6GAL1 and B3GALT5 expression on influenza and COVID-19.
A3: Cell type | B3: Gene | C3: GWAS | D3: b_SMR (SE) | E3: P_SMR | F3: P_HEIDI | G3: nSNP HEIDI | H3: Top SNP | I3: Status | J3: Significant
A4: Astro | B4: B3GALT5 | C4: COVID19_HGI_B2 | D4: 0.0078 (0.0214) | E4: 0.7162509 | F4: 0.4139484 | G4: 5 | H4: rs613758 | I4: ok | J4: No
A5: Chandelier / Pvalb | B5: B3GALT5 | C5: COVID19_HGI_B2 | D5: 0.0071 (0.0211) | E5: 0.7355925 | F5: 0.2075901 | G5: 9 | H5: rs1475593 | I5: ok | J5: No
A6: L2.3.IT | B6: B3GALT5 | C6: COVID19_HGI_B2 | D6: 0.0110 (0.0161) | E6: 0.496208 | F6: 0.4477685 | G6: 13 | H6: rs6517553 | I6: ok | J6: No
A7: L4.IT | B7: B3GALT5 | C7: COVID19_HGI_B2 | D7: 0.0100 (0.0146) | E7: 0.496007 | F7: 0.5767213 | G7: 14 | H7: rs6517553 | I7: ok | J7: No
A8: L5.6.NP | B8: B3GALT5 | C8: COVID19_HGI_B2 | I8: error | J8: No
A9: L5.IT | B9: B3GALT5 | C9: COVID19_HGI_B2 | I9: error | J9: No
A10: L6.CT | B10: B3GALT5 | C10: COVID19_HGI_B2 | I10: error | J10: No
A11: L6.IT | B11: B3GALT5 | C11: COVID19_HGI_B2 | D11: 0.0062 (0.0183) | E11: 0.7354815 | F11: 0.2977766 | G11: 10 | H11: rs1475593 | I11: ok | J11: No
A12: L6b | B12: B3GALT5 | C12: COVID19_HGI_B2 | I12: error | J12: No
A13: Lamp5 | B13: B3GALT5 | C13: COVID19_HGI_B2 | I13: error | J13: No
A14: Lamp5.Lhx6 | B14: B3GALT5 | C14: COVID19_HGI_B2 | I14: error | J14: No
A15: Micro.PVM | B15: B3GALT5 | C15: COVID19_HGI_B2 | I15: error | J15: No
A16: OPC | B16: B3GALT5 | C16: COVID19_HGI_B2 | I16: error | J16: No
A17: Oligo | B17: B3GALT5 | C17: COVID19_HGI_B2 | I17: error | J17: No
A18: PC | B18: B3GALT5 | C18: COVID19_HGI_B2 | I18: error | J18: No
A19: Sst / Sst.Chodl | B19: B3GALT5 | C19: COVID19_HGI_B2 | I19: error | J19: No
A20: Vip | B20: B3GALT5 | C20: COVID19_HGI_B2 | D20: 0.0084 (0.0214) | E20: 0.6959852 | H20: rs3787927 | I20: ok | J20: No
A21: Astro | B21: B3GALT5 | C21: J10_INFLUENZA | D21: -0.0292 (0.0393) | E21: 0.4571443 | F21: 0.6202938 | G21: 5 | H21: rs613758 | I21: ok | J21: No
A22: Chandelier / Pvalb | B22: B3GALT5 | C22: J10_INFLUENZA | D22: 0.0151 (0.0286) | E22: 0.5969982 | F22: 0.5362723 | G22: 9 | H22: rs1475593 | I22: ok | J22: No
A23: L2.3.IT | B23: B3GALT5 | C23: J10_INFLUENZA | D23: 0.0141 (0.0254) | E23: 0.5796605 | F23: 0.3069686 | G23: 13 | H23: rs6517553 | I23: ok | J23: No
A24: L4.IT | B24: B3GALT5 | C24: J10_INFLUENZA | D24: 0.0128 (0.0231) | E24: 0.5795433 | F24: 0.18748 | G24: 14 | H24: rs6517553 | I24: ok | J24: No
A25: L5.6.NP | B25: B3GALT5 | C25: J10_INFLUENZA | I25: error | J25: No
A26: L5.IT | B26: B3GALT5 | C26: J10_INFLUENZA | I26: error | J26: No
A27: L6.CT | B27: B3GALT5 | C27: J10_INFLUENZA | I27: error | J27: No
A28: L6.IT | B28: B3GALT5 | C28: J10_INFLUENZA | D28: 0.0131 (0.0247) | E28: 0.5966055 | F28: 0.3542772 | G28: 10 | H28: rs1475593 | I28: ok | J28: No
A29: L6b | B29: B3GALT5 | C29: J10_INFLUENZA | I29: error | J29: No
A30: Lamp5 | B30: B3GALT5 | C30: J10_INFLUENZA | I30: error | J30: No
A31: Lamp5.Lhx6 | B31: B3GALT5 | C31: J10_INFLUENZA | I31: error | J31: No
A32: Micro.PVM | B32: B3GALT5 | C32: J10_INFLUENZA | I32: error | J32: No
A33: OPC | B33: B3GALT5 | C33: J10_INFLUENZA | I33: error | J33: No
A34: Oligo | B34: B3GALT5 | C34: J10_INFLUENZA | I34: error | J34: No
A35: PC | B35: B3GALT5 | C35: J10_INFLUENZA | I35: error | J35: No
A36: Sst / Sst.Chodl | B36: B3GALT5 | C36: J10_INFLUENZA | I36: error | J36: No
A37: Vip | B37: B3GALT5 | C37: J10_INFLUENZA | D37: 0.0183 (0.0344) | E37: 0.5952182 | H37: rs3787927 | I37: ok | J37: No
A38: Astro | B38: ST6GAL1 | C38: COVID19_HGI_B2 | I38: error | J38: No
A39: Chandelier / Pvalb | B39: ST6GAL1 | C39: COVID19_HGI_B2 | D39: 0.0092 (0.0129) | E39: 0.4768537 | F39: 0.8477275 | G39: 20 | H39: rs1468906 | I39: ok | J39: No
A40: L2.3.IT | B40: ST6GAL1 | C40: COVID19_HGI_B2 | D40: 0.0104 (0.0146) | E40: 0.4771214 | F40: 0.9741256 | G40: 20 | H40: rs1468906 | I40: ok | J40: No
A41: L4.IT | B41: ST6GAL1 | C41: COVID19_HGI_B2 | D41: 0.0092 (0.0130) | E41: 0.4768544 | F41: 0.9290953 | G41: 20 | H41: rs1468906 | I41: ok | J41: No
A42: L5.6.NP | B42: ST6GAL1 | C42: COVID19_HGI_B2 | I42: error | J42: No
A43: L5.IT | B43: ST6GAL1 | C43: COVID19_HGI_B2 | D43: 0.0098 (0.0137) | E43: 0.4769474 | F43: 0.9737634 | G43: 20 | H43: rs1468906 | I43: ok | J43: No
A44: L6.CT | B44: ST6GAL1 | C44: COVID19_HGI_B2 | I44: error | J44: No
A45: L6.IT | B45: ST6GAL1 | C45: COVID19_HGI_B2 | D45: 0.0222 (0.0183) | E45: 0.2254354 | F45: 0.5652411 | G45: 18 | H45: rs13064443 | I45: ok | J45: No
A46: L6b | B46: ST6GAL1 | C46: COVID19_HGI_B2 | I46: error | J46: No
A47: Lamp5 | B47: ST6GAL1 | C47: COVID19_HGI_B2 | D47: 0.0231 (0.0192) | E47: 0.2293053 | F47: 0.587046 | G47: 11 | H47: rs13064443 | I47: ok | J47: No
A48: Lamp5.Lhx6 | B48: ST6GAL1 | C48: COVID19_HGI_B2 | I48: error | J48: No
A49: Micro.PVM | B49: ST6GAL1 | C49: COVID19_HGI_B2 | I49: error | J49: No
A50: OPC | B50: ST6GAL1 | C50: COVID19_HGI_B2 | D50: 0.0065 (0.0190) | E50: 0.7299857 | F50: 0.8051178 | G50: 3 | H50: rs28366037 | I50: ok | J50: No
A51: Oligo | B51: ST6GAL1 | C51: COVID19_HGI_B2 | I51: error | J51: No
A52: PC | B52: ST6GAL1 | C52: COVID19_HGI_B2 | I52: error | J52: No
A53: Sst / Sst.Chodl | B53: ST6GAL1 | C53: COVID19_HGI_B2 | D53: 0.0074 (0.0126) | E53: 0.5566845 | F53: 0.927663 | G53: 16 | H53: rs2041965 | I53: ok | J53: No
A54: Vip | B54: ST6GAL1 | C54: COVID19_HGI_B2 | D54: 0.0067 (0.0153) | E54: 0.6602098 | F54: 0.9682439 | G54: 15 | H54: rs1981767 | I54: ok | J54: No
A55: Astro | B55: ST6GAL1 | C55: J10_INFLUENZA | I55: error | J55: No
A56: Chandelier / Pvalb | B56: ST6GAL1 | C56: J10_INFLUENZA | D56: 0.0711 (0.0221) | E56: 0.001302781 | F56: 0.08156285 | G56: 20 | H56: rs1468906 | I56: ok | J56: Yes
A57: L2.3.IT | B57: ST6GAL1 | C57: J10_INFLUENZA | I57: error | J57: No
A58: L4.IT | B58: ST6GAL1 | C58: J10_INFLUENZA | D58: 0.0713 (0.0222) | E58: 0.001303279 | F58: 0.03118047 | G58: 20 | H58: rs1468906 | I58: ok | J58: Yes
A59: L5.6.NP | B59: ST6GAL1 | C59: J10_INFLUENZA | I59: error | J59: No
A60: L5.IT | B60: ST6GAL1 | C60: J10_INFLUENZA | I60: error | J60: No
A61: L6.CT | B61: ST6GAL1 | C61: J10_INFLUENZA | I61: error | J61: No
A62: L6.IT | B62: ST6GAL1 | C62: J10_INFLUENZA | D62: 0.1524 (0.0379) | E62: 5.872723e-05 | F62: 0.04161848 | G62: 18 | H62: rs13064443 | I62: ok | J62: Yes
A63: L6b | B63: ST6GAL1 | C63: J10_INFLUENZA | I63: error | J63: No
A64: Lamp5 | B64: ST6GAL1 | C64: J10_INFLUENZA | D64: 0.1584 (0.0429) | E64: 0.0002227048 | F64: 0.03855388 | G64: 11 | H64: rs13064443 | I64: ok | J64: Yes
A65: Lamp5.Lhx6 | B65: ST6GAL1 | C65: J10_INFLUENZA | I65: error | J65: No
A66: Micro.PVM | B66: ST6GAL1 | C66: J10_INFLUENZA | I66: error | J66: No
A67: OPC | B67: ST6GAL1 | C67: J10_INFLUENZA | D67: 0.1049 (0.0357) | E67: 0.003290814 | F67: 0.1122045 | G67: 3 | H67: rs28366037 | I67: ok | J67: Yes
A68: Oligo | B68: ST6GAL1 | C68: J10_INFLUENZA | I68: error | J68: No
A69: PC | B69: ST6GAL1 | C69: J10_INFLUENZA | I69: error | J69: No
A70: Sst / Sst.Chodl | B70: ST6GAL1 | C70: J10_INFLUENZA | D70: 0.0694 (0.0216) | E70: 0.001338463 | F70: 0.0166273 | G70: 16 | H70: rs2041965 | I70: ok | J70: Yes
A71: Vip | B71: ST6GAL1 | C71: J10_INFLUENZA | D71: 0.0391 (0.0204) | E71: 0.05453118 | F71: 0.04436729 | G71: 15 | H71: rs1981767 | I71: ok | J71: No
A73: Note: Summary-data-based Mendelian randomization (SMR) testing whether the cis-regulatory expression of ST6GAL1 and B3GALT5 in each brain cell type has a causal effect on influenza (FinnGen J10_INFLUENZA) or COVID-19 (COVID-19 HGI B2), using brain cell-type-specific eQTL instruments. b_SMR is the SMR effect estimate (SE) on the liability scale; P values are two-sided. The HEIDI test (P_HEIDI) distinguishes a single shared causal variant from linkage-driven associations; a low P_HEIDI suggests the signal is driven by two distinct variants in linkage disequilibrium. Significant indicates the original study thresholds; HEIDI P < 0.05 is a linkage alert, and four of the six ST6GAL1 associations did not pass this threshold; all significant associations are for ST6GAL1 in J10_INFLUENZA. Rows with Status error could not be computed because of missing cell-type eQTL reference data and are retained for completeness. NA, not computed. Abbreviations: eQTL, expression quantitative trait locus; GWAS, genome-wide association study; HEIDI, heterogeneity in dependent instruments; SE, standard error; SMR, summary-data-based Mendelian randomization; SNP, single-nucleotide polymorphism.

Sheet Supplementary Table 16
A1: Supplementary Table 16. Bidirectional two-sample Mendelian randomization between influenza and the psychiatric disorder GWAS datasets.
A3: Block | B3: Direction | C3: Panel | D3: Exposure | E3: Outcome | F3: nSNP | G3: IVW OR (95% CI) | H3: IVW P | I3: MR-Egger OR | J3: MR-Egger P | K3: Weighted median OR | L3: Weighted median P | M3: Egger intercept | N3: Egger intercept P | O3: Q P (IVW) | P3: MR-PRESSO global P | Q3: Steiger passed | R3: Meta OR (95% CI) | S3: Meta P | T3: Meta FDR | U3: nSNP total | V3: Panels | W3: n IVs | X3: Instrument R2 | Y3: Detectable OR upper | Z3: Detectable OR lower | AA3: Power
A4: Per-panel MR | B4: Forward | C4: Primary | D4: Influenza | E4: Attention deficit hyperactivity disorder | F4: 12 | G4: 1.0519 (0.9466, 1.1691) | H4: 0.34698215 | I4: 1.222357 | J4: 0.18280175 | K4: 1.0251186 | L4: 0.68494525 | M4: -0.016 | N4: 0.274 | O4: 0.037 | P4: 0.044 | Q4: Yes
A5: Per-panel MR | B5: Forward | C5: Primary | D5: Influenza | E5: Anorexia nervosa | F5: 12 | G5: 1.0443 (0.9327, 1.1693) | H5: 0.45206108 | I5: 0.91671122 | J5: 0.58461072 | K5: 1.0102545 | L5: 0.87948484 | M5: 0.013 | N5: 0.382 | O5: 0.132 | P5: 0.118 | Q5: Yes
A6: Per-panel MR | B6: Forward | C6: Replication | D6: Influenza | E6: Anorexia nervosa | F6: 12 | G6: 1.0849 (0.9431, 1.2481) | H6: 0.25415495 | I6: 0.75001155 | J6: 0.10218155 | K6: 1.1522583 | L6: 0.093154589 | M6: 0.038 | N6: 0.032 | O6: 0.115 | P6: 0.13 | Q6: Yes
A7: Per-panel MR | B7: Forward | C7: Primary | D7: Influenza | E7: Anxiety disorder | F7: 13 | G7: 1.0277 (0.9768, 1.0812) | H7: 0.29206402 | I7: 0.95128773 | J7: 0.49481391 | K7: 1.0147839 | L7: 0.62059034 | M7: 0.008 | N7: 0.266 | O7: 0.07 | P7: 0.071 | Q7: Yes
A8: Per-panel MR | B8: Forward | C8: Primary | D8: Influenza | E8: Autism spectrum disorder | F8: 13 | G8: 0.9483 (0.7910, 1.1369) | H8: 0.5660089 | I8: 0.78228436 | J8: 0.34437312 | K8: 1.0191412 | L8: 0.82653344 | M8: 0.02 | N8: 0.421 | O8: 0.002 | P8: 0.004 | Q8: Yes
A9: Per-panel MR | B9: Forward | C9: Replication | D9: Influenza | E9: Bipolar disorder | F9: 13 | G9: 0.9968 (0.9009, 1.1029) | H9: 0.95032289 | I9: 0.98227987 | J9: 0.90475166 | K9: 1.0467337 | L9: 0.40569649 | M9: 0.002 | N9: 0.916 | O9: 0.041 | P9: 0.051 | Q9: Yes
A10: Per-panel MR | B10: Forward | C10: Primary | D10: Influenza | E10: Major depressive disorder | F10: 9 | G10: 1.0222 (0.9377, 1.1144) | H10: 0.61751866 | I10: 0.90101708 | J10: 0.38486283 | K10: 1.0168163 | L10: 0.7525213 | M10: 0.013 | N10: 0.264 | O10: 0.191 | P10: 0.207 | Q10: Yes
A11: Per-panel MR | B11: Forward | C11: Primary | D11: Influenza | E11: Parkinson disease | F11: 13 | G11: 0.8183 (0.6756, 0.9912) | H11: 0.040316233 | I11: 0.925508 | J11: 0.76786703 | K11: 0.94611087 | L11: 0.6744908 | M11: -0.013 | N11: 0.613 | O11: 0.554 | P11: 0.573 | Q11: Yes
A12: Per-panel MR | B12: Forward | C12: Replication | D12: Influenza | E12: Major depressive disorder | F12: 13 | G12: 1.0834 (0.9986, 1.1754) | H12: 0.054025574 | I12: 0.97200727 | J12: 0.756941 | K12: 1.0315882 | L12: 0.51924094 | M12: 0.016 | N12: 0.202 | O12: 0.08 | P12: 0.117 | Q12: Yes
A13: Per-panel MR | B13: Forward | C13: Replication | D13: Influenza | E13: Autism spectrum disorder | F13: 12 | G13: 0.9571 (0.7977, 1.1483) | H13: 0.637161 | I13: 0.85356897 | J13: 0.53620774 | K13: 0.97088879 | L13: 0.71508056 | M13: 0.012 | N13: 0.626 | O13: 0.001 | P13: 0.002 | Q13: Yes
A14: Per-panel MR | B14: Forward | C14: Primary | D14: Influenza | E14: Opiate dependence | F14: 13 | G14: 1.0017 (0.9208, 1.0896) | H14: 0.96901757 | I14: 0.99622378 | J14: 0.97365205 | K14: 1.0114598 | L14: 0.84857408 | M14: 0.001 | N14: 0.959 | O14: 0.664 | P14: 0.672 | Q14: Yes
A15: Per-panel MR | B15: Forward | C15: Replication | D15: Influenza | E15: Alzheimers disease | F15: 12 | G15: 0.9867 (0.9164, 1.0624) | H15: 0.72231708 | I15: 1.0710739 | J15: 0.49449832 | K15: 1.0138757 | L15: 0.76030944 | M15: -0.009 | N15: 0.379 | O15: 0.232 | P15: 0.233 | Q15: Yes
... A30: Per-panel MR | B30: Forward | C30: Replication | D30: Influenza | E30: Obsessive-compulsive disorder | F30: 12 | G30: 0.9287 (0.6821, 1.2643) | H30: 0.63823838 | I30: 0.74298762 | J30: 0.52692873 | K30: 0.82120687 | L30: 0.32893722 | M30: 0.024 | N30: 0.609 | O30: 0.257 | P30: 0.262 | Q30: Yes
A31: Per-panel MR | B31: Forward | C31: Replication | D31: Influenza | E31: Opiate dependence | F31: 2 | G31: 1.0041 (0.9670, 1.0426) | H31: 0.83198286 | O31: 0.15 | Q31: Yes
A32: Per-panel MR | B32: Forward | C32: Replication | D32: Influenza | E32: Post traumatic stress disorder | F32: 13 | G32: 1.1280 (1.0024, 1.2694) | H32: 0.045553772 | I32: 1.1151405 | J32: 0.5078791 | K32: 1.0865133 | L32: 0.31472519 | M32: 0.001 | N32: 0.939 | O32: 0.635 | P32: 0.666 | Q32: Yes
A33: Per-panel MR | B33: Forward | C33: Primary | D33: Influenza | E33: Post traumatic stress disorder | F33: 13 | G33: 1.0042 (0.9902, 1.0183) | H33: 0.55969357 | I33: 1.0124132 | J33: 0.53336716 | K33: 1.0094295 | L33: 0.34535596 | M33: -0.001 | N33: 0.655 | O33: 0.571 | P33: 0.584 | Q33: Yes
A34: Per-panel MR | B34: Forward | C34: Primary | D34: Influenza | E34: Suicide attempt | F34: 11 | G34: 0.9952 (0.9214, 1.0749) | H34: 0.90251199 | I34: 1.1668273 | J34: 0.1774414 | K34: 0.95399458 | L34: 0.38759321 | M34: -0.017 | N34: 0.14 | O34: 0.376 | P34: 0.372 | Q34: Yes
A35: Per-panel MR | B35: Forward | C35: Replication | D35: Influenza | E35: Suicide attempt | F35: 11 | G35: 1.0079 (0.9295, 1.0929) | H35: 0.84842467 | I35: 1.1644613 | J35: 0.20625528 | K35: 0.9462758 | L35: 0.31962029 | M35: -0.015 | N35: 0.2 | O35: 0.381 | P35: 0.366 | Q35: Yes
A36: Per-panel MR | B36: Forward | C36: Primary | D36: Influenza | E36: Tourette syndrome | F36: 12 | G36: 1.0290 (0.8085, 1.3096) | H36: 0.81638647 | I36: 1.3825071 | J36: 0.34926768 | K36: 1.224293 | L36: 0.20125778 | M36: -0.032 | N36: 0.357 | O36: 0.206 | P36: 0.223 | Q36: Yes
A37: Per-panel MR | B37: Reverse | C37: Primary | D37: Attention deficit hyperactivity disorder | E37: Influenza | F37: 123 | G37: 1.0338 (0.9778, 1.0930) | H37: 0.24208671 | I37: 0.95716196 | J37: 0.67289342 | K37: 1.0703819 | L37: 0.062880605 | M37: 0.005 | N37: 0.44 | O37: 0.007 | P37: 0.007 | Q37: Yes
A38: Per-panel MR | B38: Reverse | C38: Primary | D38: Anorexia nervosa | E38: Influenza | F38: 67 | G38: 1.0150 (0.9488, 1.0857) | H38: 0.66527951 | I38: 1.0290819 | J38: 0.80912855 | K38: 1.0160587 | L38: 0.71502831 | M38: -0.001 | N38: 0.903 | O38: 0.027 | P38: 0.035 | Q38: Yes
A39: Per-panel MR | B39: Reverse | C39: Replication | D39: Anorexia nervosa | E39: Influenza | F39: 52 | G39: 1.0354 (0.9823, 1.0914) | H39: 0.19482111 | I39: 1.0722391 | J39: 0.54858001 | K39: 1.0435067 | L39: 0.26555296 | M39: -0.003 | N39: 0.757 | O39: 0.836 | P39: 0.871 | Q39: Yes
A40: Per-panel MR | B40: Reverse | C40: Primary | D40: Anxiety disorder | E40: Influenza | F40: 199 | G40: 1.2240 (1.1377, 1.3169) | H40: 6.0646703e-08 | I40: 1.1932238 | J40: 0.15363614 | K40: 1.2196843 | L40: 0.00018345197 | M40: 0.001 | N40: 0.829 | O40: 0.222 | P40: 0.228 | Q40: Yes
A41: Per-panel MR | B41: Reverse | C41: Primary | D41: Autism spectrum disorder | E41: Influenza | F41: 35 | G41: 1.0433 (0.9641, 1.1291) | H41: 0.29265684 | I41: 1.0203988 | J41: 0.86418155 | K41: 1.0328202 | L41: 0.51553505 | M41: 0.002 | N41: 0.841 | O41: 0.052 | P41: 0.054 | Q41: Yes
A42: Per-panel MR | B42: Reverse | C42: Replication | D42: Bipolar disorder | E42: Influenza | F42: 176 | G42: 1.0223 (0.9791, 1.0674) | H42: 0.31600635 | I42: 0.96201673 | J42: 0.64010306 | K42: 1.0168387 | L42: 0.58170136 | M42: 0.004 | N42: 0.446 | O42: 0.042 | P42: 0.042 | Q42: Yes
A43: Per-panel MR | B43: Reverse | C43: Primary | D43: Major depressive disorder | E43: Influenza | F43: 34 | G43: 1.0643 (0.9248, 1.2249) | H43: 0.38455873 | I43: 1.0092523 | J43: 0.9616743 | K43: 1.0551655 | L43: 0.51038054 | M43: 0.003 | N43: 0.764 | O43: 0.004 | P43: 0.006 | Q43: Yes
... A69: Per-panel MR | B69: Reverse | C69: Primary | D69: Tourette syndrome | E69: Influenza | F69: 22 | G69: 0.9886 (0.9569, 1.0212) | H69: 0.48848895 | I69: 1.01071 | J69: 0.68842362 | K69: 1.0071009 | L69: 0.76843678 | M69: -0.007 | N69: 0.287 | O69: 0.751 | P69: 0.666 | Q69: Yes
A70: Reverse meta-analysis | B70: Reverse | C70: Meta (fixed effect) | D70: Anxiety disorder | E70: Influenza | F70: 216 | R70: 1.2250 (1.1380, 1.3180) | S70: 5.5e-08 | T70: 8.8e-07 | V70: Primary;Replication
A71: Reverse meta-analysis | B71: Reverse | C71: Meta (fixed effect) | D71: Opiate dependence | E71: Influenza | F71: 65 | R71: 1.1410 (1.0530, 1.2350) | S71: 0.0012 | T71: 0.0096 | V71: Primary;Replication
A72: Reverse meta-analysis | B72: Reverse | C72: Meta (fixed effect) | D72: Suicide attempt | E72: Influenza | F72: 80 | R72: 1.0790 (1.0030, 1.1600) | S72: 0.041 | T72: 0.164 | V72: Primary;Replication
A73: Reverse meta-analysis | B73: Reverse | C73: Meta (fixed effect) | D73: Tobacco use disorder | E73: Influenza | F73: 75 | R73: 1.0580 (1.0080, 1.1100) | S73: 0.023 | T73: 0.12266667 | V73: Primary;Replication
A74: Reverse meta-analysis | B74: Reverse | C74: Meta (fixed effect) | D74: Post traumatic stress disorder | E74: Influenza | F74: 245 | R74: 1.0490 (0.9870, 1.1140) | S74: 0.12 | T74: 0.27428571 | V74: Primary;Replication
A75: Reverse meta-analysis | B75: Reverse | C75: Meta (fixed effect) | D75: Major depressive disorder | E75: Influenza | F75: 66 | R75: 1.0420 (0.9660, 1.1240) | S75: 0.28 | T75: 0.34461538 | V75: Primary;Replication
A76: Reverse meta-analysis | B76: Reverse | C76: Meta (fixed effect) | D76: Attention deficit hyperactivity disorder | E76: Influenza | F76: 198 | R76: 1.0360 (0.9810, 1.0940) | S76: 0.21 | T76: 0.28 | V76: Primary;Replication
A77: Reverse meta-analysis | B77: Reverse | C77: Meta (fixed effect) | D77: Autism spectrum disorder | E77: Influenza | F77: 78 | R77: 1.0360 (0.9810, 1.0940) | S77: 0.21 | T77: 0.28 | V77: Primary;Replication
A78: Reverse meta-analysis | B78: Reverse | C78: Meta (fixed effect) | D78: Bipolar disorder | E78: Influenza | F78: 353 | R78: 1.0290 (0.9990, 1.0610) | S78: 0.061 | T78: 0.1952 | V78: Primary;Replication
A79: Reverse meta-analysis | B79: Reverse | C79: Meta (fixed effect) | D79: Anorexia nervosa | E79: Influenza | F79: 119 | R79: 1.0280 (0.9860, 1.0710) | S79: 0.2 | T79: 0.28 | V79: Primary;Replication
A80: Reverse meta-analysis | B80: Reverse | C80: Meta (fixed effect) | D80: Schizophrenia | E80: Influenza | F80: 364 | R80: 1.0200 (0.9900, 1.0500) | S80: 0.19 | T80: 0.28 | V80: Primary;Replication
A81: Reverse meta-analysis | B81: Reverse | C81: Meta (fixed effect) | D81: Parkinson disease | E81: Influenza | F81: 89 | R81: 1.0050 (0.9800, 1.0320) | S81: 0.68 | T81: 0.68 | V81: Primary;Replication
... A85: Reverse meta-analysis | B85: Reverse | C85: Meta (fixed effect) | D85: Alzheimers disease | E85: Influenza | F85: 185 | R85: 0.9710 (0.9320, 1.0110) | S85: 0.16 | T85: 0.28 | V85: Primary;Replication
A86: Forward meta-analysis | B86: Forward | C86: Meta | D86: Influenza | E86: Sleep disorder | R86: 1.100 (1.022, 1.183) | S86: 0.010720018 | T86: 0.091120156 | U86: 26 | V86: 2
A87: Forward meta-analysis | B87: Forward | C87: Meta | D87: Influenza | E87: Anorexia nervosa | R87: 1.060 (0.971, 1.158) | S87: 0.19316602 | T87: 0.65676446 | U87: 24 | V87: 2
A88: Forward meta-analysis | B88: Forward | C88: Meta | D88: Influenza | E88: Major depressive disorder | R88: 1.054 (0.993, 1.118) | S88: 0.081189987 | T88: 0.46007659 | U88: 22 | V88: 2
A89: Forward meta-analysis | B89: Forward | C89: Meta | D89: Influenza | E89: Tobacco use disorder | R89: 1.029 (0.961, 1.102) | S89: 0.41071147 | T89: 0.78216431 | U89: 26 | V89: 2
A90: Forward meta-analysis | B90: Forward | C90: Meta | D90: Influenza | E90: Tourette syndrome | R90: 1.029 (0.808, 1.310) | S90: 0.81638647 | T90: 0.94523008 | U90: 12 | V90: 1
A91: Forward meta-analysis | B91: Forward | C91: Meta | D91: Influenza | E91: Alcohol dependence | R91: 1.019 (0.944, 1.100) | S91: 0.62950766 | T91: 0.89180251 | U91: 26 | V91: 2
A92: Forward meta-analysis | B92: Forward | C92: Meta | D92: Influenza | E92: Attention deficit hyperactivity disorder | R92: 1.018 (0.996, 1.041) | S92: 0.11022909 | T92: 0.46847365 | U92: 25 | V92: 2
A93: Forward meta-analysis | B93: Forward | C93: Meta | D93: Influenza | E93: Schizophrenia | R93: 1.009 (0.985, 1.033) | S93: 0.48669552 | T93: 0.78216431 | U93: 26 | V93: 2
A94: Forward meta-analysis | B94: Forward | C94: Meta | D94: Influenza | E94: Post-traumatic stress disorder | R94: 1.006 (0.992, 1.020) | S94: 0.41546415 | T94: 0.78216431 | U94: 26 | V94: 2
A95: Forward meta-analysis | B95: Forward | C95: Meta | D95: Influenza | E95: Opiate dependence | R95: 1.004 (0.970, 1.039) | S95: 0.83402654 | T95: 0.94523008 | U95: 15 | V95: 2
A96: Forward meta-analysis | B96: Forward | C96: Meta | D96: Influenza | E96: Alzheimer's disease | R96: 1.002 (0.985, 1.020) | S96: 0.77646104 | T96: 0.94523008 | U96: 21 | V96: 2
A97: Forward meta-analysis | B97: Forward | C97: Meta | D97: Influenza | E97: Anxiety disorder | R97: 1.002 (0.999, 1.005) | S97: 0.30309257 | T97: 0.78216431 | U97: 25 | V97: 2
... A102: Forward meta-analysis | B102: Forward | C102: Meta | D102: Influenza | E102: Parkinson disease | R102: 0.828 (0.731, 0.938) | S102: 0.0029591449 | T102: 0.050305464 | U102: 26 | V102: 2
A103: Forward power | B103: Forward | C103: Primary | D103: Influenza | E103: Attention deficit hyperactivity disorder | W103: 12 | X103: 0.00649 | Y103: 1.2 | Z103: 0.833 | AA103: 0.8
A104: Forward power | B104: Forward | C104: Primary | D104: Influenza | E104: Anorexia nervosa | W104: 12 | X104: 0.00613 | Y104: 1.233 | Z104: 0.811 | AA104: 0.8
A105: Forward power | B105: Forward | C105: Primary | D105: Influenza | E105: Anxiety disorder | W105: 13 | X105: 0.00701 | Y105: 1.105 | Z105: 0.905 | AA105: 0.8
A106: Forward power | B106: Forward | C106: Primary | D106: Influenza | E106: Autism spectrum disorder | W106: 13 | X106: 0.00701 | Y106: 1.359 | Z106: 0.736 | AA106: 0.8
A107: Forward power | B107: Forward | C107: Primary | D107: Influenza | E107: Major depressive disorder | W107: 9 | X107: 0.00492 | Y107: 1.133 | Z107: 0.883 | AA107: 0.8
A108: Forward power | B108: Forward | C108: Primary | D108: Influenza | E108: Parkinson disease | W108: 13 | X108: 0.00701 | Y108: 1.504 | Z108: 0.665 | AA108: 0.8
A109: Forward power | B109: Forward | C109: Primary | D109: Influenza | E109: Opiate dependence | W109: 13 | X109: 0.00701 | Y109: 1.282 | Z109: 0.78 | AA109: 0.8
A110: Forward power | B110: Forward | C110: Primary | D110: Influenza | E110: Alcohol dependence | W110: 13 | X110: 0.00701 | Y110: 1.302 | Z110: 0.768 | AA110: 0.8
A111: Forward power | B111: Forward | C111: Primary | D111: Influenza | E111: Alzheimers disease | W111: 9 | X111: 0.00499 | Y111: 1.165 | Z111: 0.858 | AA111: 0.8
A112: Forward power | B112: Forward | C112: Primary | D112: Influenza | E112: Tobacco use disorder | W112: 13 | X112: 0.00701 | Y112: 1.281 | Z112: 0.781 | AA112: 0.8
A113: Forward power | B113: Forward | C113: Primary | D113: Influenza | E113: Sleep disorder | W113: 13 | X113: 0.00701 | Y113: 1.419 | Z113: 0.705 | AA113: 0.8
A114: Forward power | B114: Forward | C114: Primary | D114: Influenza | E114: Obsessive-compulsive disorder | W114: 12 | X114: 0.00654 | Y114: 1.714 | Z114: 0.583 | AA114: 0.8
... A119: Forward power | B119: Forward | C119: Primary | D119: Influenza | E119: Tourette syndrome | W119: 12 | X119: 0.00654 | Y119: 1.734 | Z119: 0.577 | AA119: 0.8
A120: Forward power | W120: 12 | X120: 0.00649 | Y120: 1.325 | Z120: 0.754 | AA120: 0.8
A121: Forward power | B121: Forward | C121: Replication | D121: Influenza | E121: Bipolar disorder | W121: 13 | X121: 0.00701 | Y121: 1.338 | Z121: 0.748 | AA121: 0.8
A122: Forward power | B122: Forward | C122: Replication | D122: Influenza | E122: Major depressive disorder | W122: 13 | X122: 0.00701 | Y122: 1.253 | Z122: 0.798 | AA122: 0.8
A123: Forward power | B123: Forward | C123: Replication | D123: Influenza | E123: Autism spectrum disorder | W123: 12 | X123: 0.00652 | Y123: 1.337 | Z123: 0.748 | AA123: 0.8
A124: Forward power | B124: Forward | C124: Replication | D124: Influenza | E124: Alzheimers disease | W124: 12 | X124: 0.00652 | Y124: 1.133 | Z124: 0.882 | AA124: 0.8
A125: Forward power | B125: Forward | C125: Replication | D125: Influenza | E125: Anxiety disorder | W125: 12 | X125: 0.00652 | Y125: 1.28 | Z125: 0.781 | AA125: 0.8
A126: Forward power | B126: Forward | C126: Replication | D126: Influenza | E126: Attention deficit hyperactivity disorder | W126: 13 | X126: 0.00701 | Y126: 1.318 | Z126: 0.759 | AA126: 0.8
A127: Forward power | B127: Forward | C127: Replication | D127: Influenza | E127: Schizophrenia | W127: 13 | X127: 0.00701 | Y127: 1.384 | Z127: 0.722 | AA127: 0.8
A128: Forward power | B128: Forward | C128: Replication | D128: Influenza | E128: Sleep disorder | W128: 13 | X128: 0.00701 | Y128: 1.25 | Z128: 0.8 | AA128: 0.8
A129: Forward power | B129: Forward | C129: Replication | D129: Influenza | E129: Alcohol dependence | W129: 13 | X129: 0.00701 | Y129: 1.272 | Z129: 0.786 | AA129: 0.8
A130: Forward power | B130: Forward | C130: Replication | D130: Influenza | E130: Tobacco use disorder | W130: 13 | X130: 0.00701 | Y130: 1.281 | Z130: 0.781 | AA130: 0.8
A131: Forward power | B131: Forward | C131: Replication | D131: Influenza | E131: Parkinson disease | W131: 13 | X131: 0.00701 | Y131: 1.191 | Z131: 0.839 | AA131: 0.8
A132: Forward power | B132: Forward | C132: Replication | D132: Influenza | E132: Obsessive-compulsive disorder | W132: 12 | X132: 0.00654 | Y132: 1.932 | Z132: 0.518 | AA132: 0.8
... A135: Forward power | B135: Forward | C135: Replication | D135: Influenza | E135: Suicide attempt | W135: 11 | X135: 0.00602 | Y135: 1.223 | Z135: 0.818 | AA135: 0.8
A137: Note: Two-sample Mendelian randomization (MR) between influenza (FinnGen J10_INFLUENZA) and the psychiatric disorder GWAS datasets, in both directions. The per-panel MR block reports estimates for the primary and replication panels separately. Forward and reverse meta-analysis blocks report fixed-effect IVW composite estimates; because some panels share cohorts or are nested, these composites are descriptive rather than independent replication. FDR was computed by the Benjamini-Hochberg procedure within direction. Effect estimates are odds ratios (OR) per genetically higher liability to the exposure trait, with 95% confidence intervals in parentheses. MR-Egger and weighted median estimates are sensitivity analyses; the Egger intercept P value tests directional pleiotropy; the Q P value is Cochran's Q heterogeneity statistic for the IVW model; the MR-PRESSO global P value tests overall horizontal pleiotropy; Steiger filtering indicates whether the instrument explained more variance in the exposure than in the outcome (causal direction consistent). The forward power block reports, for each panel, the number of instrumental variants (n IVs), their combined R2, and the smallest and largest OR detectable at 80% power with alpha = 0.05 for the influenza-to-disorder direction. P values are two-sided. NA, not estimated or not applicable. Abbreviations: CI, confidence interval; FDR, false discovery rate; IVW, inverse variance weighted; MR, Mendelian randomization; OR, odds ratio; SNP, single-nucleotide polymorphism.

Sheet Supplementary Table 17
A1: Supplementary Table 17. Bias-corrected Mendelian randomization of the effect of psychiatric disorders on influenza by MRlap.
A3: Panel | B3: Trait | C3: GWAS accession | D3: n IVs | E3: Status | F3: Observed beta | G3: Observed SE | H3: Observed P | I3: MR-Egger beta | J3: Egger intercept P | K3: Corrected beta | L3: Corrected SE | M3: Corrected P | N3: FDR (panel) | O3: FDR (all) | P3: Difference statistic | Q3: Difference P | R3: h2 exposure | S3: h2 outcome | T3: rg | U3: Cross-trait intercept | V3: Polygenicity
A4: Primary | B4: Alcohol dependence | C4: GCST90435890 | D4: 3 | E4: ok | F4: 0.020961416 | G4: 0.084180163 | H4: 0.80335568 | I4: -0.59291015 | J4: 0.45344703 | K4: 0.03089591 | L4: 0.12607932 | M4: 0.80641666 | N4: 0.86844871 | O4: 0.87361805 | P4: -0.22679352 | Q4: 0.8205843 | R4: 0.010426024 | S4: 0.0065286423 | T4: 0.28991928 | U4: 0.0014636872 | V4: 0.0017312186
A5: Primary | B5: Alzheimer's disease | C5: GCST90449055 | D5: 34 | E5: ok | F5: -0.018910676 | G5: 0.017958201 | H5: 0.29232338 | I5: -0.034994263 | J5: 0.51418368 | K5: -0.021986061 | L5: 0.021136168 | M5: 0.29824218 | N5: 0.60211977 | O5: 0.65229641 | P5: 10.26374 | Q5: 1.026527e-24 | R5: 0.025130525 | S5: 0.0065286423 | T5: 0.094980937 | U5: 0.0001103926 | V5: 0.0016018596
A6: Primary | B6: Anorexia nervosa | C6: an_be2026 | D6: 10 | E6: ok | F6: 0.030414617 | G6: 0.086130151 | H6: 0.72399554 | I6: -0.66387425 | J6: 0.21698101 | K6: 0.045550427 | L6: 0.12789512 | M6: 0.72172483 | N6: 0.8420123 | O6: 0.81962207 | P6: -0.33139982 | Q6: 0.7403425 | R6: 0.011972125 | S6: 0.0065286423 | T6: 0.099533101 | U6: 0.00044620762 | V6: 0.0066574487
A7: Primary | B7: Anxiety disorder | C7: anx2026 | D7: 70 | E7: ok | F7: 0.12816323 | G7: 0.027553396 | H7: 3.2961022e-06 | I7: -0.4167306 | J7: 0.089646572 | K7: 0.16746847 | L7: 0.036033566 | M7: 3.3587042e-06 | N7: 2.351093e-05 | O7: 4.3663155e-05 | P7: -4.1085627 | Q7: 3.9812919e-05 | R7: 0.034768956 | S7: 0.0065286423 | T7: 0.36256698 | U7: 0.0031304069 | V7: 0.0081609952
A8: Primary | B8: ADHD | C8: ADHD2022 | D8: 26 | E8: ok | F8: 0.027099561 | G8: 0.032744142 | H8: 0.40788826 | I8: -0.0248899 | J8: 0.86349716 | K8: 0.039383161 | L8: 0.046708438 | M8: 0.39913329 | N8: 0.65885664 | O8: 0.78659416 | P8: -0.945519 | Q8: 0.34439398 | R8: 0.094671676 | S8: 0.0065286423 | T8: 0.31920545 | U8: -0.0032170691 | V8: 0.0077004383
A9: Primary | B9: Autism spectrum disorder | C9: asd2019 | D9: 2 | E9: ok | F9: -0.014595101 | G9: 0.093210723 | H9: 0.87557446 | K9: -0.027794877 | L9: 0.17382532 | M9: 0.8729589 | N9: 0.8729589 | O9: 0.90787726 | P9: 0.16187611 | Q9: 0.87140342 | R9: 0.20355068 | S9: 0.0065286423 | T9: -0.037925868 | U9: 0.0018962711 | V9: 0.0067117267
A10: Primary | B10: Bipolar disorder | C10: ieu_b_5110 | D10: 65 | E10: ok | F10: 0.015793795 | G10: 0.019470772 | H10: 0.41727722 | I10: -0.056318637 | J10: 0.65256503 | K10: 0.020680755 | L10: 0.025842017 | M10: 0.4235507 | N10: 0.65885664 | O10: 0.78659416 | P10: -0.77371905 | Q10: 0.43909695 | R10: 0.071816442 | S10: 0.0065286423 | T10: 0.19279226 | U10: 0.00063683109 | V10: 0.0082953989
A11: Primary | B11: Major depressive disorder | C11: GCST005839 | D11: 9 | E11: ok | F11: -0.062123997 | G11: 0.058742553 | H11: 0.29025436 | I11: -0.46771894 | J11: 0.69224428 | K11: -0.094167521 | L11: 0.091056734 | M11: 0.30105988 | N11: 0.60211977 | O11: 0.65229641 | P11: 1.0279019 | Q11: 0.30399596 | R11: 0.027588119 | S11: 0.0065286423 | T11: 0.3521324 | U11: -0.0027728639 | V11: 0.0061406381
A12: Primary | B12: Obsessive-compulsive disorder | C12: ieu_a_1189 | E12: no IV left after thresholding
A13: Primary | B13: Opiate dependence | C13: GCST90018994 | D13: 2 | E13: ok | F13: 0.055193555 | G13: 0.083676809 | H13: 0.50950801 | K13: 0.10827664 | L13: 0.15965702 | M13: 0.49765581 | N13: 0.69671814 | O13: 0.81962207 | P13: -0.69029132 | Q13: 0.49001101 | R13: 0.13870835 | S13: 0.0065286423 | T13: 0.42308011 | U13: -0.0075524276 | V13: 0.0081591711
A14: Primary | B14: Parkinson disease | C14: GCST009324 | D14: 19 | E14: ok | F14: 0.0033912456 | G14: 0.0081732872 | H14: 0.67820178 | I14: 0.064752818 | J14: 0.13263833 | K14: 0.0041707401 | L14: 0.010220517 | M14: 0.68321844 | N14: 0.8420123 | O14: 0.81962207 | P14: -0.52851715 | Q14: 0.59714045 | R14: 0.21877219 | S14: 0.0065286423 | T14: -0.058069402 | U14: 0.00042846651 | V14: 0.0012389706
A15: Primary | B15: PTSD | C15: ptsd2024 | D15: 88 | E15: ok | F15: 0.15295392 | G15: 0.033015863 | H15: 3.6085692e-06 | I15: 0.25477654 | J15: 0.7075512 | K15: 0.19653046 | L15: 0.042216359 | M15: 3.2348556e-06 | N15: 2.351093e-05 | O15: 4.3663155e-05 | P15: -3.7207058 | Q15: 0.00019866678 | R15: 0.028204447 | S15: 0.0065286423 | T15: 0.43510242 | U15: 0.0040495317 | V15: 0.008925336
A16: Primary | B16: Schizophrenia | C16: ieu_b_5102 | D16: 211 | E16: ok | F16: 0.0083667328 | G16: 0.0055960164 | H16: 0.13488234 | I16: 0.0095523752 | J16: 0.96104118 | K16: 0.010203491 | L16: 0.0068260585 | M16: 0.13497051 | N16: 0.37791743 | O16: 0.36845554 | P16: -2.1033062 | Q16: 0.035439011 | R16: 0.37695942 | S16: 0.0065286423 | T16: 0.14442376 | U16: -0.0014044914 | V16: 0.0084207392
A17: Primary | B17: Sleep disorder | C17: GCST90691931 | E17: insufficient IVs (1 left after pruning)
A18: Primary | B18: Suicide attempt | C18: sui2023 | D18: 5 | E18: ok | F18: 0.26905649 | G18: 0.10556437 | H18: 0.010811185 | I18: -0.69485873 | J18: 0.59732092 | K18: 0.4441717 | L18: 0.17432214 | M18: 0.010834446 | N18: 0.05056075 | O18: 0.056339122 | P18: -2.56547 | Q18: 0.010303614 | R18: 0.013422002 | S18: 0.0065286423 | T18: 0.37989736 | U18: -0.0018071746 | V18: 0.0057797195
A19: Primary | B19: Tobacco use disorder | C19: GCST90691929 | D19: 3 | E19: ok | F19: 0.23664979 | G19: 0.10179262 | H19: 0.020081444 | I19: -6.5967071 | J19: 0.45630243 | K19: 0.40829759 | L19: 0.17535806 | M19: 0.019892725 | N19: 0.069624536 | O19: 0.086201807 | P19: -2.2509097 | Q19: 0.02439126 | R19: 0.019350205 | S19: 0.0065286423 | T19: 0.3787991 | U19: 0.0010693976 | V19: 0.0049223232
A20: Primary | B20: Tourette syndrome | C20: ts2019 | E20: insufficient IVs (1 left after pruning)
A21: Replication | B21: Alcohol dependence | C21: GCST90691955 | D21: 2 | E21: ok | F21: -0.048314926 | G21: 0.093093937 | H21: 0.60376694 | K21: -0.078873766 | L21: 0.14909321 | M21: 0.59678936 | N21: 0.79096396 | O21: 0.81962207 | P21: 0.53993727 | Q21: 0.5892403 | R21: 0.013555418 | S21: 0.0065286423 | T21: 0.19211644 | U21: 0.0023810042 | V21: 0.0027758466
A22: Replication | B22: Alzheimer's disease | C22: GCST90027158 | D22: 60 | E22: ok | F22: -0.027129483 | G22: 0.018788573 | H22: 0.14875718 | I22: 0.0056443791 | J22: 0.49048106 | K22: -0.030677252 | L22: 0.020876841 | M22: 0.14171367 | N22: 0.34011281 | O22: 0.36845554 | P22: 2.5340144 | Q22: 0.011276409 | R22: 0.018911372 | S22: 0.0065286423 | T22: -0.1160468 | U22: 0.0052116637 | V22: 0.00086598167
A23: Replication | B23: Anorexia nervosa | C23: an2019 | D23: 10 | E23: ok | F23: 0.03145935 | G23: 0.02065053 | H23: 0.12765463 | I23: -0.15680405 | J23: 0.25233035 | K23: 0.04808205 | L23: 0.030424759 | M23: 0.11402461 | N23: 0.34011281 | O23: 0.36845554 | P23: -1.5458119 | Q23: 0.12215001 | R23: 0.17842401 | S23: 0.0065286423 | T23: 0.090322534 | U23: -0.0047918734 | V23: 0.0055172529
A24: Replication | B24: Anxiety disorder | C24: GCST90225527 | E24: no IV left after thresholding
A25: Replication | B25: ADHD | C25: GCST90275147 | D25: 11 | E25: ok | F25: 0.0099479908 | G25: 0.027909221 | H25: 0.72151032 | I25: -0.11736144 | J25: 0.62384795 | K25: 0.014825981 | L25: 0.04215312 | M25: 0.72505029 | N25: 0.79096396 | O25: 0.81962207 | P25: -0.33277743 | Q25: 0.73930229 | R25: 0.2590313 | S25: 0.0065286423 | T25: 0.27662979 | U25: 0.0015900892 | V25: 0.0067531844
A26: Replication | B26: Autism spectrum disorder | C26: GCST010514 | D26: 4 | E26: ok | F26: -0.0051293845 | G26: 0.043575353 | H26: 0.90629509 | I26: 0.71258646 | J26: 0.71101033 | K26: -0.0085245697 | L26: 0.074022865 | M26: 0.90831727 | N26: 0.90831727 | O26: 0.90831727 | P26: 0.10976888 | Q26: 0.91259267 | R26: 0.20022605 | S26: 0.0065286423 | T26: 0.0040025098 | U26: -0.00093090919 | V26: 0.0066122169
A27: Replication | B27: Bipolar disorder | C27: bip2021 | D27: 66 | E27: ok | F27: 0.0033588697 | G27: 0.0068346062 | H27: 0.62310795 | I27: -0.017008726 | J27: 0.71800686 | K27: 0.004449911 | L27: 0.0089256115 | M27: 0.61809269 | N27: 0.79096396 | O27: 0.81962207 | P27: -0.44713431 | Q27: 0.65477809 | R27: 0.57297235 | S27: 0.0065286423 | T27: 0.19433438 | U27: -0.00015526298 | V27: 0.0082125517
A28: Replication | B28: Major depressive disorder | C28: GCST009979 | E28: insufficient IVs (1 left after pruning)
A29: Replication | B29: Obsessive-compulsive disorder | C29: ocd2018 | E29: no IV left after thresholding
A30: Replication | B30: Opiate dependence | C30: OUD2022 | D30: 2 | E30: ok | F30: 0.23597096 | G30: 0.14452092 | H30: 0.10251515 | K30: 0.43880015 | L30: 0.26543961 | M30: 0.098309028 | N30: 0.34011281 | O30: 0.36514782 | P30: -1.6435747 | Q30: 0.10026409 | R30: 0.013526984 | S30: 0.0065286423 | T30: 0.36734524 | U30: -0.0070732685 | V30: 0.0058854256
A31: Replication | B31: Parkinson disease | C31: ieu_b_7 | D31: 27 | E31: ok | F31: -0.012904538 | G31: 0.032061556 | H31: 0.68732157 | I31: 0.2219492 | J31: 0.066755853 | K31: -0.015301506 | L31: 0.038233829 | M31: 0.68900291 | N31: 0.79096396 | O31: 0.81962207 | P31: 0.31172201 | Q31: 0.7552518 | R31: 0.016197738 | S31: 0.0065286423 | T31: -0.0034225125 | U31: -0.0011130911 | V31: 0.0013811701
A32: Replication | B32: PTSD | C32: ptsd2019 | D32: 2 | E32: ok | F32: -0.034829458 | G32: 0.086219492 | H32: 0.68624016 | K32: -0.055730538 | L32: 0.13833196 | M32: 0.68703992 | N32: 0.79096396 | O32: 0.81962207 | P32: 0.39588825 | Q32: 0.69218747 | R32: 0.014198298 | S32: 0.0065286423 | T32: 0.48219409 | U32: -0.000196234 | V32: 0.0014229534
A33: Replication | B33: Schizophrenia | C33: GCST90275158 | D33: 2 | E33: ok | F33: 0.032403737 | G33: 0.07806333 | H33: 0.678072 | K33: 0.060472475 | L33: 0.14020562 | M33: 0.66624096 | N33: 0.79096396 | O33: 0.81962207 | P33: -0.44778987 | Q33: 0.65430485 | R33: 0.1415865 | S33: 0.0065286423 | T33: 0.40403222 | U33: -0.0087238952 | V33: 0.0044506008
A34: Replication | B34: Sleep disorder | C34: GCST90473333 | E34: insufficient IVs (1 left after pruning)
A35: Replication | B35: Suicide attempt | C35: sui2023_noUKB | D35: 3 | E35: ok | F35: 0.32998556 | G35: 0.10285757 | H35: 0.0013357799 | I35: 0.79353182 | J35: 0.83485963 | K35: 0.57879269 | L35: 0.17985543 | M35: 0.0012904298 | N35: 0.015485158 | O35: 0.011183725 | P35: -3.0990115 | Q35: 0.0019416746 | R35: 0.020812274 | S35: 0.0065286423 | T35: 0.39009992 | U35: -0.00190753 | V35: 0.0058803204
A36: Replication | B36: Tobacco use disorder | C36: GCST90693050 | D36: 4 | E36: ok | F36: 0.24775335 | G36: 0.085948085 | H36: 0.0039441662 | I36: -0.26998149 | J36: 0.90669637 | K36: 0.41029313 | L36: 0.14231903 | M36: 0.0039401833 | N36: 0.0236411 | O36: 0.025611192 | P36: -2.7971199 | Q36: 0.0051560401 | R36: 0.021066639 | S36: 0.0065286423 | T36: 0.37178464 | U36: 0.0014088429 | V36: 0.0047453172
A38: Note: MRlap bias-corrected Mendelian randomization for the disorder-to-influenza (reverse) direction in the primary and replication panels. MRlap re-estimates the causal effect after modelling and removing bias from linkage disequilibrium and sample overlap between the exposure and outcome GWAS. Observed beta is the standard inverse-variance-weighted estimate and corrected beta the MRlap bias-corrected estimate, reported as beta (SE) on the log-odds ratio scale per standard deviation higher genetic liability to the disorder; P values are two-sided. m IVs is the number of instrumental variants retained after MRlap pruning. Status indicates pairs for which MRlap could not be computed because too few instruments remained; for these pairs corrected estimates are not available. FDR was computed by the Benjamini-Hochberg procedure within each panel (FDR panel) and across all 33 tests (FDR all). The difference test statistic and its P value compare the corrected and observed estimates. h2 exposure and h2 outcome are the SNP-based heritabilities used by MRlap; rg is their genetic correlation; the cross-trait intercept estimates correlation due to sample overlap; polygenicity is the estimated fraction of causal variants. NA, not estimated. Abbreviations: FDR, false discovery rate; IV, instrumental variant; MR, Mendelian randomization; SE, standard error; SNP, single-nucleotide polymorphism.

Sheet Supplementary Table 18
A1: Supplementary Table 18. Multivariable Mendelian randomization of substance-use traits on influenza and related outcomes.
A3: Block | B3: Model | C3: Panel | D3: Outcome | E3: Exposure | F3: Exposure accession | G3: Covariate accessions | H3: n SNPs | I3: OR | J3: OR_lci | K3: OR_uci | L3: P | M3: Q P | N3: Conditional F (main) | O3: Conditional F (min) | P3: Analysis note
A4: MVMR models | B4: Tobacco_p5e5 | C4: Primary | D4: Influenza | E4: Tobacco use disorder | F4: GCST90691929 | G4: GCST009004;GCST90566697 | H4: 110 | I4: 1.1290279 | J4: 1.0733045 | K4: 1.1876444 | L4: 2.6091062e-06 | M4: 0.28892981 | N4: 15.028915 | O4: 5.0081246 | P4: Threshold sensitivity p=5e-5
A5: MVMR models | B5: Tobacco_pneumonia | C5: Primary | D5: Pneumonia | E5: Tobacco use disorder | F5: GCST90691929 | G5: GCST009004;GCST90566697 | H5: 38 | I5: 1.1326671 | J5: 1.0691752 | K5: 1.1999295 | L5: 2.3103143e-05 | M5: 0.028091528 | N5: 21.180766 | O5: 7.8713636 | P5: Specificity test on pneumonia
A6: MVMR models | B6: Tobacco_p1e4 | C6: Primary | D6: Influenza | E6: Tobacco use disorder | F6: GCST90691929 | G6: GCST009004;GCST90566697 | H6: 160 | I6: 1.0971455 | J6: 1.0490701 | K6: 1.147424 | L6: 5.003739e-05 | M6: 0.50694885 | N6: 13.574517 | O6: 3.9274289 | P6: Threshold sensitivity p=1e-4
A7: MVMR models | B7: Tobacco_p1e4_Rep | C7: Replication | D7: Influenza | E7: Tobacco use disorder | F7: GCST90693050 | G7: GCST009004;GCST90566697 | H7: 150 | I7: 1.0519881 | J7: 1.0247351 | K7: 1.0799658 | L7: 0.0001539666 | M7: 0.2415831 | N7: 13.677796 | O7: 4.2504403 | P7: Replication threshold p=1e-4
A8: MVMR models | B8: Tobacco_adj_neutrophil | C8: Primary | D8: Influenza | E8: Tobacco use disorder | F8: GCST90691929 | G8: ieu-b-34;GCST009004;GCST90566697 | H8: 37 | I8: 1.1368597 | J8: 1.0550694 | K8: 1.2249906 | L8: 0.00075926228 | M8: 0.035062073 | N8: 21.301573 | O8: 4.6239579 | P8: Control for neutrophil count
A9: MVMR models | B9: Tobacco_simple | C9: Primary | D9: Influenza | E9: Tobacco use disorder | F9: GCST90691929 | G9: GCST009004;GCST90566697 | H9: 41 | I9: 1.1263781 | J9: 1.0507127 | K9: 1.2074924 | L9: 0.00079562292 | M9: 0.071709519 | N9: 21.695419 | O9: 7.6150768 | P9: Minimal covariates to maximize conditional F
A10: MVMR models | B10: Tobacco_p5e7 | C10: Primary | D10: Influenza | E10: Tobacco use disorder | F10: GCST90691929 | G10: GCST009004;GCST90566697 | H10: 9 | I10: 1.2511517 | J10: 1.0947927 | K10: 1.4298419 | L10: 0.0010031224 | M10: 0.70960214 | N10: 40.748948 | O10: 6.3051812 | P10: Threshold sensitivity p=5e-7
A11: MVMR models | B11: Tobacco_adj_smoking | C11: Primary | D11: Influenza | E11: Tobacco use disorder | F11: GCST90691929 | G11: GCST007327;GCST009004;GCST90566697 | H11: 41 | I11: 1.1235613 | J11: 1.0479281 | K11: 1.2046532 | L11: 0.0010503524 | M11: 0.07150955 | N11: 22.252988 | O11: 7.2379474 | P11: Control for smoking status
A12: MVMR models | B12: Tobacco_simple_adjEdu_only | C12: Primary | D12: Influenza | E12: Tobacco use disorder | F12: GCST90691929 | G12: GCST90566697 | H12: 42 | I12: 1.1215413 | J12: 1.0468211 | K12: 1.2015949 | L12: 0.0011109285 | M12: 0.061238874 | N12: 21.10863 | O12: 7.637525 | P12: IV strength check: adjust for education only
A13: MVMR models | B13: Tobacco_kb_5000 | C13: Primary | D13: Influenza | E13: Tobacco use disorder | F13: GCST90691929 | G13: GCST009004;GCST90566697 | H13: 42 | I13: 1.1189502 | J13: 1.0445731 | K13: 1.1986231 | L13: 0.001361723 | M13: 0.058255832 | N13: 21.679343 | O13: 7.4034603 | P13: Clumping kb=5000
A14: MVMR models | B14: Tobacco_adj_smoking_Rep | C14: Replication | D14: Influenza | E14: Tobacco use disorder | F14: GCST90693050 | G14: GCST007327;GCST009004;GCST90566697 | H14: 37 | I14: 1.073104 | J14: 1.0270924 | K14: 1.1211769 | L14: 0.0016017982 | M14: 0.35755953 | N14: 21.942358 | O14: 7.9480624 | P14: Replication control smoking
A15: MVMR models | B15: Tobacco_p1e7 | C15: Primary | D15: Influenza | E15: Tobacco use disorder | F15: GCST90691929 | G15: GCST009004;GCST90566697 | H15: 5 | I15: 1.3476186 | J15: 1.1194461 | K15: 1.6222985 | L15: 0.0016205821 | M15: 0.85150304 | N15: 60.37014 | O15: 13.145512 | P15: Threshold sensitivity p=1e-7
... A33: MVMR models | B33: Tobacco_p5e7_Rep | C33: Replication | D33: Influenza | E33: Tobacco use disorder | F33: GCST90693050 | G33: GCST009004;GCST90566697 | H33: 10 | I33: 1.0951308 | J33: 1.0200916 | K33: 1.1756899 | L33: 0.012097454 | M33: 0.23726296 | N33: 39.428332 | O33: 4.7589582 | P33: Replication threshold p=5e-7
A34: MVMR models | B34: Tobacco_univariate | C34: Primary | D34: Influenza | E34: Tobacco use disorder | F34: GCST90691929 | H34: 53 | I34: 1.0773271 | J34: 1.0161122 | K34: 1.14223 | L34: 0.012576943 | M34: 0.046373979 | N34: 23.810854 | O34: 23.810854 | P34: Univariate MR no covariates (instrument strength reference)
A35: MVMR models | B35: Tobacco_simple_adjBMI_only | C35: Primary | D35: Influenza | E35: Tobacco use disorder | F35: GCST90691929 | G35: GCST009004 | H35: 51 | I35: 1.0778575 | J35: 1.0157062 | K35: 1.1438119 | L35: 0.013349777 | M35: 0.035651794 | N35: 24.257131 | O35: 9.0904665 | P35: IV strength check: adjust for BMI only
A36: MVMR models | B36: Tobacco_p1e6 | C36: Primary | D36: Influenza | E36: Tobacco use disorder | F36: GCST90691929 | G36: GCST009004;GCST90566697 | H36: 14 | I36: 1.1473086 | J36: 1.0289451 | K36: 1.2792879 | L36: 0.013374659 | M36: 0.2063243 | N36: 29.841198 | O36: 6.7567758 | P36: Threshold sensitivity p=1e-6
A37: MVMR models | B37: Tobacco_p1e7_Rep | C37: Replication | D37: Influenza | E37: Tobacco use disorder | F37: GCST90693050 | G37: GCST009004;GCST90566697 | H37: 4 | I37: 1.2088302 | J37: 1.0388942 | K37: 1.4065632 | L37: 0.014141096 | M37: 0.21944233 | N37: 59.853049 | O37: 10.276584 | P37: Replication threshold p=1e-7
A38: MVMR models | B38: Tobacco_kb_250 | C38: Primary | D38: Influenza | E38: Tobacco use disorder | F38: GCST90691929 | G38: GCST009004;GCST90566697 | H38: 52 | I38: 1.0805101 | J38: 1.0127507 | K38: 1.152803 | L38: 0.019106344 | M38: 0.017057701 | N38: 19.735965 | O38: 6.7445466 | P38: Tight clumping kb=250
A39: MVMR models | B39: Tobacco_p1e6_Rep | C39: Replication | D39: Influenza | E39: Tobacco use disorder | F39: GCST90693050 | G39: GCST009004;GCST90566697 | H39: 18 | I39: 1.0727189 | J39: 1.0115513 | K39: 1.1375853 | L39: 0.019108204 | M39: 0.58058149 | N39: 26.677449 | O39: 7.7000112 | P39: Replication threshold p=1e-6
A40: MVMR models | B40: Tobacco_r2_05 | C40: Primary | D40: Influenza | E40: Tobacco use disorder | F40: GCST90691929 | G40: GCST009004;GCST90566697 | H40: 53 | I40: 1.0722051 | J40: 1.0058831 | K40: 1.1429 | L40: 0.032349871 | M40: 0.021395545 | N40: 19.998674 | O40: 6.8351752 | P40: Relaxed clumping r2=0.05
A41: MVMR models | B41: Tobacco_p5e6 | C41: Primary | D41: Influenza | E41: Tobacco use disorder | F41: GCST90691929 | G41: GCST009004;GCST90566697 | H41: 28 | I41: 1.0773191 | J41: 0.98900849 | K41: 1.1735152 | L41: 0.08787434 | M41: 0.70456971 | N41: 22.292863 | O41: 9.3801958 | P41: Threshold sensitivity p=5e-6
A42: MVMR models | B42: Opiate_simple_Rep | C42: Replication | D42: Influenza | E42: Opiate dependence | F42: OUD2022 | G42: GCST009004;GCST90566697 | H42: 34 | I42: 1.1152374 | J42: 0.91748823 | K42: 1.3556081 | L42: 0.27341181 | M42: 0.52017825 | N42: 13.130859 | O42: 6.0472558 | P42: Opiate dependence replication
A43: MVMR models | B43: Opiate_simple | C43: Primary | D43: Influenza | E43: Opiate dependence | F43: GCST90018994 | G43: GCST009004;GCST90566697 | H43: 48 | I43: 1.0542577 | J43: 0.95319511 | K43: 1.1660354 | L43: 0.30410795 | M43: 0.44961765 | N43: 13.070238 | O43: 11.240516 | P43: Opiate dependence as exposure
A44: MVMR models | B44: Smoking_simple | C44: Primary | D44: Influenza | E44: Smoking status | F44: GCST007327 | G44: GCST009004;GCST90566697 | H44: 300 | I44: 1.0721683 | J44: 0.92874503 | K44: 1.2377399 | L44: 0.3415646 | M44: 0.011859775 | N44: 26.549269 | O44: 9.1556989 | P44: Smoking status as exposure
A45: MVMR models | B45: Alcohol_simple_Rep | C45: Replication | D45: Influenza | E45: Alcohol dependence | F45: GCST90691955 | G45: GCST009004;GCST90566697 | H45: 30 | I45: 1.0252485 | J45: 0.95955525 | K45: 1.0954393 | L45: 0.4604961 | M45: 0.30304688 | N45: 13.891952 | O45: 2.8782242 | P45: Alcohol dependence replication
A46: MVMR models | B46: Alcohol_simple | C46: Primary | D46: Influenza | E46: Alcohol dependence | F46: GCST90435890 | G46: GCST009004;GCST90566697 | H46: 25 | I46: 1.0179886 | J46: 0.89292882 | K46: 1.1605638 | L46: 0.789782 | M46: 0.21895534 | N46: 10.476476 | O46: 1.8433121 | P46: Alcohol dependence as exposure
A47: MVMR models | B47: GSCAN_CigarettesPerDay_pneumonia | C47: Primary | D47: Pneumonia | E47: Cigarettes per day | F47: ieu-b-25 | H47: 20 | I47: 1.2194407 | J47: 1.1629557 | K47: 1.278669 | L47: 2.4277106e-16 | M47: 0.28378171 | N47: 96.800126 | O47: 96.800126
A48: MVMR models | B48: GSCAN_CigarettesPerDay_flupneu | C48: Primary | D48: Influenza and pneumonia | E48: Cigarettes per day | F48: ieu-b-25 | H48: 20 | I48: 1.2069954 | J48: 1.1527917 | K48: 1.2637477 | L48: 1.0128256e-15 | M48: 0.42163796 | N48: 96.800126 | O48: 96.800126
A49: MVMR models | B49: GSCAN_CigarettesPerDay_pneumonia_adjBMI | C49: Primary | D49: Pneumonia | E49: Cigarettes per day | F49: ieu-b-25 | G49: GCST009004 | H49: 20 | I49: 1.214493 | J49: 1.1552021 | K49: 1.276827 | L49: 2.745e-14 | M49: 0.24275567 | N49: 93.924744 | O49: 14.859425
A50: MVMR models | B50: GSCAN_SmokingInitiation_pneumonia | C50: Primary | D50: Pneumonia | E50: Smoking initiation | F50: ieu-b-4877 | H50: 79 | I50: 1.2293902 | J50: 1.1654442 | K50: 1.2968447 | L50: 3.514e-14 | M50: 1.9960725e-06 | N50: 43.462814 | O50: 43.462814 | P50: Pneumonia outcome (J10_INFLUPNEU surrogate)
A51: MVMR models | B51: GSCAN_SmokingInitiation_pneumonia_adjBMI | C51: Primary | D51: Pneumonia | E51: Smoking initiation | F51: ieu-b-4877 | G51: GCST009004 | H51: 79 | I51: 1.2275293 | J51: 1.1632933 | K51: 1.2953125 | L51: 7.68e-14 | M51: 1.5013783e-06 | N51: 43.494383 | O51: 30.668979 | P51: Pneumonia outcome + BMI
A52: MVMR models | B52: GSCAN_CigarettesPerDay_flupneu_adjBMI | C52: Primary | D52: Influenza and pneumonia | E52: Cigarettes per day | F52: ieu-b-25 | G52: GCST009004 | H52: 20 | I52: 1.1996247 | J52: 1.1428399 | K52: 1.2592309 | L52: 1.8871e-13 | M52: 0.39443452 | N52: 93.924744 | O52: 14.859425
A53: MVMR models | B53: GSCAN_SmokingInitiation_flupneu | C53: Primary | D53: Influenza and pneumonia | E53: Smoking initiation | F53: ieu-b-4877 | H53: 79 | I53: 1.2107119 | J53: 1.149657 | K53: 1.2750092 | L53: 4.4007e-13 | M53: 5.9796132e-07 | N53: 43.462814 | O53: 43.462814
A54: MVMR models | B54: GSCAN_SmokingInitiation_flupneu_adjBMI | C54: Primary | D54: Influenza and pneumonia | E54: Smoking initiation | F54: ieu-b-4877 | G54: GCST009004 | H54: 79 | I54: 1.2095009 | J54: 1.1481375 | K54: 1.274144 | L54: 8.0573e-13 | M54: 4.2880208e-07 | N54: 43.494383 | O54: 30.668979
A55: MVMR models | B55: GSCAN_SmokingInitiation_pneumonia_adjEdu | C55: Primary | D55: Pneumonia | E55: Smoking initiation | F55: ieu-b-4877 | G55: GCST90566697 | H55: 78 | I55: 1.2806464 | J55: 1.194487 | K55: 1.3730205 | L55: 3.37364e-12 | M55: 7.4150446e-06 | N55: 25.54405 | O55: 12.376573 | P55: Pneumonia outcome + Education
A56: MVMR models | B56: GSCAN_CigarettesPerDay_pneumonia_adjEdu | C56: Primary | D56: Pneumonia | E56: Cigarettes per day | F56: ieu-b-25 | G56: GCST90566697 | H56: 19 | I56: 1.2144631 | J56: 1.1487483 | K56: 1.2839371 | L56: 7.59899e-12 | M56: 0.18823901 | N56: 76.738725 | O56: 13.503301
A57: MVMR models | B57: GSCAN_SmokingInitiation_flupneu_adjEdu | C57: Primary | D57: Influenza and pneumonia | E57: Smoking initiation | F57: ieu-b-4877 | G57: GCST90566697 | H57: 78 | I57: 1.2618778 | J57: 1.1795496 | K57: 1.3499522 | L57: 1.40666e-11 | M57: 3.7721424e-06 | N57: 25.54405 | O57: 12.376573
A58: MVMR models | B58: GSCAN_CigarettesPerDay_flupneu_adjEdu | C58: Primary | D58: Influenza and pneumonia | E58: Cigarettes per day | F58: ieu-b-25 | G58: GCST90566697 | H58: 19 | I58: 1.1978136 | J58: 1.1349699 | K58: 1.2641369 | L58: 5.21846e-11 | M58: 0.31304024 | N58: 76.738725 | O58: 13.503301
A59: MVMR models | B59: GSCAN_SmokingInitiation_covid | C59: Primary | D59: COVID-19 | E59: Smoking initiation | F59: ieu-b-4877 | H59: 79 | I59: 1.2039484 | J59: 1.1092619 | K59: 1.3067174 | L59: 8.9445158e-06 | M59: 5.1510501e-05 | N59: 43.462814 | O59: 43.462814
A60: MVMR models | B60: GSCAN_SmokingInitiation_covid_adjBMI | C60: Primary | D60: COVID-19 | E60: Smoking initiation | F60: ieu-b-4877 | G60: GCST009004 | H60: 79 | I60: 1.2021371 | J60: 1.1071901 | K60: 1.3052262 | L60: 1.1559967e-05 | M60: 3.935165e-05 | N60: 43.494383 | O60: 30.668979
A61: MVMR models | B61: GSCAN_CigarettesPerDay_flu | C61: Primary | D61: Influenza | E61: Cigarettes per day | F61: ieu-b-25 | H61: 20 | I61: 1.1758384 | J61: 1.0502557 | K61: 1.3164376 | L61: 0.0049405052 | M61: 0.056676476 | N61: 96.800126 | O61: 96.800126 | P61: Cigarettes per day unadjusted
A62: MVMR models | B62: GSCAN_SmokingInitiation_flu_adjBMI | C62: Primary | D62: Influenza | E62: Smoking initiation | F62: ieu-b-4877 | G62: GCST009004 | H62: 79 | I62: 1.1744021 | J62: 1.0336475 | K62: 1.3343235 | L62: 0.013584074 | M62: 0.020228142 | N62: 43.494383 | O62: 30.668979
A63: MVMR models | B63: GSCAN_SmokingInitiation_flu | C63: Primary | D63: Influenza | E63: Smoking initiation | F63: ieu-b-4877 | H63: 79 | I63: 1.1643154 | J63: 1.0255756 | K63: 1.321824 | L63: 0.018767466 | M63: 0.019399207 | N63: 43.462814 | O63: 43.462814 | P63: Smoking initiation unadjusted
A64: MVMR models | B64: GSCAN_SmokingInitiation_flu_adjEdu | C64: Primary | D64: Influenza | E64: Smoking initiation | F64: ieu-b-4877 | G64: GCST90566697 | H64: 78 | I64: 1.2147366 | J64: 1.0295645 | K64: 1.4332128 | L64: 0.021150892 | M64: 0.027338856 | N64: 25.54405 | O64: 12.376573
A65: MVMR models | B65: GSCAN_CigarettesPerDay_covid | C65: Primary | D65: COVID-19 | E65: Cigarettes per day | F65: ieu-b-25 | H65: 20 | I65: 1.0874085 | J65: 1.0120588 | K65: 1.1683682 | L65: 0.022186303 | M65: 2.6713528e-05 | N65: 96.800126 | O65: 96.800126
A66: MVMR models | B66: GSCAN_CigarettesPerDay_flu_adjBMI | C66: Primary | D66: Influenza | E66: Cigarettes per day | F66: ieu-b-25 | G66: GCST009004 | H66: 20 | I66: 1.1195483 | J66: 0.99374584 | K66: 1.2612767 | L66: 0.063333992 | M66: 0.18074678 | N66: 93.924744 | O66: 14.859425
A67: MVMR models | B67: GSCAN_CigarettesPerDay_flu_adjEdu | C67: Primary | D67: Influenza | E67: Cigarettes per day | F67: ieu-b-25 | G67: GCST90566697 | H67: 19 | I67: 1.1149448 | J67: 0.97657446 | K67: 1.2729207 | L67: 0.10753331 | M67: 0.053974604 | N67: 76.738725 | O67: 13.503301
A68: MVMR models | B68: GSCAN_CigarettesPerDay_covid_adjBMI | C68: Primary | D68: COVID-19 | E68: Cigarettes per day | F68: ieu-b-25 | G68: GCST009004 | H68: 20 | I68: 1.0326418 | J68: 0.95722803 | K68: 1.1139969 | L68: 0.40643652 | M68: 0.0047393647 | N68: 93.924744 | O68: 14.859425
A69: MVMR models | B69: GSCAN_SmokingInitiation_covid_adjEdu | C69: Primary | D69: COVID-19 | E69: Smoking initiation | F69: ieu-b-4877 | G69: GCST90566697 | H69: 78 | I69: 1.043597 | J69: 0.93610185 | K69: 1.1634362 | L69: 0.441641 | M69: 0.0011878988 | N69: 25.54405 | O69: 12.376573
A70: MVMR models | B70: GSCAN_CigarettesPerDay_covid_adjEdu | C70: Primary | D70: COVID-19 | E70: Cigarettes per day | F70: ieu-b-25 | G70: GCST90566697 | H70: 19 | I70: 1.0203558 | J70: 0.9376613 | K70: 1.1103433 | L70: 0.64027257 | M70: 0.0011202165 | N70: 76.738725 | O70: 13.503301
A71: MVMR models | B71: Tobacco_any_infection_hosp | C71: Primary | D71: Hospital contact for infections | E71: Tobacco use disorder | F71: GCST90691929 | G71: GCST009004;GCST90566697 | H71: 43 | I71: 1.0744978 | J71: 1.0478497 | K71: 1.1018235 | L71: 2.0478408e-08 | M71: 0.10190628 | N71: 21.286101 | O71: 7.2443686 | P71: Tobacco on any infection hospitalized
A72: MVMR models | B72: Tobacco_pneumonia_large | C72: Primary | D72: Pneumonia | E72: Tobacco use disorder | F72: GCST90691929 | G72: GCST009004;GCST90566697 | H72: 36 | I72: 1.021196 | J72: 1.0114254 | K72: 1.031061 | L72: 1.9017953e-05 | M72: 0.15514836 | N72: 21.071777 | O72: 8.4775303 | P72: Tobacco on large pneumonia GWAS
A73: MVMR models | B73: Tobacco_pneumonia_hosp | C73: Primary | D73: Pneumonia | E73: Tobacco use disorder | F73: GCST90691929 | G73: GCST009004;GCST90566697 | H73: 43 | I73: 1.0732973 | J73: 1.0359024 | K73: 1.112042 | L73: 9.2478131e-05 | M73: 0.1315425 | N73: 21.286101 | O73: 7.2443686 | P73: Tobacco on pneumonia hospitalized
A74: MVMR models | B74: Tobacco_influenza_pneumonia_J09J18 | C74: Primary | D74: Influenza and pneumonia | E74: Tobacco use disorder | F74: GCST90691929 | G74: GCST009004;GCST90566697 | H74: 40 | I74: 1.0651011 | J74: 1.0259083 | K74: 1.1057912 | L74: 0.00097651695 | M74: 0.44921839 | N74: 21.552704 | O74: 7.4711882 | P74: Tobacco on influenza and pneumonia J09-J18
A75: MVMR models | B75: Tobacco_flu_Rep_extended | C75: Replication | D75: Influenza | E75: Tobacco use disorder | F75: GCST90693050 | G75: GCST009004;GCST90566697 | H75: 37 | I75: 1.0727399 | J75: 1.0268662 | K75: 1.1206629 | L75: 0.0016385084 | M75: 0.40210272 | N75: 21.36692 | O75: 8.6030883 | P75: Tobacco replication extended
A76: MVMR models | B76: Alcohol_covid_hosp | C76: Primary | D76: COVID-19 | E76: Alcohol dependence | F76: GCST90435890 | G76: GCST009004;GCST90566697 | H76: 26 | I76: 0.81017068 | J76: 0.67884258 | K76: 0.96690536 | L76: 0.019649346 | M76: 0.42777862 | N76: 12.662737 | O76: 2.2518713 | P76: Alcohol on COVID-19 hospitalized
A77: MVMR models | B77: Tobacco_covid_hosp | C77: Primary | D77: COVID-19 | E77: Tobacco use disorder | F77: GCST90691929 | G77: GCST009004;GCST90566697 | H77: 39 | I77: 1.1329677 | J77: 1.0122029 | K77: 1.2681409 | L77: 0.029937359 | M77: 0.0081175573 | N77: 21.488639 | O77: 7.8842859 | P77: Tobacco on COVID-19 hospitalized
A78: MVMR models | B78: Opiate_any_infection_hosp | C78: Primary | D78: Hospital contact for infections | E78: Opiate dependence | F78: GCST90018994 | G78: GCST009004;GCST90566697 | H78: 48 | I78: 1.035987 | J78: 0.99902777 | K78: 1.0743136 | L78: 0.056453424 | M78: 0.24310261 | N78: 13.070238 | O78: 11.240516 | P78: Opiate on any infection hospitalized
A79: MVMR models | B79: MultiSUD_flu | C79: Primary | D79: Influenza | E79: Tobacco use disorder | F79: GCST90691929;GCST90435890;GCST90018994 | G79: GCST009004;GCST90566697 | H79: 41 | I79: 1.0927171 | J79: 0.99108696 | K79: 1.2047688 | L79: 0.075036103 | M79: 0.053916817 | N79: 12.042866 | O79: 1.0607518 | P79: Multiple SUD on influenza
A80: MVMR models | B80: Opiate_pneumonia_large | C80: Primary | D80: Pneumonia | E80: Opiate dependence | F80: GCST90018994 | G80: GCST009004;GCST90566697 | H80: 43 | I80: 1.0098964 | J80: 0.99573407 | K80: 1.0242602 | L80: 0.17172061 | M80: 0.16312463 | N80: 12.278846 | O80: 10.47705 | P80: Opiate on large pneumonia GWAS
A81: MVMR models | B81: Opiate_covid_hosp | C81: Primary | D81: COVID-19 | E81: Opiate dependence | F81: GCST90018994 | G81: GCST009004;GCST90566697 | H81: 48 | I81: 0.89761457 | J81: 0.76704518 | K81: 1.05041 | L81: 0.17804849 | M81: 0.070623158 | N81: 13.070238 | O81: 11.240516 | P81: Opiate on COVID-19 hospitalized
A82: MVMR models | B82: Opiate_flu | C82: Primary | D82: Influenza | E82: Opiate dependence | F82: GCST90018994 | G82: GCST009004;GCST90566697 | H82: 48 | I82: 1.0542577 | J82: 0.95319511 | K82: 1.1660354 | L82: 0.30410795 | M82: 0.44961765 | N82: 13.070238 | O82: 11.240516 | P82: Opiate on influenza
... A88: MVMR models | B88: Alcohol_pneumonia_large | C88: Primary | D88: Pneumonia | E88: Alcohol dependence | F88: GCST90435890 | G88: GCST009004;GCST90566697 | H88: 22 | I88: 1.0010595 | J88: 0.98478762 | K88: 1.0176003 | L88: 0.89921711 | M88: 0.42696978 | N88: 13.132357 | O88: 2.5914949 | P88: Alcohol on large pneumonia GWAS
A90: Note: Multivariable Mendelian randomization (MVMR) of substance-use exposures on influenza and related infection outcomes. The MVMR models block reports one row per fitted model: genetic associations with the outcome were jointly regressed on the exposure and the covariates listed (accessions in the Covariate accessions column, semicolon-separated), so the exposure effect is independent of the covariates. Estimates are odds ratios (OR) per standard deviation higher genetic liability to the exposure, with 95% confidence intervals in parentheses; P values are two-sided. The Q P value tests instrument heterogeneity. Conditional F (main) is the main-exposure conditional instrument strength given the covariates; Conditional F (min) is the minimum exposure-specific conditional F statistic, not the strength of an individual SNP. Values below 10 indicate potential weak-instrument bias. Model variants include replication-panel fits, P-value threshold sensitivity analyses (P = 5e-5, 1e-4), and adjustment for smoking status, healthcare cost, asthma and neutrophil count. PAF estimates were removed because the MR liability-scale effect and case-control outcome proportion do not support a valid population intervention conversion. NA, not estimated or not applicable. Abbreviations: CI, confidence interval; MVMR, multivariable Mendelian randomization; OR, odds ratio; SNP, single-nucleotide polymorphism.

Sheet Supplementary Table 19
A1: Supplementary Table 19. Incident psychiatric diagnoses after influenza, upper respiratory tract infection and pneumonia in UK Biobank.
A3: section | B3: exposure | C3: analysis | D3: outcome | E3: term | F3: contrast | G3: estimate_type | H3: estimate | I3: ci_lo | J3: ci_hi | K3: p | L3: n_total | M3: n_events | N3: n_exposed | O3: events_exposed | P3: py_exposed | Q3: events_unexposed | R3: py_unexposed | S3: crude_rr | T3: stratifier | U3: stratum | V3: note
A4: main | B4: flu | C4: crude | D4: any_psych | E4: flu | F4: incident flu vs never-flu | G4: RR | H4: 1.5267 | L4: 417687 | M4: 47583 | N4: 3123 | O4: 346 | P4: 27779 | Q4: 47237 | R4: 5790036.9 | S4: 1.5267
A5: main | B5: flu | C5: unadjusted | D5: any_psych | E5: flu | F5: incident flu vs never-flu | G5: RR | H5: 1.5267 | I5: 1.3822 | J5: 1.6864 | K5: 7.6458986e-17 | L5: 417687 | M5: 47583 | N5: 3123 | O5: 346 | P5: 27779 | Q5: 47237 | R5: 5790036.9 | S5: 1.5267
A6: main | B6: flu | C6: no_lifestyle | D6: any_psych | E6: flu | F6: incident flu vs never-flu | G6: RR | H6: 1.4941 | I6: 1.352 | J6: 1.6512 | K6: 3.4672573e-15 | L6: 417687 | M6: 47583 | N6: 3123 | O6: 346 | P6: 27779 | Q6: 47237 | R6: 5790036.9 | S6: 1.5267
A7: main | B7: flu | C7: primary | D7: any_psych | E7: flu | F7: incident flu vs never-flu | G7: RR | H7: 1.5416 | I7: 1.3976 | J7: 1.7004 | K7: 5.1431741e-18 | L7: 417687 | M7: 47583 | N7: 3123 | O7: 346 | P7: 27779 | Q7: 47237 | R7: 5790036.9 | S7: 1.5267
A8: main | B8: flu | C8: mutual | D8: any_psych | E8: flu | F8: incident flu vs never-flu | G8: RR | H8: 1.4177 | I8: 1.285 | J8: 1.5641 | K8: 3.3355226e-12 | L8: 417687 | M8: 47583 | N8: 3123 | O8: 346 | P8: 27779 | Q8: 47237 | R8: 5790036.9 | S8: 1.5267
A9: sensitivity | B9: flu | C9: S0_unadjusted | D9: any_psych | E9: flu | F9: incident flu vs never-flu | G9: RR | H9: 1.5267 | I9: 1.3822 | J9: 1.6864 | K9: 7.6458986e-17 | L9: 417687 | M9: 47583
A10: sensitivity | B10: flu | C10: S1_nolifestyle | D10: any_psych | E10: flu | F10: incident flu vs never-flu | G10: RR | H10: 1.4941 | I10: 1.352 | J10: 1.6512 | K10: 3.4672573e-15 | L10: 417687 | M10: 47583
A11: sensitivity | B11: flu | C11: S2_plus_healthcare_contact | D11: any_psych | E11: flu | F11: incident flu vs never-flu | G11: RR | H11: 1.4826 | I11: 1.3451 | J11: 1.6342 | K11: 2.2305158e-15 | L11: 417687 | M11: 47583
A12: sensitivity | B12: flu | C12: S3_plus_index_year | D12: any_psych | E12: flu | F12: incident flu vs never-flu | G12: RR | H12: 1.4177 | I12: 1.2368 | J12: 1.6251 | K12: 5.428454e-07 | L12: 417687 | M12: 47583
A13: sensitivity | B13: flu | C13: S4_logit_2y_window | D13: any_psych | E13: flu | F13: incident flu vs never-flu | G13: OR | H13: 3.1551 | I13: 2.5834 | J13: 3.8534 | K13: 1.9722851e-29 | L13: 415483 | M13: 5791
A14: sensitivity | B14: flu | C14: S5_min2y_followup | D14: any_psych | E14: flu | F14: incident flu vs never-flu | G14: RR | H14: 1.5085 | I14: 1.3659 | J14: 1.6661 | K14: 5.0082332e-16 | L14: 415483 | M14: 47452
A15: strata | B15: flu | C15: stratified | D15: any_psych | E15: flu | F15: incident flu vs never-flu | G15: RR | H15: 1.154 | I15: 0.5579 | J15: 2.3869 | K15: 0.69929262 | L15: 4218 | M15: 743 | T15: gp_nerves | U15: missing
A16: strata | B16: flu | C16: stratified | D16: any_psych | E16: flu | F16: incident flu vs never-flu | G16: RR | H16: 1.5084 | I16: 1.3076 | J16: 1.7401 | K16: 1.7219676e-08 | L16: 304659 | M16: 25281 | T16: gp_nerves | U16: no
A17: strata | B17: flu | C17: stratified | D17: any_psych | E17: flu | F17: incident flu vs never-flu | G17: RR | H17: 1.3832 | I17: 1.2036 | J17: 1.5896 | K17: 4.8337052e-06 | L17: 108810 | M17: 21559 | T17: gp_nerves | U17: yes
A18: strata | B18: flu | C18: stratified | D18: any_psych | E18: flu | F18: incident flu vs never-flu | G18: RR | H18: 1.6658 | I18: 0.7807 | J18: 3.5543 | K18: 0.1869358 | L18: 2785 | M18: 582 | T18: psych_spec | U18: missing
A19: strata | B19: flu | C19: stratified | D19: any_psych | E19: flu | F19: incident flu vs never-flu | G19: RR | H19: 1.4603 | I19: 1.3037 | J19: 1.6357 | K19: 6.043505e-11 | L19: 385191 | M19: 39656 | T19: psych_spec | U19: no
A20: strata | B20: flu | C20: stratified | D20: any_psych | E20: flu | F20: incident flu vs never-flu | G20: RR | H20: 1.4257 | I20: 1.1599 | J20: 1.7523 | K20: 0.00075264999 | L20: 29711 | M20: 7345 | T20: psych_spec | U20: yes
A21: strata | B21: flu | C21: stratified | D21: any_psych | E21: flu | F21: incident flu vs never-flu | G21: RR | H21: 1.3825 | I21: 1.224 | J21: 1.5615 | K21: 1.8537786e-07 | L21: 267772 | M21: 35632 | T21: hosp_ever | U21: ever
A22: strata | B22: flu | C22: stratified | D22: any_psych | E22: flu | F22: incident flu vs never-flu | G22: RR | H22: 1.9084 | I22: 1.602 | J22: 2.2734 | K22: 4.6029647e-13 | L22: 149915 | M22: 11951 | T22: hosp_ever | U22: never
A23: main | B23: flu | C23: crude | D23: F17_tobacco | E23: flu | F23: incident flu vs never-flu | G23: RR | H23: 1.1324 | L23: 472750 | M23: 23222 | N23: 4106 | O23: 146 | P23: 36538.5 | Q23: 23076 | R23: 6539940.7 | S23: 1.1324
A24: main | B24: flu | C24: unadjusted | D24: F17_tobacco | E24: flu | F24: incident flu vs never-flu | G24: RR | H24: 1.1324 | I24: 0.9657 | J24: 1.328 | K24: 0.12590745 | L24: 472750 | M24: 23222 | N24: 4106 | O24: 146 | P24: 36538.5 | Q24: 23076 | R24: 6539940.7 | S24: 1.1324
A25: main | B25: flu | C25: no_lifestyle | D25: F17_tobacco | E25: flu | F25: incident flu vs never-flu | G25: RR | H25: 1.1539 | I25: 0.9816 | J25: 1.3564 | K25: 0.082838895 | L25: 472750 | M25: 23222 | N25: 4106 | O25: 146 | P25: 36538.5 | Q25: 23076 | R25: 6539940.7 | S25: 1.1324
A26: main | B26: flu | C26: primary | D26: F17_tobacco | E26: flu | F26: incident flu vs never-flu | G26: RR | H26: 1.2259 | I26: 1.0611 | J26: 1.4163 | K26: 0.0056803216 | L26: 472750 | M26: 23222 | N26: 4106 | O26: 146 | P26: 36538.5 | Q26: 23076 | R26: 6539940.7 | S26: 1.1324
A27: main | B27: flu | C27: mutual | D27: F17_tobacco | E27: flu | F27: incident flu vs never-flu | G27: RR | H27: 1.161 | I27: 1.0043 | J27: 1.3421 | K27: 0.04362207 | L27: 472750 | M27: 23222 | N27: 4106 | O27: 146 | P27: 36538.5 | Q27: 23076 | R27: 6539940.7 | S27: 1.1324
A28: sensitivity | B28: flu | C28: S0_unadjusted | D28: F17_tobacco | E28: flu | F28: incident flu vs never-flu | G28: RR | H28: 1.1324 | I28: 0.9657 | J28: 1.328 | K28: 0.12590745 | L28: 472750 | M28: 23222
A29: sensitivity | B29: flu | C29: S1_nolifestyle | D29: F17_tobacco | E29: flu | F29: incident flu vs never-flu | G29: RR | H29: 1.1539 | I29: 0.9816 | J29: 1.3564 | K29: 0.082838895 | L29: 472750 | M29: 23222
A30: sensitivity | B30: flu | C30: S2_plus_healthcare_contact | D30: F17_tobacco | E30: flu | F30: incident flu vs never-flu | G30: RR | H30: 1.1978 | I30: 1.0369 | J30: 1.3836 | K30: 0.0141888 | L30: 472750 | M30: 23222
A31: sensitivity | B31: flu | C31: S3_plus_index_year | D31: F17_tobacco | E31: flu | F31: incident flu vs never-flu | G31: RR | H31: 1.2792 | I31: 1.0771 | J31: 1.5192 | K31: 0.0050082421 | L31: 472750 | M31: 23222
A32: sensitivity | B32: flu | C32: S4_logit_2y_window | D32: F17_tobacco | E32: flu | F32: incident flu vs never-flu | G32: OR | H32: 2.5767 | I32: 1.8709 | J32: 3.5488 | K32: 6.7948165e-09 | L32: 470153 | M32: 2687
A33: sensitivity | B33: flu | C33: S5_min2y_followup | D33: F17_tobacco | E33: flu | F33: incident flu vs never-flu | G33: RR | H33: 1.1981 | I33: 1.0351 | J33: 1.3868 | K33: 0.015393439 | L33: 470153 | M33: 23161
A34: strata | B34: flu | C34: stratified | D34: F17_tobacco | E34: flu | F34: incident flu vs never-flu | G34: RR | H34: 0.4337 | I34: 0.0619 | J34: 3.037 | K34: 0.4001782 | L34: 4665 | M34: 349 | T34: gp_nerves | U34: missing
A35: strata | B35: flu | C35: stratified | D35: F17_tobacco | E35: flu | F35: incident flu vs never-flu | G35: RR | H35: 1.2698 | I35: 1.019 | J35: 1.5822 | K35: 0.033331814 | L35: 310931 | M35: 12717 | T35: gp_nerves | U35: no
A36: strata | B36: flu | C36: stratified | D36: F17_tobacco | E36: flu | F36: incident flu vs never-flu | G36: RR | H36: 0.9815 | I36: 0.7719 | J36: 1.248 | K36: 0.8790668 | L36: 157154 | M36: 10156 | T36: gp_nerves | U36: yes
A37: strata | B37: flu | C37: stratified | D37: F17_tobacco | E37: flu | F37: incident flu vs never-flu | G37: RR | H37: 1.4031 | I37: 0.3736 | J37: 5.2695 | K37: 0.6159302 | L37: 3411 | M37: 304 | T37: psych_spec | U37: missing
A38: strata | B38: flu | C38: stratified | D38: F17_tobacco | E38: flu | F38: incident flu vs never-flu | G38: RR | H38: 1.0962 | I38: 0.9055 | J38: 1.3271 | K38: 0.3461307 | L38: 416303 | M38: 18307 | T38: psych_spec | U38: no
A39: strata | B39: flu | C39: stratified | D39: F17_tobacco | E39: flu | F39: incident flu vs never-flu | G39: RR | H39: 1.143 | I39: 0.8392 | J39: 1.5567 | K39: 0.3966311 | L39: 53036 | M39: 4611 | T39: psych_spec | U39: yes
A40: strata | B40: flu | C40: stratified | D40: F17_tobacco | E40: flu | F40: incident flu vs never-flu | G40: RR | H40: 1.0429 | I40: 0.8553 | J40: 1.2716 | K40: 0.67819101 | L40: 308923 | M40: 17488 | T40: hosp_ever | U40: ever
A41: strata | B41: flu | C41: stratified | D41: F17_tobacco | E41: flu | F41: incident flu vs never-flu | G41: RR | H41: 1.5406 | I41: 1.1648 | J41: 2.0378 | K41: 0.002455354 | L41: 163827 | M41: 5734 | T41: hosp_ever | U41: never
A42: main | B42: flu | C42: crude | D42: F20_schizophrenia | E42: flu | F42: incident flu vs never-flu | G42: RR | H42: 1.2615 | L42: 493222 | M42: 531 | N42: 4725 | O42: 4 | P42: 40929.3 | Q42: 527 | R42: 6802817.6 | S42: 1.2615
A43: main | B43: flu | C43: unadjusted | D43: F20_schizophrenia | E43: flu | F43: incident flu vs never-flu | G43: RR | H43: 1.2615 | I43: 0.4717 | J43: 3.3738 | K43: 0.64342305 | L43: 493222 | M43: 531 | N43: 4725 | O43: 4 | P43: 40929.3 | Q43: 527 | R43: 6802817.6 | S43: 1.2615
A44: main | B44: flu | C44: no_lifestyle | D44: F20_schizophrenia | E44: flu | F44: incident flu vs never-flu | G44: RR | H44: 1.2415 | I44: 0.463 | J44: 3.329 | K44: 0.66725425 | L44: 493222 | M44: 531 | N44: 4725 | O44: 4 | P44: 40929.3 | Q44: 527 | R44: 6802817.6 | S44: 1.2615
A45: main | B45: flu | C45: primary | D45: F20_schizophrenia | E45: flu | F45: incident flu vs never-flu | G45: RR | H45: 1.1044 | I45: 0.412 | J45: 2.9604 | K45: 0.84346947 | L45: 493222 | M45: 531 | N45: 4725 | O45: 4 | P45: 40929.3 | Q45: 527 | R45: 6802817.6 | S45: 1.2615
A46: main | B46: flu | C46: mutual | D46: F20_schizophrenia | E46: flu | F46: incident flu vs never-flu | G46: RR | H46: 1.1375 | I46: 0.4244 | J46: 3.0486 | K46: 0.79785056 | L46: 493222 | M46: 531 | N46: 4725 | O46: 4 | P46: 40929.3 | Q46: 527 | R46: 6802817.6 | S46: 1.2615
A47: main | B47: flu | C47: crude | D47: F25_schizoaffective | E47: flu | F47: incident flu vs never-flu | G47: RR | H47: 3.0354 | L47: 493926 | M47: 167 | N47: 4741 | O47: 3 | P47: 41051.3 | Q47: 164 | R47: 6811748.2 | S47: 3.0354
A48: main | B48: flu | C48: unadjusted | D48: F25_schizoaffective | E48: flu | F48: incident flu vs never-flu | G48: RR | H48: 3.0354 | I48: 0.9695 | J48: 9.5034 | K48: 0.056554784 | L48: 493926 | M48: 167 | N48: 4741 | O48: 3 | P48: 41051.3 | Q48: 164 | R48: 6811748.2 | S48: 3.0354
A49: main | B49: flu | C49: no_lifestyle | D49: F25_schizoaffective | E49: flu | F49: incident flu vs never-flu | G49: RR | H49: 3.0947 | I49: 0.984 | J49: 9.7331 | K49: 0.053316196 | L49: 493926 | M49: 167 | N49: 4741 | O49: 3 | P49: 41051.3 | Q49: 164 | R49: 6811748.2 | S49: 3.0354
A50: main | B50: flu | C50: primary | D50: F25_schizoaffective | E50: flu | F50: incident flu vs never-flu | G50: RR | H50: 2.7359 | I50: 0.8691 | J50: 8.6126 | K50: 0.085411296 | L50: 493926 | M50: 167 | N50: 4741 | O50: 3 | P50: 41051.3 | Q50: 164 | R50: 6811748.2 | S50: 3.0354
A51: main | B51: flu | C51: mutual | D51: F25_schizoaffective | E51: flu | F51: incident flu vs never-flu | G51: RR | H51: 3.2148 | I51: 1.0255 | J51: 10.0781 | K51: 0.045166446 | L51: 493926 | M51: 167 | N51: 4741 | O51: 3 | P51: 41051.3 | Q51: 164 | R51: 6811748.2 | S51: 3.0354
A52: main | B52: flu | C52: crude | D52: F30_mania | E52: flu | F52: incident flu vs never-flu | G52: RR | H52: 2.2629 | L52: 493814 | M52: 223 | N52: 4740 | O52: 3 | P52: 41038.2 | Q52: 220 | R52: 6810201.6 | S52: 2.2629
A53: main | B53: flu | C53: unadjusted | D53: F30_mania | E53: flu | F53: incident flu vs never-flu | G53: RR | H53: 2.2629 | I53: 0.7246 | J53: 7.0676 | K53: 0.15988481 | L53: 493814 | M53: 223 | N53: 4740 | O53: 3 | P53: 41038.2 | Q53: 220 | R53: 6810201.6 | S53: 2.2629
A54: main | B54: flu | C54: no_lifestyle | D54: F30_mania | E54: flu | F54: incident flu vs never-flu | G54: RR | H54: 2.2464 | I54: 0.7182 | J54: 7.0261 | K54: 0.16419261 | L54: 493814 | M54: 223 | N54: 4740 | O54: 3 | P54: 41038.2 | Q54: 220 | R54: 6810201.6 | S54: 2.2629
A55: main | B55: flu | C55: primary | D55: F30_mania | E55: flu | F55: incident flu vs never-flu | G55: RR | H55: 2.1053 | I55: 0.6712 | J55: 6.6035 | K55: 0.20182557 | L55: 493814 | M55: 223 | N55: 4740 | O55: 3 | P55: 41038.2 | Q55: 220 | R55: 6810201.6 | S55: 2.2629
A56: main | B56: flu | C56: mutual | D56: F30_mania | E56: flu | F56: incident flu vs never-flu | G56: RR | H56: 1.7548 | I56: 0.547 | J56: 5.63 | K56: 0.34438569 | L56: 493814 | M56: 223 | N56: 4740 | O56: 3 | P56: 41038.2 | Q56: 220 | R56: 6810201.6 | S56: 2.2629
A57: main | B57: flu | C57: crude | D57: F31_bipolar | E57: flu | F57: incident flu vs never-flu | G57: RR | H57: 2.527 | L57: 492398 | M57: 868 | N57: 4713 | O57: 13 | P57: 40863.7 | Q57: 855 | R57: 6791608.7 | S57: 2.527
A58: main | B58: flu | C58: unadjusted | D58: F31_bipolar | E58: flu | F58: incident flu vs never-flu | G58: RR | H58: 2.527 | I58: 1.4624 | J58: 4.3669 | K58: 0.00089463313 | L58: 492398 | M58: 868 | N58: 4713 | O58: 13 | P58: 40863.7 | Q58: 855 | R58: 6791608.7 | S58: 2.527
A59: main | B59: flu | C59: no_lifestyle | D59: F31_bipolar | E59: flu | F59: incident flu vs never-flu | G59: RR | H59: 2.4881 | I59: 1.4368 | J59: 4.3088 | K59: 0.0011401635 | L59: 492398 | M59: 868 | N59: 4713 | O59: 13 | P59: 40863.7 | Q59: 855 | R59: 6791608.7 | S59: 2.527
A60: main | B60: flu | C60: primary | D60: F31_bipolar | E60: flu | F60: incident flu vs never-flu | G60: RR | H60: 2.2729 | I60: 1.3104 | J60: 3.9421 | K60: 0.0034758206 | L60: 492398 | M60: 868 | N60: 4713 | O60: 13 | P60: 40863.7 | Q60: 855 | R60: 6791608.7 | S60: 2.527
A61: main | B61: flu | C61: mutual | D61: F31_bipolar | E61: flu | F61: incident flu vs never-flu | G61: RR | H61: 2.1932 | I61: 1.2551 | J61: 3.8323 | K61: 0.0058166175 | L61: 492398 | M61: 868 | N61: 4713 | O61: 13 | P61: 40863.7 | Q61: 855 | R61: 6791608.7 | S61: 2.527
A62: sensitivity | B62: flu | C62: S0_unadjusted | D62: F31_bipolar | E62: flu | F62: incident flu vs never-flu | G62: RR | H62: 2.527 | I62: 1.4624 | J62: 4.3669 | K62: 0.00089463313 | L62: 492398 | M62: 868
A63: sensitivity | B63: flu | C63: S1_nolifestyle | D63: F31_bipolar | E63: flu | F63: incident flu vs never-flu | G63: RR | H63: 2.4881 | I63: 1.4368 | J63: 4.3088 | K63: 0.0011401635 | L63: 492398 | M63: 868
A64: sensitivity | B64: flu | C64: S2_plus_healthcare_contact | D64: F31_bipolar | E64: flu | F64: incident flu vs never-flu | G64: RR | H64: 1.75 | I64: 1.007 | J64: 3.0412 | K64: 0.047163362 | L64: 492398 | M64: 868
A65: sensitivity | B65: flu | C65: S3_plus_index_year | D65: F31_bipolar | E65: flu | F65: incident flu vs never-flu | G65: RR | H65: 2.1277 | I65: 0.9501 | J65: 4.7646 | K65: 0.06641591 | L65: 492398 | M65: 868
A66: sensitivity | B66: flu | C66: S4_logit_2y_window | D66: F31_bipolar | E66: flu | F66: incident flu vs never-flu | G66: OR | H66: 5.1796 | I66: 2.0911 | J66: 12.8294 | K66: 0.00037929851 | L66: 489476 | M66: 108 | V66: not_converged
A67: sensitivity | B67: flu | C67: S5_min2y_followup | D67: F31_bipolar | E67: flu | F67: incident flu vs never-flu | G67: RR | H67: 2.1203 | I67: 1.1963 | J67: 3.758 | K67: 0.010064365 | L67: 489476 | M67: 864
A68: strata | B68: flu | C68: stratified | D68: F31_bipolar | E68: flu | F68: incident flu vs never-flu | G68: RR | L68: 4908 | M68: 14 | T68: gp_nerves | U68: missing | V68: zero_events_exposed
A69: strata | B69: flu | C69: stratified | D69: F31_bipolar | E69: flu | F69: incident flu vs never-flu | G69: RR | H69: 2.9272 | I69: 0.7185 | J69: 11.9249 | K69: 0.13394165 | L69: 323247 | M69: 124 | T69: gp_nerves | U69: no | V69: zero_events_exposed
A70: strata | B70: flu | C70: stratified | D70: F31_bipolar | E70: flu | F70: incident flu vs never-flu | G70: RR | H70: 2.0188 | I70: 1.113 | J70: 3.6618 | K70: 0.020766421 | L70: 164243 | M70: 730 | T70: gp_nerves | U70: yes | V70: zero_events_exposed
A71: strata | B71: flu | C71: stratified | D71: F31_bipolar | E71: flu | F71: incident flu vs never-flu | G71: RR | L71: 3594 | M71: 11 | T71: psych_spec | U71: missing | V71: zero_events_exposed
A72: strata | B72: flu | C72: stratified | D72: F31_bipolar | E72: flu | F72: incident flu vs never-flu | G72: RR | H72: 5.3843 | I72: 2.66 | J72: 10.8991 | K72: 2.8822374e-06 | L72: 433979 | M72: 274 | T72: psych_spec | U72: no | V72: zero_events_exposed
A73: strata | B73: flu | C73: stratified | D73: F31_bipolar | E73: flu | F73: incident flu vs never-flu | G73: RR | H73: 0.9546 | I73: 0.3961 | J73: 2.3004 | K73: 0.91756749 | L73: 54825 | M73: 583 | T73: psych_spec | U73: yes | V73: zero_events_exposed
A74: strata | B74: flu | C74: stratified | D74: F31_bipolar | E74: flu | F74: incident flu vs never-flu | G74: RR | H74: 2.1243 | I74: 1.0991 | J74: 4.1055 | K74: 0.025017241 | L74: 323611 | M74: 716 | T74: hosp_ever | U74: ever | V74: zero_events_exposed
A75: strata | B75: flu | C75: stratified | D75: F31_bipolar | E75: flu | F75: incident flu vs never-flu | G75: RR | H75: 4.3961 | I75: 1.6223 | J75: 11.9127 | K75: 0.0036001131 | L75: 168787 | M75: 152 | T75: hosp_ever | U75: never | V75: zero_events_exposed
A76: main | B76: flu | C76: crude | D76: F32_dep_single | E76: flu | F76: incident flu vs never-flu | G76: RR | H76: 1.9393 | L76: 453850 | M76: 21314 | N76: 3920 | O76: 224 | P76: 34328.7 | Q76: 21090 | R76: 6268146.8 | S76: 1.9393
A77: main | B77: flu | C77: unadjusted | D77: F32_dep_single | E77: flu | F77: incident flu vs never-flu | G77: RR | H77: 1.9393 | I77: 1.7068 | J77: 2.2036 | K77: 2.8841323e-24 | L77: 453850 | M77: 21314 | N77: 3920 | O77: 224 | P77: 34328.7 | Q77: 21090 | R77: 6268146.8 | S77: 1.9393
A78: main | B78: flu | C78: no_lifestyle | D78: F32_dep_single | E78: flu | F78: incident flu vs never-flu | G78: RR | H78: 1.852 | I78: 1.6283 | J78: 2.1064 | K78: 6.3675014e-21 | L78: 453850 | M78: 21314 | N78: 3920 | O78: 224 | P78: 34328.7 | Q78: 21090 | R78: 6268146.8 | S78: 1.9393
A79: main | B79: flu | C79: primary | D79: F32_dep_single | E79: flu | F79: incident flu vs never-flu | G79: RR | H79: 1.788 | I79: 1.5724 | J79: 2.0332 | K79: 7.8214278e-19 | L79: 453850 | M79: 21314 | N79: 3920 | O79: 224 | P79: 34328.7 | Q79: 21090 | R79: 6268146.8 | S79: 1.9393
A80: main | B80: flu | C80: mutual | D80: F32_dep_single | E80: flu | F80: incident flu vs never-flu | G80: RR | H80: 1.6377 | I80: 1.4393 | J80: 1.8634 | K80: 7.0881351e-14 | L80: 453850 | M80: 21314 | N80: 3920 | O80: 224 | P80: 34328.7 | Q80: 21090 | R80: 6268146.8 | S80: 1.9393
A81: sensitivity | B81: flu | C81: S0_unadjusted | D81: F32_dep_single | E81: flu | F81: incident flu vs never-flu | G81: RR | H81: 1.9393 | I81: 1.7068 | J81: 2.2036 | K81: 2.8841323e-24 | L81: 453850 | M81: 21314
A82: sensitivity | B82: flu | C82: S1_nolifestyle | D82: F32_dep_single | E82: flu | F82: incident flu vs never-flu | G82: RR | H82: 1.852 | I82: 1.6283 | J82: 2.1064 | K82: 6.3675014e-21 | L82: 453850 | M82: 21314
A83: sensitivity | B83: flu | C83: S2_plus_healthcare_contact | D83: F32_dep_single | E83: flu | F83: incident flu vs never-flu | G83: RR | H83: 1.5831 | I83: 1.3946 | J83: 1.797 | K83: 1.2286843e-12 | L83: 453850 | M83: 21314
A84: sensitivity | B84: flu | C84: S3_plus_index_year | D84: F32_dep_single | E84: flu | F84: incident flu vs never-flu | G84: RR | H84: 1.5719 | I84: 1.2981 | J84: 1.9034 | K84: 3.6087819e-06 | L84: 453850 | M84: 21314
A85: sensitivity | B85: flu | C85: S4_logit_2y_window | D85: F32_dep_single | E85: flu | F85: incident flu vs never-flu | G85: OR | H85: 3.6456 | I85: 2.81 | J85: 4.7299 | K85: 2.0844904e-22 | L85: 451245 | M85: 2232
A86: sensitivity | B86: flu | C86: S5_min2y_followup | D86: F32_dep_single | E86: flu | F86: incident flu vs never-flu | G86: RR | H86: 1.7755 | I86: 1.5597 | J86: 2.0212 | K86: 3.8900715e-18 | L86: 451245 | M86: 21246
A87: strata | B87: flu | C87: stratified | D87: F32_dep_single | E87: flu | F87: incident flu vs never-flu | G87: RR | H87: 1.9286 | I87: 0.8218 | J87: 4.5263 | K87: 0.13131193 | L87: 4654 | M87: 320 | T87: gp_nerves | U87: missing
A88: strata | B88: flu | C88: stratified | D88: F32_dep_single | E88: flu | F88: incident flu vs never-flu | G88: RR | H88: 1.9537 | I88: 1.5512 | J88: 2.4607 | K88: 1.273615e-08 | L88: 320971 | M88: 7227 | T88: gp_nerves | U88: no
A89: strata | B89: flu | C89: stratified | D89: F32_dep_single | E89: flu | F89: incident flu vs never-flu | G89: RR | H89: 1.559 | I89: 1.336 | J89: 1.8192 | K89: 1.7158924e-08 | L89: 128225 | M89: 13767 | T89: gp_nerves | U89: yes
A90: strata | B90: flu | C90: stratified | D90: F32_dep_single | E90: flu | F90: incident flu vs never-flu | G90: RR | H90: 1.5838 | I90: 0.5065 | J90: 4.9528 | K90: 0.42922822 | L90: 3163 | M90: 304 | T90: psych_spec | U90: missing
A91: strata | B91: flu | C91: stratified | D91: F32_dep_single | E91: flu | F91: incident flu vs never-flu | G91: RR | H91: 1.7658 | I91: 1.5053 | J91: 2.0712 | K91: 2.8674499e-12 | L91: 413474 | M91: 15606 | T91: psych_spec | U91: no
A92: strata | B92: flu | C92: stratified | D92: F32_dep_single | E92: flu | F92: incident flu vs never-flu | G92: RR | H92: 1.6132 | I92: 1.3067 | J92: 1.9916 | K92: 8.6376472e-06 | L92: 37213 | M92: 5404 | T92: psych_spec | U92: yes
A93: strata | B93: flu | C93: stratified | D93: F32_dep_single | E93: flu | F93: incident flu vs never-flu | G93: RR | H93: 1.7391 | I93: 1.4961 | J93: 2.0217 | K93: 5.809014e-13 | L93: 294479 | M93: 16787 | T93: hosp_ever | U93: ever
A94: strata | B94: flu | C94: stratified | D94: F32_dep_single | E94: flu | F94: incident flu vs never-flu | G94: RR | H94: 2.3943 | I94: 1.8687 | J94: 3.0676 | K94: 5.0084974e-12 | L94: 159371 | M94: 4527 | T94: hosp_ever | U94: never
A95: main | B95: flu | C95: crude | D95: F33_dep_recur | E95: flu | F95: incident flu vs never-flu | G95: RR | H95: 1.6732 | L95: 491541 | M95: 1214 | N95: 4667 | O95: 12 | P95: 40453.7 | Q95: 1202 | R95: 6780161.9 | S95: 1.6732
A96: main | B96: flu | C96: unadjusted | D96: F33_dep_recur | E96: flu | F96: incident flu vs never-flu | G96: RR | H96: 1.6732 | I96: 0.9484 | J96: 2.9522 | K96: 0.075573847 | L96: 491541 | M96: 1214 | N96: 4667 | O96: 12 | P96: 40453.7 | Q96: 1202 | R96: 6780161.9 | S96: 1.6732
A97: main | B97: flu | C97: no_lifestyle | D97: F33_dep_recur | E97: flu | F97: incident flu vs never-flu | G97: RR | H97: 1.6446 | I97: 0.932 | J97: 2.9018 | K97: 0.085966028 | L97: 491541 | M97: 1214 | N97: 4667 | O97: 12 | P97: 40453.7 | Q97: 1202 | R97: 6780161.9 | S97: 1.6732
A98: main | B98: flu | C98: primary | D98: F33_dep_recur | E98: flu | F98: incident flu vs never-flu | G98: RR | H98: 1.545 | I98: 0.876 | J98: 2.725 | K98: 0.13290412 | L98: 491541 | M98: 1214 | N98: 4667 | O98: 12 | P98: 40453.7 | Q98: 1202 | R98: 6780161.9 | S98: 1.6732
A99: main | B99: flu | C99: mutual | D99: F33_dep_recur | E99: flu | F99: incident flu vs never-flu | G99: RR | H99: 1.3195 | I99: 0.7447 | J99: 2.3382 | K99: 0.34212161 | L99: 491541 | M99: 1214 | N99: 4667 | O99: 12 | P99: 40453.7 | Q99: 1202 | R99: 6780161.9 | S99: 1.6732
A100: sensitivity | B100: flu | C100: S0_unadjusted | D100: F33_dep_recur | E100: flu | F100: incident flu vs never-flu | G100: RR | H100: 1.6732 | I100: 0.9484 | J100: 2.9522 | K100: 0.075573847 | L100: 491541 | M100: 1214
A101: sensitivity | B101: flu | C101: S1_nolifestyle | D101: F33_dep_recur | E101: flu | F101: incident flu vs never-flu | G101: RR | H101: 1.6446 | I101: 0.932 | J101: 2.9018 | K101: 0.085966028 | L101: 491541 | M101: 1214
...

Sheet Supplementary Table 20
A1: Supplementary Table 20. Smoking status, cigarette dose and self-reported recent flu, pneumonia or ear infection in NHANES 2005–2018.
A3: analysis | B3: cycle | C3: model | D3: outcome | E3: exposure | F3: contrast | G3: adjustment | H3: n | I3: n_exposed | J3: n_exposed_flu | K3: n_events | L3: estimate | M3: ci_lo | N3: ci_hi | O3: p_value | P3: est_type
A4: smoking_status | B4: 2005-2006 | C4: M1 | D4: flu | E4: former | F4: former_vs_never | G4: age+sex+race(+cycle) | H4: 4348 | I4: 1127 | J4: 40 | K4: 206 | L4: 0.56173922 | M4: 0.33612267 | N4: 0.93879699 | O4: 0.027733615 | P4: OR
A5: smoking_status | B5: 2005-2006 | C5: M1 | D5: flu | E5: current | F5: current_vs_never | G5: age+sex+race(+cycle) | H5: 4348 | I5: 943 | J5: 57 | K5: 206 | L5: 1.3599207 | M5: 0.87104567 | N5: 2.1231772 | O5: 0.17619087 | P5: OR
A6: smoking_status | B6: 2005-2006 | C6: M2 | D6: flu | E6: former | F6: former_vs_never | G6: M1+poverty_ratio+education | H6: 4348 | I6: 1127 | J6: 40 | K6: 206 | L6: 0.55109654 | M6: 0.32938967 | N6: 0.92203071 | O6: 0.023259601 | P6: OR
A7: smoking_status | B7: 2005-2006 | C7: M2 | D7: flu | E7: current | F7: current_vs_never | G7: M1+poverty_ratio+education | H7: 4348 | I7: 943 | J7: 57 | K7: 206 | L7: 1.2936024 | M7: 0.83029776 | N7: 2.0154302 | O7: 0.25514561 | P7: OR
A8: smoking_dose | B8: 2005-2006 | C8: M1 | D8: flu | E8: cpd_1_9 | F8: cpd_1_9_vs_never | G8: age+sex+race(+cycle) | H8: 3215 | I8: 334 | J8: 16 | K8: 166 | L8: 0.89465664 | M8: 0.44878473 | N8: 1.7835066 | O8: 0.75181483 | P8: OR
A9: smoking_dose | B9: 2005-2006 | C9: M1 | D9: flu | E9: cpd_10_19 | F9: cpd_10_19_vs_never | G9: age+sex+race(+cycle) | H9: 3215 | I9: 259 | J9: 14 | K9: 166 | L9: 1.3366817 | M9: 0.66422695 | N9: 2.689921 | O9: 0.41603415 | P9: OR
A10: smoking_dose | B10: 2005-2006 | C10: M1 | D10: flu | E10: cpd_20p | F10: cpd_20p_vs_never | G10: age+sex+race(+cycle) | H10: 3215 | I10: 344 | J10: 27 | K10: 166 | L10: 1.7196435 | M10: 0.95187719 | N10: 3.1066756 | O10: 0.072405875 | P10: OR
A11: smoking_dose | B11: 2005-2006 | C11: M2 | D11: flu | E11: cpd_1_9 | F11: cpd_1_9_vs_never | G11: M1+poverty_ratio+education | H11: 3215 | I11: 334 | J11: 16 | K11: 166 | L11: 0.86758595 | M11: 0.44032347 | N11: 1.7094373 | O11: 0.68144286 | P11: OR
A12: smoking_dose | B12: 2005-2006 | C12: M2 | D12: flu | E12: cpd_10_19 | F12: cpd_10_19_vs_never | G12: M1+poverty_ratio+education | H12: 3215 | I12: 259 | J12: 14 | K12: 166 | L12: 1.2991102 | M12: 0.64781813 | N12: 2.6051867 | O12: 0.46106205 | P12: OR
A13: smoking_dose | B13: 2005-2006 | C13: M2 | D13: flu | E13: cpd_20p | F13: cpd_20p_vs_never | G13: M1+poverty_ratio+education | H13: 3215 | I13: 344 | J13: 27 | K13: 166 | L13: 1.5745794 | M13: 0.86816408 | N13: 2.8557968 | O13: 0.13502426 | P13: OR
A14: smoking_status | B14: 2007-2008 | C14: M1 | D14: flu | E14: former | F14: former_vs_never | G14: age+sex+race(+cycle) | H14: 5223 | I14: 1331 | J14: 59 | K14: 238 | L14: 1.1907857 | M14: 0.76824545 | N14: 1.8457261 | O14: 0.43485396 | P14: OR
A15: smoking_status | B15: 2007-2008 | C15: M1 | D15: flu | E15: current | F15: current_vs_never | G15: age+sex+race(+cycle) | H15: 5223 | I15: 1172 | J15: 58 | K15: 238 | L15: 1.3887699 | M15: 0.9083648 | N15: 2.1232459 | O15: 0.12945016 | P15: OR
... A83: smoking_dose | B83: Pooled_2005_2018 | C83: M2 | D83: flu | E83: cpd_20p | F83: cpd_20p_vs_never | G83: M1+poverty_ratio+education | H83: 26802 | I83: 2033 | J83: 109 | K83: 1137 | L83: 1.6131742 | M83: 1.2131307 | N83: 2.1451365 | O83: 0.0010064891 | P83: OR
A85: Note: Survey-weighted logistic regression examined self-reported recent flu, pneumonia or ear infection in the past 30 days (HSQ520; a composite item, not influenza-like illness). M1 adjusted for age, sex, race/ethnicity and cycle; M2 additionally adjusted for poverty ratio and education. Current smokers were categorized as 1–9, 10–19 or at least 20 cigarettes per day. Models used MEC examination weights divided by the number of pooled cycles and HC1 robust standard errors; strata and PSU were not modelled, so standard errors may be understated. OR, odds ratio; CI, confidence interval; MEC, mobile examination center; NHANES, National Health and Nutrition Examination Survey.

Sheet Supplementary Table 21
A1: Supplementary Table 21. Doctor-diagnosed depression, perceived stress, smoking and influenza vaccination in KNHANES 2016–2019.
A3: exposure | B3: level | C3: model | D3: cycle | E3: adjustment | F3: estimate | G3: ci_lo | H3: ci_hi | I3: p | J3: n | K3: events | L3: exposed
A4: dep_dx | B4: 1 | C4: M1 | D4: 2016 | E4: age+sex(+cycle) | F4: 1.2176692 | G4: 0.90446512 | H4: 1.6393317 | I4: 0.19425027 | J4: 5831 | K4: 2601 | L4: 276
A5: dep_dx | B5: 1 | C5: M1 | D5: 2017 | E5: age+sex(+cycle) | F5: 1.0768971 | G5: 0.77640097 | H5: 1.4936964 | I5: 0.65717923 | J5: 5839 | K5: 2576 | L5: 246
A6: dep_dx | B6: 1 | C6: M1 | D6: 2018 | E6: age+sex(+cycle) | F6: 1.2377789 | G6: 0.91112602 | H6: 1.681542 | I6: 0.17238563 | J6: 5980 | K6: 2573 | L6: 277
A7: dep_dx | B7: 1 | C7: M1 | D7: 2019 | E7: age+sex(+cycle) | F7: 1.5199429 | G7: 1.1240305 | H7: 2.0553059 | I7: 0.0065400874 | J7: 5925 | K7: 2835 | L7: 288
A8: dep_dx | B8: 1 | C8: M1 | D8: Pooled | E8: age+sex(+cycle) | F8: 1.2683016 | G8: 1.0874612 | H8: 1.479215 | I8: 0.0024598852 | J8: 23575 | K8: 10585 | L8: 1087
A9: dep_dx | B9: 1 | C9: M2 | D9: 2016 | E9: M1+income+education+marital | F9: 1.1673461 | G9: 0.86115556 | H9: 1.582405 | I9: 0.31881157 | J9: 5831 | K9: 2601 | L9: 276
A10: dep_dx | B10: 1 | C10: M2 | D10: 2017 | E10: M1+income+education+marital | F10: 1.0886827 | G10: 0.77651899 | H10: 1.5263374 | I10: 0.62211907 | J10: 5839 | K10: 2576 | L10: 246
A11: dep_dx | B11: 1 | C11: M2 | D11: 2018 | E11: M1+income+education+marital | F11: 1.2645138 | G11: 0.92469589 | H11: 1.729212 | I11: 0.14164683 | J11: 5980 | K11: 2573 | L11: 277
A12: dep_dx | B12: 1 | C12: M2 | D12: 2019 | E12: M1+income+education+marital | F12: 1.51494 | G12: 1.1132363 | H12: 2.0615958 | I12: 0.0082331513 | J12: 5925 | K12: 2835 | L12: 288
A13: dep_dx | B13: 1 | C13: M2 | D13: Pooled | E13: M1+income+education+marital | F13: 1.2653468 | G13: 1.0807731 | H13: 1.4814419 | I13: 0.0034384911 | J13: 23575 | K13: 10585 | L13: 1087
A14: smoke | B14: current | C14: M1 | D14: 2016 | E14: age+sex(+cycle) | F14: 0.60007007 | G14: 0.47589318 | H14: 0.75664899 | I14: 1.5797447e-05 | J14: 5802 | K14: 2581 | L14: 2282
A15: smoke | B15: former | C15: M1 | D15: 2016 | E15: age+sex(+cycle) | F15: 0.85097448 | G15: 0.68410042 | H15: 1.0585545 | I15: 0.14733557 | J15: 5802 | K15: 2581 | L15: 2282
... A43: stress | B43: 1 | C43: M2 | D43: Pooled | E43: M1+income+education+marital | F43: 1.0077577 | G43: 0.9317798 | H43: 1.089931 | I43: 0.84678297 | J43: 23502 | K43: 10538 | L43: 6255
A45: Note: The outcome was self-reported influenza vaccination (BH9_11), not influenza infection. M1 adjusted for age, sex and year; M2 additionally adjusted for income, education and marital status. Survey-weighted logistic models used examination weights divided by four and HC1 robust standard errors; strata and PSU were not modelled, so standard errors may be understated. OR, odds ratio; CI, confidence interval; KNHANES, Korea National Health and Nutrition Examination Survey.
